Workbook

Sheet Introduction
B1: Level 1 — Unit Test | Test Case Specification Template
B2: xUnit + Moq + FluentAssertions + Coverlet (backend .NET 8) · Vitest + React Testing Library + MSW (frontend TypeScript) · EF Core InMemory cho service inject ApplicationDbContext · Mock IClock/ITimeProvider cho mọi test phụ thuộc thời gian
B4: 🎯 Purpose — What does this test level verify?
B5: Verify that a single method or function produces the correct output for a given input — in complete isolation from all external dependencies. Key question: 'Does this method's logic work correctly?'
B7: ✅ In Scope
B8: • One class under test per sheet • One method per block within the sheet • All dependencies (DB, queue, external APIs) replaced by mocks • Domain logic: state machine transitions, business rule enforcement, boundary value validation, error handling paths
B10: ❌ Out of Scope
B11: • Database read/write (→ L2) • Message broker events (→ L2) • HTTP layer and API contracts (→ L3) • Browser UI rendering (→ L4) • Integration between two real components (→ L2)
B13: 🔬 Coverage Techniques
B14: Branch Coverage (BC): Every if/switch/ternary must be tested TRUE and FALSE. → Minimum: one test per branch direction. Condition Coverage (CC): For compound conditions (A && B), each sub-condition must be tested TRUE and FALSE independently. → Use when method contains && or || operators. Equivalence Partitioning (EP): Divide input domain into groups the system treats identically. Test one representative value per group. → Groups: valid range / below minimum / above maximum / null / wrong type. Boundary Value Analysis (BVA): Test at the exact edges of each partition. → Test points: min, min-1, max, max+1, and the default value. State Transition: Each valid transition (source state + event → target state) and each invalid transition (must throw exception) gets its own test.
B16: 🛠️ Primary Tool
B17: xUnit + Moq + FluentAssertions + Coverlet (backend .NET 8) · Vitest + React Testing Library + MSW (frontend TypeScript) · EF Core InMemory cho service inject ApplicationDbContext · Mock IClock/ITimeProvider cho mọi test phụ thuộc thời gian
B19: 📋 Column Definitions — How to fill each column
B20: Test ID | C20: Format: L1-[ClassName abbr]-[NN] Example: L1-SM-01, L1-BR-03, L1-BV-06 Numbering resets per block.
B21: Coverage Technique | C21: Which technique generated this test case. Values: BC-TRUE, BC-FALSE, CC, EP-Valid, EP-Invalid, BVA-Min, BVA-Max, BVA-Min-1, BVA-Max+1, State-Valid, State-Invalid, Guard-TRUE, Guard-FALSE
B22: Covers (Decision/Condition) | C22: The specific branch, condition, or partition this test exercises. Example: 'webhookSignatureValid = FALSE' Example: 'quantity partition: above maximum (> 10)' Example: 'transition: Processing + DEFECT_REPORTED → ManualReview'
B23: SRS Reference | C23: The SRS element this test traces to. Format: AC-xx | NAC-xx | BV-xx | DC-xx | BR-xx Example: BR-04, BV-02a, DC-02, NAC-03c
B24: Priority | C24: P1 Critical — must pass before release P2 High — should pass P3 Medium — nice to have
B25: Given (Precondition / Mock Setup) | C25: System state before the method is called. List each mock explicitly: _repoMock.Setup(r => r.FindById("X")).Returns(order) _svcMock.Setup(s => s.Check()).Returns(true)
B26: When (Input / Act) | C26: The exact method call being tested. Format: methodName(param1, param2) Include parameter values explicitly. For [Theory]+[InlineData]: list all input rows.
B27: Then (Expected Output / Assert) | C27: What must be true after the call. Cover ALL of: • Return value or exception thrown • Mock interactions verified (called / never called) • Side effects (state changes, events published) • For exceptions: message content
B28: Negative? | C28: Yes = test expects an exception or rejection. No = test expects success.
B29: Status | C29: Not Run / Pass / Fail / Blocked / Skip Dropdown — updated after each test run.
B30: Defect ID | C30: Issue tracker reference when Status = Fail. Example: GH-142
B31: Notes | C31: Optional: test data file, known limitation, or why this case was added.
B33: 📝 How to Fill — Step by step
B34: 1. Identify the CLASS under test → create one sheet per class.
B35: 2. Identify each METHOD in the class → create one block per method within the sheet.
B36: 3. For each method, list all decision points (if/switch/ternary) → write BC-TRUE and BC-FALSE test for each.
B37: 4. Check for compound conditions (&&, ||) → add CC tests for each sub-condition.
B38: 5. Identify numeric parameters → apply BVA: test min, min-1, max, max+1, default.
B39: 6. Identify categorical parameters (enum, status) → apply EP: one test per partition.
B40: 7. For state machine methods → one test per row in SRS Part 4.4 state transition table.
B41: 8. For every NAC-xx in SRS → write a Negative test (Negative? = Yes).
B42: 9. Fill Coverage Technique and Covers columns to make coverage traceable.
B43: 10. Run tests → update Status column → add Defect ID if Fail.
B45: 🎨 Priority & Status Legend
B46: P1 — Critical | C46: Must pass before any release. Blocking.
B47: P2 — High | C47: Should pass. Non-blocking but important.
B48: P3 — Medium | C48: Nice to have in this cycle.
B50: Not Run
B51: Pass
B52: Fail
B53: Blocked
B54: Skip

Sheet TestCase List
A1: TestCase List | L1 Unit Test index — 390 test case truy vết SRS | v3.1
A3: Total test cases | B3: =COUNTA(A6:A794) -> 391 | C3: P1 | D3: =COUNTIF(E6:E794,"P1") -> 279 | E3: P2 | F3: =COUNTIF(E6:E794,"P2") -> 85 | G3: P3 | H3: =COUNTIF(E6:E794,"P3") -> 26
A4: Negative tests | B4: =COUNTIF(F6:F794,"Yes") -> 169 | C4: Pass | D4: =COUNTIF(G6:G794,"Pass") -> 384 | E4: Fail | F4: =COUNTIF(G6:G794,"Fail") -> 3 | G4: Not Run | H4: =COUNTIF(G6:G794,"Not Run") -> 0
A6: Test ID | B6: Class (Sheet) | C6: Method / Block | D6: SRS Reference | E6: Priority | F6: Negative? | G6: Status (live link) | H6: Defect ID (live link) | I6: Fix Status (live link)
A7: L1-AUTH-01 | B7: AuthService | C7: RegisterAsync() | D7: FT-01 NAC-01; BR-023 | E7: P1 | F7: Yes | G7: =AuthService!J6 -> Pass | H7: =AuthService!K6 | I7: =AuthService!M6
A8: L1-AUTH-02 | B8: AuthService | C8: RegisterAsync() | D8: FT-01 AC-02; BR-023; NFR-SEC02 | E8: P1 | F8: No | G8: =AuthService!J7 -> Pass | H8: =AuthService!K7 | I8: =AuthService!M7
A9: L1-AUTH-03 | B9: AuthService | C9: RegisterAsync() | D9: FT-01 NAC-01; BR-023 | E9: P2 | F9: Yes | G9: =AuthService!J8 -> Pass | H9: =AuthService!K8 | I9: =AuthService!M8
A10: L1-AUTH-04 | B10: AuthService | C10: VerifyOtpAsync() | D10: FT-01 NAC-02; BV-02; BR-024 | E10: P1 | F10: Yes | G10: =AuthService!J10 -> Pass | H10: =AuthService!K10 | I10: =AuthService!M10
A11: L1-AUTH-05 | B11: AuthService | C11: VerifyOtpAsync() | D11: FT-01 NAC-02; BV-02; BR-024 | E11: P2 | F11: Yes | G11: =AuthService!J11 -> Pass | H11: =AuthService!K11 | I11: =AuthService!M11
A12: L1-AUTH-06 | B12: AuthService | C12: VerifyOtpAsync() | D12: FT-01 AC-04; BV-02; BR-024 | E12: P1 | F12: No | G12: =AuthService!J12 -> Pass | H12: =AuthService!K12 | I12: =AuthService!M12
A13: L1-AUTH-07 | B13: AuthService | C13: LoginAsync() | D13: NFR-SEC02; NFR-SEC03 | E13: P1 | F13: No | G13: =AuthService!J14 -> Pass | H13: =AuthService!K14 | I13: =AuthService!M14
A14: L1-AUTH-08 | B14: AuthService | C14: LoginAsync() | D14: NFR-SEC02 | E14: P1 | F14: Yes | G14: =AuthService!J15 -> Pass | H14: =AuthService!K15 | I14: =AuthService!M15
A15: L1-AUTH-09 | B15: AuthService | C15: LoginAsync() | D15: NFR-SEC02 | E15: P2 | F15: Yes | G15: =AuthService!J16 -> Pass | H15: =AuthService!K16 | I15: =AuthService!M16
A16: L1-AUTH-10 | B16: AuthService | C16: LoginWithGoogleAsync() | D16: FT-01 AC-02; FT-04 AC-02; BR-002; BR-023 | E16: P2 | F16: No | G16: =AuthService!J18 -> Pass | H16: =AuthService!K18 | I16: =AuthService!M18 -> ✅ ĐÃ FIX AuthService.cs:278 dùng IGoogleTokenValidator (DI) thay vì static call nên mock được; logic auto-create + AutoAssignCustomerAsync đúng (278-320).
A17: L1-AUTH-11 | B17: AuthService | C17: LoginWithGoogleAsync() | D17: FT-01 AC-02; NAC-01; BR-023 | E17: P2 | F17: No | G17: =AuthService!J19 -> Pass | H17: =AuthService!K19 | I17: =AuthService!M19 -> ✅ ĐÃ FIX Cùng cơ chế DI ở trên; nhánh user đã tồn tại (286-299) không gọi AddAsync.
A18: L1-AUTH-12 | B18: AuthService | C18: RefreshTokenAsync() | D18: NFR-SEC02 | E18: P1 | F18: No | G18: =AuthService!J21 -> Pass | H18: =AuthService!K21 | I18: =AuthService!M21
A19: L1-AUTH-13 | B19: AuthService | C19: RefreshTokenAsync() | D19: NFR-SEC02 | E19: P1 | F19: Yes | G19: =AuthService!J22 -> Pass | H19: =AuthService!K22 | I19: =AuthService!M22
A20: L1-AUTH-14 | B20: AuthService | C20: ResetPasswordAsync() / LogoutAsync() | D20: NFR-SEC02 | E20: P1 | F20: Yes | G20: =AuthService!J24 -> Pass | H20: =AuthService!K24 | I20: =AuthService!M24
A21: L1-AUTH-15 | B21: AuthService | C21: ResetPasswordAsync() / LogoutAsync() | D21: NFR-SEC02 | E21: P1 | F21: No | G21: =AuthService!J25 -> Pass | H21: =AuthService!K25 | I21: =AuthService!M25
A22: L1-AUTH-16 | B22: AuthService | C22: ResetPasswordAsync() / LogoutAsync() | D22: NFR-SEC02 | E22: P2 | F22: No | G22: =AuthService!J26 -> Pass | H22: =AuthService!K26 | I22: =AuthService!M26
A23: L1-AUTH-17 | B23: AuthService | C23: Xác thực SĐT qua SMS | D23: FT-01 AC-04; BR-024; NFR-SEC04 | E23: P1 | F23: No | G23: =AuthService!J28 -> Pass | H23: =AuthService!K28 | I23: =AuthService!M28 -> ✅ ĐÃ FIX AuthService.cs:504-505 lưu HASH (BCrypt) thay vì OTP thô; SendSmsAsync gọi đúng 1 lần (517).
A24: L1-AUTH-18 | B24: AuthService | C24: Xác thực SĐT qua SMS | D24: FT-01 BV-02; NAC-02 | E24: P1 | F24: Yes | G24: =AuthService!J29 -> Pass | H24: =AuthService!K29 | I24: =AuthService!M29 -> ✅ ĐÃ FIX AuthService.cs:486-493 chặn resend trước 60s, SMS không được gọi.
A25: L1-AUTH-19 | B25: AuthService | C25: Xác thực SĐT qua SMS | D25: FT-01 BV-02 | E25: P1 | F25: No | G25: =AuthService!J30 -> Pass | H25: =AuthService!K30 | I25: =AuthService!M30 -> ✅ Pass (không đổi)
A26: L1-AUTH-20 | B26: AuthService | C26: Xác thực SĐT qua SMS | D26: FT-01 BV-02; NAC-02; BR-024 | E26: P1 | F26: Yes | G26: =AuthService!J31 -> Pass | H26: =AuthService!K31 | I26: =AuthService!M31 -> ⚠ FIX MỘT PHẦN Giới hạn 5 lần/30 phút đã có (495-502) nhưng KHÔNG có giới hạn 10 lần/ngày cho OTP điện thoại (User.cs thiếu field ngày cho Phone OTP).
A27: L1-AUTH-21 | B27: AuthService | C27: Xác thực SĐT qua SMS | D27: FT-01 AC-04; BV-02 | E27: P1 | F27: No | G27: =AuthService!J32 -> Pass | H27: =AuthService!K32 | I27: =AuthService!M32 -> ✅ Pass (không đổi)
A28: L1-AUTH-22 | B28: AuthService | C28: Xác thực SĐT qua SMS | D28: FT-01 BV-02; NAC-02 | E28: P1 | F28: Yes | G28: =AuthService!J33 -> Pass | H28: =AuthService!K33 | I28: =AuthService!M33 -> ✅ Pass (không đổi)
A29: L1-AUTH-23 | B29: AuthService | C29: Xác thực SĐT qua SMS | D29: FT-01 BV-02; NAC-02 | E29: P1 | F29: Yes | G29: =AuthService!J34 -> Pass | H29: =AuthService!K34 | I29: =AuthService!M34 -> ✅ ĐÃ FIX AuthService.cs:530-539 khoá sau 5 lần sai, trả OTP_ATTEMPT_LIMIT_REACHED ở lần 6.
A30: L1-AUTH-24 | B30: AuthService | C30: Xác thực SĐT qua SMS | D30: FT-01 AC-04; BR-024 | E30: P1 | F30: No | G30: =AuthService!J35 -> Pass | H30: =AuthService!K35 | I30: =AuthService!M35 -> ✅ Pass (không đổi)
A31: L1-AUTH-25 | B31: AuthService | C31: Xác thực SĐT qua SMS | D31: FT-01 AC-02 | E31: P2 | F31: No | G31: =AuthService!J36 -> Pass | H31: =AuthService!K36 | I31: =AuthService!M36 -> ✅ Pass (không đổi)
A32: L1-AUTH-26 | B32: AuthService | C32: Gửi lại OTP qua email | D32: FT-01 NAC-02; BR-024 | E32: P1 | F32: Yes | G32: =AuthService!J41 -> Pass | H32: =AuthService!K41 | I32: =AuthService!M41 -> ✅ ĐÃ FIX ResendEmailOtpAsync (169-170) trả thông điệp CHUNG cho email không tồn tại, không gọi emailService.
A33: L1-AUTH-27 | B33: AuthService | C33: Gửi lại OTP qua email | D33: FT-01 AC-04; NAC-02 | E33: P1 | F33: Yes | G33: =AuthService!J42 -> Pass | H33: =AuthService!K42 | I33: =AuthService!M42 -> ✅ Pass (không đổi)
A34: L1-AUTH-28 | B34: AuthService | C34: Gửi lại OTP qua email | D34: FT-01 AC-04; BV-02; BR-024 | E34: P1 | F34: No | G34: =AuthService!J43 -> Pass | H34: =AuthService!K43 | I34: =AuthService!M43 -> ⚠ FIX MỘT PHẦN OTP mới + hash + gửi đúng 1 lần OK, nhưng hạn dùng const cứng EmailOtpValidityMinutes=5 (dòng 155), KHÔNG đọc từ SystemConfig OTP_EXPIRE_MINUTES.
A35: L1-AUTH-29 | B35: AuthService | C35: Gửi lại OTP qua email | D35: FT-01 BV-02; BR-024 | E35: P1 | F35: Yes | G35: =AuthService!J44 -> Pass | H35: =AuthService!K44 | I35: =AuthService!M44 -> ⚠ FIX MỘT PHẦN Hành vi throttle 59/60/61s đúng nhưng ngưỡng là const cứng EmailOtpResendCooldownSeconds=60 (156), không đọc SystemConfig OTP_RESEND_SECONDS.
A36: L1-AUTH-30 | B36: AuthService | C36: Gửi lại OTP qua email | D36: FT-01 BV-02; BR-024 | E36: P1 | F36: Yes | G36: =AuthService!J45 -> Pass | H36: =AuthService!K45 | I36: =AuthService!M45 -> ⚠ FIX MỘT PHẦN Chặn đúng ở lần 6/30 phút nhưng giới hạn là const cứng EmailOtpMaxSendsPerWindow=5 (157), không đọc SystemConfig OTP_MAX_ATTEMPTS.
A37: L1-AUTH-31 | B37: AuthService | C37: Gửi lại OTP qua email | D37: FT-01 BV-02; BR-024 | E37: P1 | F37: Yes | G37: =AuthService!J46 -> Pass | H37: =AuthService!K46 | I37: =AuthService!M46 -> ⚠ FIX MỘT PHẦN Chặn đúng ở lần 11/ngày nhưng giới hạn là const cứng EmailOtpMaxSendsPerDay=10 (159), không đọc SystemConfig.
A38: L1-AUTH-32 | B38: AuthService | C38: Gửi lại OTP qua email | D38: NFR-SEC02; FT-01 NAC-02 | E38: P1 | F38: Yes | G38: =AuthService!J47 -> Pass | H38: =AuthService!K47 | I38: =AuthService!M47 -> ✅ Pass (không đổi)
A39: L1-AUTH-33 | B39: AuthService | C39: Gửi lại OTP qua email | D39: NFR-SEC02 | E39: P1 | F39: No | G39: =AuthService!J48 -> Pass | H39: =AuthService!K48 | I39: =AuthService!M48 -> ✅ Pass (không đổi)
A40: L1-CART-01 | B40: CartService | C40: GetCartAsync() | D40: FT-01 AC-05; BR-025 | E40: P1 | F40: No | G40: =CartService!J6 -> Pass | H40: =CartService!K6 | I40: =CartService!M6 -> ✅ Pass (không đổi)
A41: L1-CART-02 | B41: CartService | C41: GetCartAsync() | D41: FT-01 AC-05 | E41: P2 | F41: No | G41: =CartService!J7 -> Pass | H41: =CartService!K7 | I41: =CartService!M7 -> ✅ Pass (không đổi)
A42: L1-CART-03 | B42: CartService | C42: GetCartAsync() | D42: FT-01 BV-01; NAC-03; BR-025 | E42: P1 | F42: No | G42: =CartService!J8 -> Pass | H42: =CartService!K8 | I42: =CartService!M8 -> ✅ Pass (không đổi)
A43: L1-CART-04 | B43: CartService | C43: GetCartAsync() | D43: FT-01 BV-01; BR-025 | E43: P1 | F43: No | G43: =CartService!J9 -> Pass | H43: =CartService!K9 | I43: =CartService!M9 -> ✅ Pass (không đổi)
A44: L1-CART-05 | B44: CartService | C44: AddItemToCartAsync() | D44: FT-01 AC-05; FT-02 AC-02; BR-005 | E44: P1 | F44: No | G44: =CartService!J11 -> Pass | H44: =CartService!K11 | I44: =CartService!M11 -> ✅ Pass (không đổi)
A45: L1-CART-06 | B45: CartService | C45: AddItemToCartAsync() | D45: FT-01 AC-05 | E45: P1 | F45: No | G45: =CartService!J12 -> Pass | H45: =CartService!K12 | I45: =CartService!M12 -> ✅ Pass (không đổi)
A46: L1-CART-07 | B46: CartService | C46: AddItemToCartAsync() | D46: FT-01 AC-05 | E46: P1 | F46: Yes | G46: =CartService!J13 -> Pass | H46: =CartService!K13 | I46: =CartService!M13 -> ✅ Pass (không đổi)
A47: L1-CART-08 | B47: CartService | C47: AddItemToCartAsync() | D47: FT-01 NAC-04; BR-047 | E47: P1 | F47: Yes | G47: =CartService!J14 -> Pass | H47: =CartService!K14 | I47: =CartService!M14 -> ✅ Pass (không đổi)
A48: L1-CART-09 | B48: CartService | C48: UpdateCartItemAsync() / RemoveItemFromCartAsync() / ClearCartAsync() | D48: FT-01 NAC-05; NFR-SEC03 | E48: P1 | F48: Yes | G48: =CartService!J16 -> Pass | H48: =CartService!K16 | I48: =CartService!M16 -> ✅ Pass (không đổi)
A49: L1-CART-10 | B49: CartService | C49: UpdateCartItemAsync() / RemoveItemFromCartAsync() / ClearCartAsync() | D49: FT-01 AC-05 | E49: P2 | F49: No | G49: =CartService!J17 -> Pass | H49: =CartService!K17 | I49: =CartService!M17 -> ✅ Pass (không đổi)
A50: L1-PROD-01 | B50: ProductService | C50: GetProductsAsync() | D50: FT-01 AC-01 | E50: P2 | F50: No | G50: =ProductService!J6 -> Pass | H50: =ProductService!K6 | I50: =ProductService!M6
A51: L1-PROD-02 | B51: ProductService | C51: GetProductsAsync() | D51: FT-01 AC-01 | E51: P2 | F51: No | G51: =ProductService!J7 -> Pass | H51: =ProductService!K7 | I51: =ProductService!M7
A52: L1-PROD-03 | B52: ProductService | C52: GetProductsAsync() | D52: FT-01 AC-01; NAC-04; BR-047 | E52: P1 | F52: No | G52: =ProductService!J8 -> Pass | H52: =ProductService!K8 | I52: =ProductService!M8
A53: L1-PROD-04 | B53: ProductService | C53: GetProductsAsync() | D53: FT-01 AC-01 | E53: P3 | F53: No | G53: =ProductService!J9 -> Pass | H53: =ProductService!K9 | I53: =ProductService!M9
A54: L1-PROD-05 | B54: ProductService | C54: GetProductByIdAsync() | D54: FT-01 AC-01 | E54: P2 | F54: No | G54: =ProductService!J11 -> Pass | H54: =ProductService!K11 | I54: =ProductService!M11
A55: L1-ORD-01 | B55: OrderService | C55: GetCheckoutSummaryAsync() — tiered pricing | D55: FT-02 AC-01; BV-01; BR-006 | E55: P1 | F55: No | G55: =OrderService!J6 -> Pass | H55: =OrderService!K6 | I55: =OrderService!M6 -> ✅ Pass (không đổi)
A56: L1-ORD-02 | B56: OrderService | C56: GetCheckoutSummaryAsync() — tiered pricing | D56: FT-02 AC-01; BV-01; BR-006 | E56: P1 | F56: No | G56: =OrderService!J7 -> Pass | H56: =OrderService!K7 | I56: =OrderService!M7 -> ✅ Pass (không đổi)
A57: L1-ORD-03 | B57: OrderService | C57: GetCheckoutSummaryAsync() — tiered pricing | D57: FT-02 AC-01; BV-01; BR-006 | E57: P1 | F57: No | G57: =OrderService!J8 -> Pass | H57: =OrderService!K8 | I57: =OrderService!M8 -> ✅ Pass (không đổi)
A58: L1-ORD-04 | B58: OrderService | C58: GetCheckoutSummaryAsync() — tiered pricing | D58: FT-02 AC-01; AC-05; BV-01; BR-026 | E58: P1 | F58: No | G58: =OrderService!J9 -> Pass | H58: =OrderService!K9 | I58: =OrderService!M9 -> ✅ ĐÃ FIX [🟢 ĐÃ FIX HOÀN TOÀN — test unit viết lại, bỏ Skip, PASS thật (07/08/2026)] GH-13 đã fix ở code (Quotation/QuotationVersion.ProposedTotal, không phải SavedB2BPriceSnapshot như giả định gốc). Đã viết lại L1_ORD_04_Checkout_100M_WithAcceptedQuotation_NegotiatedPriceApplied (PASS) + thêm L1_ORD_04b (báo giá hết hạn vẫn bị chặn, PASS) trong OrderServiceTests.cs, bỏ [Fact(Skip=...)].
A59: L1-ORD-05 | B59: OrderService | C59: GetCheckoutSummaryAsync() — tiered pricing | D59: FT-02 AC-03; BV-01; BR-026 | E59: P1 | F59: No | G59: =OrderService!J10 -> Pass | H59: =OrderService!K10 | I59: =OrderService!M10 -> ✅ Pass (không đổi)
A60: L1-ORD-06 | B60: OrderService | C60: GetCheckoutSummaryAsync() — tiered pricing | D60: FT-02 NAC-02; BV-01 | E60: P1 | F60: Yes | G60: =OrderService!J11 -> Pass | H60: =OrderService!K11 | I60: =OrderService!M11 -> ✅ Pass (không đổi)
A61: L1-ORD-07 | B61: OrderService | C61: PlaceOrderAsync() | D61: FT-01 AC-05; FT-03 AC-04; BR-030 | E61: P1 | F61: No | G61: =OrderService!J13 -> Pass | H61: =OrderService!K13 | I61: =OrderService!M13 -> ✅ Pass (không đổi)
A62: L1-ORD-08 | B62: OrderService | C62: PlaceOrderAsync() | D62: FT-01 AC-05 | E62: P1 | F62: Yes | G62: =OrderService!J14 -> Pass | H62: =OrderService!K14 | I62: =OrderService!M14 -> ✅ Pass (không đổi)
A63: L1-ORD-09 | B63: OrderService | C63: PlaceOrderAsync() | D63: FT-01 NAC-03; FT-02 NAC-03; BV-01; BR-025 | E63: P1 | F63: Yes | G63: =OrderService!J15 -> Pass | H63: =OrderService!K15 | I63: =OrderService!M15 -> ✅ ĐÃ FIX [🟢 ĐÃ FIX HOÀN TOÀN — test unit viết lại, bỏ Skip, PASS thật (07/08/2026)] GH-08 đã fix ở code (check hạn giữ giá TRƯỚC khi gọi CartService.GetCartAsync). Đã viết lại L1_ORD_09_PlaceOrder_PriceExpiredCart_Blocked (PASS) + thêm L1_ORD_09b (chưa hết hạn vẫn checkout được, PASS) trong OrderServiceTests.cs, bỏ [Fact(Skip=...)].
A64: L1-ORD-10 | B64: OrderService | C64: PlaceOrderAsync() | D64: FT-01 NAC-03; FT-03 AC-01; BR-008 | E64: P1 | F64: Yes | G64: =OrderService!J16 -> Pass | H64: =OrderService!K16 | I64: =OrderService!M16 -> ✅ Pass (không đổi)
A65: L1-ORD-11 | B65: OrderService | C65: PlaceOrderAsync() | D65: FT-02 NAC-01; BR-005 | E65: P1 | F65: Yes | G65: =OrderService!J17 -> Pass | H65: =OrderService!K17 | I65: =OrderService!M17 -> ✅ Pass (không đổi)
A66: L1-ORD-12 | B66: OrderService | C66: GenerateSePayQrAsync() | D66: FT-03 AC-01; BV-01; BR-008 | E66: P1 | F66: No | G66: =OrderService!J19 -> Pass | H66: =OrderService!K19 | I66: =OrderService!M19 -> ✅ Pass (không đổi)
A67: L1-ORD-13 | B67: OrderService | C67: GenerateSePayQrAsync() | D67: FT-03 NAC-02; BR-016; BR-029 | E67: P1 | F67: Yes | G67: =OrderService!J20 -> Pass | H67: =OrderService!K20 | I67: =OrderService!M20 -> ✅ ĐÃ FIX OrderService.cs:296-297 throw nếu PaymentStatus=Paid trước khi sinh QR mới -> map 409.
A68: L1-ORD-14 | B68: OrderService | C68: ProcessSePayWebhookAsync() | D68: FT-03 AC-02; BV-01; BR-009; NFR-SEC05 | E68: P1 | F68: No | G68: =OrderService!J22 -> Pass | H68: =OrderService!K22 | I68: =OrderService!M22 -> ✅ Pass (không đổi)
A69: L1-ORD-15 | B69: OrderService | C69: ProcessSePayWebhookAsync() | D69: FT-03 NAC-01; NFR-SEC05 | E69: P1 | F69: Yes | G69: =OrderService!J23 -> Pass | H69: =OrderService!K23 | I69: =OrderService!M23 -> ✅ Pass (không đổi)
A70: L1-ORD-16 | B70: OrderService | C70: ProcessSePayWebhookAsync() | D70: FT-03 NAC-01; BV-01 | E70: P1 | F70: Yes | G70: =OrderService!J24 -> Pass | H70: =OrderService!K24 | I70: =OrderService!M24 -> ✅ Pass (không đổi)
A71: L1-ORD-17 | B71: OrderService | C71: ProcessSePayWebhookAsync() | D71: FT-03 NAC-01; BV-01 | E71: P1 | F71: Yes | G71: =OrderService!J25 -> Pass | H71: =OrderService!K25 | I71: =OrderService!M25 -> ✅ Pass (không đổi)
A72: L1-ORD-18 | B72: OrderService | C72: ProcessSePayWebhookAsync() | D72: FT-03 NAC-02; BR-029 | E72: P1 | F72: No | G72: =OrderService!J26 -> Pass | H72: =OrderService!K26 | I72: =OrderService!M26 -> ✅ Pass (không đổi)
A73: L1-ORD-19 | B73: OrderService | C73: ProcessSePayWebhookAsync() | D73: FT-03 NAC-03; BV-01; BR-033 | E73: P1 | F73: Yes | G73: =OrderService!J27 -> Pass | H73: =OrderService!K27 | I73: =OrderService!M27 -> ✅ Pass (không đổi)
A74: L1-ORD-20 | B74: OrderService | C74: ConfirmOrderAsync() | D74: FT-05 AC-01; BR-011 | E74: P1 | F74: No | G74: =OrderService!J29 -> Pass | H74: =OrderService!K29 | I74: =OrderService!M29 -> ✅ Pass (không đổi)
A75: L1-ORD-21 | B75: OrderService | C75: ConfirmOrderAsync() | D75: FT-05 AC-01; NAC-05 | E75: P1 | F75: Yes | G75: =OrderService!J30 -> Pass | H75: =OrderService!K30 | I75: =OrderService!M30 -> ✅ Pass (không đổi)
A76: L1-ORD-22 | B76: OrderService | C76: PlaceDirectOrderAsync() — walk-in | D76: FT-01 AC-03; BR-030 | E76: P1 | F76: No | G76: =OrderService!J32 -> Pass | H76: =OrderService!K32 | I76: =OrderService!M32 -> ✅ Pass (không đổi)
A77: L1-ORD-23 | B77: OrderService | C77: PlaceDirectOrderAsync() — walk-in | D77: FT-05 NAC-01; BV-02; BR-032 | E77: P1 | F77: Yes | G77: =OrderService!J33 -> Pass | H77: =OrderService!K33 | I77: =OrderService!M33 -> ✅ Pass (không đổi)
A78: L1-ORD-24 | B78: OrderService | C78: PlaceDirectOrderAsync() — walk-in | D78: FT-01 AC-04; NAC-02; BR-030 | E78: P1 | F78: Yes | G78: =OrderService!J34 -> Pass | H78: =OrderService!K34 | I78: =OrderService!M34 -> ✅ ĐÃ FIX OrderService.cs:595-598 validate SĐT bằng regex ^0\d{9}$, throw nếu sai định dạng.
A79: L1-ORD-25 | B79: OrderService | C79: PlaceDirectOrderAsync() — walk-in | D79: FT-01 AC-05; BR-030 | E79: P1 | F79: Yes | G79: =OrderService!J35 -> Pass | H79: =OrderService!K35 | I79: =OrderService!M35 -> ✅ Pass (không đổi)
A80: L1-ORD-26 | B80: OrderService | C80: PlaceDirectOrderAsync() — walk-in | D80: FT-05 AC-02; BR-032; NFR-A05 | E80: P1 | F80: No | G80: =OrderService!J36 -> Pass | H80: =OrderService!K36 | I80: =OrderService!M36 -> ✅ Pass (không đổi)
A81: L1-ORD-27 | B81: OrderService | C81: PlaceDirectOrderAsync() — walk-in | D81: FT-05 BV-01; BR-032 | E81: P1 | F81: No | G81: =OrderService!J37 -> Pass | H81: =OrderService!K37 | I81: =OrderService!M37 -> ✅ Pass (không đổi)
A82: L1-ORD-28 | B82: OrderService | C82: RequestVatInvoiceAsync() | D82: (chờ xác nhận) FT-01 AC-03 | E82: P1 | F82: Yes | G82: =OrderService!J39 -> Pass | H82: =OrderService!K39 | I82: =OrderService!M39 -> ✅ Pass (không đổi)
A83: L1-ORD-29 | B83: OrderService | C83: RequestVatInvoiceAsync() | D83: (chờ xác nhận) FT-01 AC-03 | E83: P1 | F83: Yes | G83: =OrderService!J40 -> Pass | H83: =OrderService!K40 | I83: =OrderService!M40 -> ✅ Pass (không đổi)
A84: L1-ORD-30 | B84: OrderService | C84: RequestVatInvoiceAsync() | D84: (chờ xác nhận) FT-01 AC-03 | E84: P2 | F84: Yes | G84: =OrderService!J41 -> Pass | H84: =OrderService!K41 | I84: =OrderService!M41 -> ✅ Pass (không đổi)
A85: L1-ORD-31 | B85: OrderService | C85: GetOrderHistoryAsync() / GetOrderDetailForCustomerAsync() | D85: FT-01 NAC-05; NFR-SEC03 | E85: P1 | F85: Yes | G85: =OrderService!J43 -> Pass | H85: =OrderService!K43 | I85: =OrderService!M43 -> ✅ Pass (không đổi)
A86: L1-ORD-32 | B86: OrderService | C86: GetOrderHistoryAsync() / GetOrderDetailForCustomerAsync() | D86: FT-01 AC-05 | E86: P2 | F86: No | G86: =OrderService!J44 -> Pass | H86: =OrderService!K44 | I86: =OrderService!M44 -> ✅ Pass (không đổi)
A87: L1-ORD-33 | B87: OrderService | C87: RejectOrderAsync() / RequestCancelOrderAsync() / ProcessCancelRequestAsync() | D87: FT-08 AC-01; BR-017 | E87: P2 | F87: No | G87: =OrderService!J46 -> Pass | H87: =OrderService!K46 | I87: =OrderService!M46 -> ✅ Pass (không đổi)
A88: L1-ORD-34 | B88: OrderService | C88: RejectOrderAsync() / RequestCancelOrderAsync() / ProcessCancelRequestAsync() | D88: FT-08 AC-01 | E88: P2 | F88: Yes | G88: =OrderService!J47 -> Pass | H88: =OrderService!K47 | I88: =OrderService!M47 -> ✅ ĐÃ FIX OrderService.cs:1742-1745 throw nếu reason rỗng; lưu vào order.CancelReason (1765).
A89: L1-ORD-35 | B89: OrderService | C89: RejectOrderAsync() / RequestCancelOrderAsync() / ProcessCancelRequestAsync() | D89: FT-08 AC-01; BR-017 | E89: P2 | F89: No | G89: =OrderService!J48 -> Pass | H89: =OrderService!K48 | I89: =OrderService!M48 -> ✅ Pass (không đổi)
A90: L1-ORD-36 | B90: OrderService | C90: RejectOrderAsync() / RequestCancelOrderAsync() / ProcessCancelRequestAsync() | D90: FT-08 AC-01; NAC-05 | E90: P1 | F90: Yes | G90: =OrderService!J49 -> Pass | H90: =OrderService!K49 | I90: =OrderService!M49 -> ✅ Pass (không đổi)
A91: L1-ORD-37 | B91: OrderService | C91: RejectOrderAsync() / RequestCancelOrderAsync() / ProcessCancelRequestAsync() | D91: FT-08 AC-01; BR-017 | E91: P1 | F91: No | G91: =OrderService!J50 -> Pass | H91: =OrderService!K50 | I91: =OrderService!M50 -> ✅ Pass (không đổi)
A92: L1-ORD-38 | B92: OrderService | C92: ScheduleDeliveryAsync() | D92: FT-07 AC-01; BV-01; BR-037 | E92: P1 | F92: No | G92: =OrderService!J52 -> Pass | H92: =OrderService!K52 | I92: =OrderService!M52 -> ✅ Pass (không đổi)
A93: L1-ORD-39 | B93: OrderService | C93: ScheduleDeliveryAsync() | D93: FT-07 NAC-01; BV-01; BR-037 | E93: P1 | F93: Yes | G93: =OrderService!J53 -> Pass | H93: =OrderService!K53 | I93: =OrderService!M53 -> ✅ Pass (không đổi)
A94: L1-ORD-40 | B94: OrderService | C94: ScheduleDeliveryAsync() | D94: FT-07 BV-01; BR-037 | E94: P1 | F94: Yes | G94: =OrderService!J54 -> Pass | H94: =OrderService!K54 | I94: =OrderService!M54 -> ✅ Pass (không đổi)
A95: L1-ORD-41 | B95: OrderService | C95: ScheduleDeliveryAsync() | D95: FT-07 NAC-01; BV-01 | E95: P2 | F95: Yes | G95: =OrderService!J55 -> Pass | H95: =OrderService!K55 | I95: =OrderService!M55 -> ✅ Pass (không đổi)
A96: L1-ORD-42 | B96: OrderService | C96: RecordDeliveryResultAsync() | D96: FT-07 AC-04; BV-02; BR-039 | E96: P1 | F96: No | G96: =OrderService!J57 -> Pass | H96: =OrderService!K57 | I96: =OrderService!M57 -> ✅ Pass (không đổi)
A97: L1-ORD-43 | B97: OrderService | C97: RecordDeliveryResultAsync() | D97: FT-07 NAC-04; BR-016; BR-039 | E97: P1 | F97: Yes | G97: =OrderService!J58 -> Pass | H97: =OrderService!K58 | I97: =OrderService!M58 -> ✅ ĐÃ FIX OrderService.cs:2165-2166 throw nếu PaymentStatus=Paid và AmountCollected>0.
A98: L1-ORD-44 | B98: OrderService | C98: RecordDeliveryResultAsync() | D98: FT-07 NAC-03; BR-038 | E98: P1 | F98: Yes | G98: =OrderService!J59 -> Pass | H98: =OrderService!K59 | I98: =OrderService!M59 -> ✅ ĐÃ FIX OrderService.cs:2169-2170 bắt buộc RejectionReasonCode khi CustomerRejected=true; lưu ở 2268-2269.
A99: L1-ORD-45 | B99: OrderService | C99: RecordDeliveryResultAsync() | D99: FT-07 AC-05; BV-03; BR-040; FT-08 AC-05 | E99: P1 | F99: No | G99: =OrderService!J60 -> Pass | H99: =OrderService!K60 | I99: =OrderService!M60 -> ✅ Pass (không đổi)
A100: L1-ORD-46 | B100: OrderService | C100: RequestCancelPaidOrderAsync() / ApproveCancelAndCreateReplacementAsync() | D100: FT-08 AC-01; AC-02; BR-017; BR-041 | E100: P1 | F100: No | G100: =OrderService!J62 -> Pass | H100: =OrderService!K62 | I100: =OrderService!M62 -> ✅ Pass (không đổi)
A101: L1-ORD-47 | B101: OrderService | C101: RequestCancelPaidOrderAsync() / ApproveCancelAndCreateReplacementAsync() | D101: FT-08 NAC-05; NFR-SEC03 | E101: P1 | F101: Yes | G101: =OrderService!J63 -> Pass | H101: =OrderService!K63 | I101: =OrderService!M63 -> 🔒 CẦN L3 (không phải bug) ApproveCancelAndCreateReplacementAsync (2739-2860) không tự check role trong service, nhưng [Authorize(Roles="SalesManager,Admin")] ở DeliveryController.cs:124 đã chặn. Có test L3: VietTien.IntegrationTests/RoleGateTests.cs:21-42 (L1_ORD_47_...).
A102: L1-ORD-48 | B102: OrderService | C102: Đổi/trả hàng | D102: FT-08 AC-05; BR-019 | E102: P1 | F102: No | G102: =OrderService!J65 -> Pass | H102: =OrderService!K65 | I102: =OrderService!M65 -> ✅ Pass (không đổi)
...

Sheet AuthService
A1: AuthService | methods: RegisterAsync, VerifyOtpAsync, LoginAsync, LoginWithGoogleAsync, ForgotPasswordAsync, ResetPasswordAsync, RefreshTokenAsync, LogoutAsync, VerifyPhoneOtpAsync | Mock: IUnitOfWork, IJwtService, IEmailService, ISmsService, ISalesAllocationService
A2: HOW TO USE: (1) Đọc Introduction (2) Trace theo SRS v2 (Part 3 + RTW Sheet 3/6/7) (3) Cập nhật Status sau mỗi lần chạy dotnet test / vitest (4) Ghi Defect ID khi Fail
A4: Test ID | B4: Coverage Technique | C4: Covers (Decision/Condition) | D4: SRS Reference | E4: Priority | F4: Given (Precondition / Mock Setup) | G4: When (Input / Act) | H4: Then (Expected Output / Assert) | I4: Negative? | J4: Status | K4: Defect ID | L4: Notes | M4: Fix Status
A5: ▶ Block: RegisterAsync() | FT-01 SB-2 (account creation for cart flow); NFR-SEC03
A6: L1-AUTH-01 | B6: EP-Invalid | C6: Email already exists -> registration rejected | D6: FT-01 NAC-01; BR-023 | E6: P1 | F6: Mock: userRepo.EmailExistsAsync('a@x.com') -> true | G6: authService.RegisterAsync(dto{email='a@x.com'}) | H6: Success = false; Message indicates email in use userRepo.AddAsync() NEVER called emailService.SendOtpEmailAsync() NEVER called | I6: Yes | J6: Pass
A7: L1-AUTH-02 | B7: EP-Valid | C7: Valid registration -> user created, OTP email sent, password hashed | D7: FT-01 AC-02; BR-023; NFR-SEC02 | E7: P1 | F7: Mock: EmailExistsAsync -> false; PhoneExistsAsync -> false | G7: authService.RegisterAsync(validDto{password='P@ss123'}) | H7: Success = true userRepo.AddAsync() called once; saved PasswordHash != 'P@ss123' (BCrypt) emailService.SendOtpEmailAsync() called once with correct email | I7: No | J7: Pass
A8: L1-AUTH-03 | B8: EP-Invalid | C8: Phone number already exists -> rejected | D8: FT-01 NAC-01; BR-023 | E8: P2 | F8: Mock: EmailExistsAsync -> false; PhoneExistsAsync('0912345678') -> true | G8: authService.RegisterAsync(dto{phone='0912345678'}) | H8: Success = false userRepo.AddAsync() NEVER called | I8: Yes | J8: Pass
A9: ▶ Block: VerifyOtpAsync()
A10: L1-AUTH-04 | B10: EP-Invalid | C10: Wrong OTP code -> verification rejected | D10: FT-01 NAC-02; BV-02; BR-024 | E10: P1 | F10: User exists with stored OTP '123456' (not expired) | G10: authService.VerifyOtpAsync(dto{otp='999999'}) | H10: Success = false User.IsVerified remains false; no state change saved | I10: Yes | J10: Pass
A11: L1-AUTH-05 | B11: EP-Invalid | C11: Expired OTP -> verification rejected | D11: FT-01 NAC-02; BV-02; BR-024 | E11: P2 | F11: User exists; OTP created beyond configured expiry (mock IClock/time source) | G11: authService.VerifyOtpAsync(dto{otp='123456'}) | H11: Success = false; Message indicates expiry User.IsVerified remains false | I11: Yes | J11: Pass
A12: L1-AUTH-06 | B12: EP-Valid | C12: Correct OTP within window -> account verified | D12: FT-01 AC-04; BV-02; BR-024 | E12: P1 | F12: User exists with valid stored OTP '123456' | G12: authService.VerifyOtpAsync(dto{otp='123456'}) | H12: Success = true User.IsVerified = true; unitOfWork.SaveChangesAsync() called | I12: No | J12: Pass
A13: ▶ Block: LoginAsync() | NFR-SEC03, NFR-SEC04
A14: L1-AUTH-07 | B14: EP-Valid | C14: Valid credentials -> tokens issued | D14: NFR-SEC02; NFR-SEC03 | E14: P1 | F14: Mock: GetByEmailAsync -> verified user (BCrypt hash of 'P@ss123') jwtService.GenerateAccessToken -> 'jwt'; GenerateRefreshToken -> 'rt' | G14: authService.LoginAsync(dto{email, password='P@ss123'}) | H14: Success = true; Data.AccessToken = 'jwt'; Data.RefreshToken = 'rt' jwtService.GenerateAccessToken(user) called once Refresh token persisted on user record | I14: No | J14: Pass
A15: L1-AUTH-08 | B15: EP-Invalid | C15: Wrong password -> login rejected, no token | D15: NFR-SEC02 | E15: P1 | F15: Mock: GetByEmailAsync -> user with hash of 'P@ss123' | G15: authService.LoginAsync(dto{password='WRONG'}) | H15: Success = false jwtService.GenerateAccessToken() NEVER called Generic failure message (does not reveal which field is wrong) | I15: Yes | J15: Pass
A16: L1-AUTH-09 | B16: EP-Invalid | C16: Unknown email -> login rejected with generic message | D16: NFR-SEC02 | E16: P2 | F16: Mock: GetByEmailAsync -> null | G16: authService.LoginAsync(dto{email='ghost@x.com'}) | H16: Success = false; message identical wording to wrong-password case No token generated | I16: Yes | J16: Pass
A17: ▶ Block: LoginWithGoogleAsync()
A18: L1-AUTH-10 | B18: EP-Valid | C18: New Google account -> user auto-created and auto-assigned to Sales staff | D18: FT-01 AC-02; FT-04 AC-02; BR-002; BR-023 | E18: P2 | F18: Mock: GetByGoogleIdAsync -> null; GetByEmailAsync -> null | G18: authService.LoginWithGoogleAsync(dto{googleId,email}) | H18: Success = true; new user persisted salesAllocationService.AutoAssignCustomerAsync(userId) called once | I18: No | J18: Pass | L18: GoogleJsonWebSignature.ValidateAsync là static call ra Google — không mock được ở unit level, cần integration test (L2). | M18: ✅ ĐÃ FIX AuthService.cs:278 dùng IGoogleTokenValidator (DI) thay vì static call nên mock được; logic auto-create + AutoAssignCustomerAsync đúng (278-320).
A19: L1-AUTH-11 | B19: EP-Valid | C19: Existing Google account -> login without creating duplicate | D19: FT-01 AC-02; NAC-01; BR-023 | E19: P2 | F19: Mock: GetByGoogleIdAsync -> existing user | G19: authService.LoginWithGoogleAsync(dto) | H19: Success = true userRepo.AddAsync() NEVER called | I19: No | J19: Pass | L19: Google token validation không isolate được ở unit level. | M19: ✅ ĐÃ FIX Cùng cơ chế DI ở trên; nhánh user đã tồn tại (286-299) không gọi AddAsync.
A20: ▶ Block: RefreshTokenAsync() | NFR-SEC04
A21: L1-AUTH-12 | B21: EP-Valid | C21: Valid refresh token -> new access token, token rotated | D21: NFR-SEC02 | E21: P1 | F21: Mock: GetByRefreshTokenAsync('rt-old') -> user (token not expired) | G21: authService.RefreshTokenAsync(dto{refreshToken='rt-old'}) | H21: Success = true; new AccessToken returned User.RefreshToken updated to a NEW value != 'rt-old' (rotation) | I21: No | J21: Pass
A22: L1-AUTH-13 | B22: EP-Invalid | C22: Unknown/revoked refresh token -> rejected | D22: NFR-SEC02 | E22: P1 | F22: Mock: GetByRefreshTokenAsync('rt-x') -> null | G22: authService.RefreshTokenAsync(dto{refreshToken='rt-x'}) | H22: Success = false jwtService.GenerateAccessToken() NEVER called | I22: Yes | J22: Pass
A23: ▶ Block: ResetPasswordAsync() / LogoutAsync()
A24: L1-AUTH-14 | B24: EP-Invalid | C24: Invalid reset token -> password unchanged | D24: NFR-SEC02 | E24: P1 | F24: Mock: GetByResetTokenAsync('bad') -> null | G24: authService.ResetPasswordAsync(dto{token='bad', newPassword}) | H24: Success = false No user updated; SaveChangesAsync NEVER called | I24: Yes | J24: Pass
A25: L1-AUTH-15 | B25: EP-Valid | C25: Valid reset token -> new password stored as hash, token cleared | D25: NFR-SEC02 | E25: P1 | F25: Mock: GetByResetTokenAsync('tok') -> user | G25: authService.ResetPasswordAsync(dto{token='tok', newPassword='N3w!'}) | H25: Success = true PasswordHash != 'N3w!'; reset token cleared so it cannot be reused | I25: No | J25: Pass
A26: L1-AUTH-16 | B26: EP-Valid | C26: Logout -> refresh token revoked | D26: NFR-SEC02 | E26: P2 | F26: User exists with RefreshToken = 'rt' | G26: authService.LogoutAsync(userId) | H26: Success = true; User.RefreshToken cleared/null Subsequent RefreshTokenAsync('rt') would fail | I26: No | J26: Pass
A27: ▶ Block: ⊕ v2.1 — Xác thực SĐT qua SMS | RequestPhoneVerificationAsync, VerifyPhoneOtpAsync, CompleteProfileAsync | FT-01 AC-04; BV-02; BR-024
A28: L1-AUTH-17 | B28: EP-Valid | C28: Gửi OTP xác thực SĐT -> lưu HASH, gọi SMS 1 lần | D28: FT-01 AC-04; BR-024; NFR-SEC04 | E28: P1 | F28: User U1 đã verify email; mock ISmsService | G28: authService.RequestPhoneVerificationAsync(U1, dto{phone, purpose:'FIRST_ORDER'}) | H28: smsService.SendAsync gọi đúng 1 lần Giá trị lưu trong DB là HASH, không phải OTP thô OTP không xuất hiện trong log | I28: No | J28: Pass | M28: ✅ ĐÃ FIX AuthService.cs:504-505 lưu HASH (BCrypt) thay vì OTP thô; SendSmsAsync gọi đúng 1 lần (517).
A29: L1-AUTH-18 | B29: BVA-Min-1 | C29: Resend trước 60 giây -> từ chối | D29: FT-01 BV-02; NAC-02 | E29: P1 | F29: Lần gửi trước cách đây 59 giây (mock clock) | G29: authService.RequestPhoneVerificationAsync(U1, dto{phone}) | H29: Từ chối (OTP_RESEND_TOO_SOON); smsService KHÔNG được gọi | I29: Yes | J29: Pass | M29: ✅ ĐÃ FIX AuthService.cs:486-493 chặn resend trước 60s, SMS không được gọi.
A30: L1-AUTH-19 | B30: BVA-Min | C30: Resend đúng 60 giây -> cho phép | D30: FT-01 BV-02 | E30: P1 | F30: Lần gửi trước cách đây đúng 60 giây | G30: authService.RequestPhoneVerificationAsync(U1, dto{phone}) | H30: Gửi thành công; smsService gọi 1 lần | I30: No | J30: Pass | M30: ✅ Pass (không đổi)
A31: L1-AUTH-20 | B31: BVA-Max+1 | C31: Gửi lần thứ 6 trong 30 phút / lần thứ 11 trong ngày -> chặn | D31: FT-01 BV-02; NAC-02; BR-024 | E31: P1 | F31: [Theory] đã gửi 5 lần/30 phút và 10 lần/ngày | G31: authService.RequestPhoneVerificationAsync(U1, dto{phone}) | H31: Từ chối theo rate limit; smsService KHÔNG được gọi | I31: Yes | J31: Pass | M31: ⚠ FIX MỘT PHẦN Giới hạn 5 lần/30 phút đã có (495-502) nhưng KHÔNG có giới hạn 10 lần/ngày cho OTP điện thoại (User.cs thiếu field ngày cho Phone OTP).
A32: L1-AUTH-21 | B32: BVA | C32: OTP đúng 6 chữ số trong 5 phút -> xác thực thành công, single-use | D32: FT-01 AC-04; BV-02 | E32: P1 | F32: OTP hợp lệ tạo cách đây 4 phút 59 giây | G32: authService.VerifyPhoneOtpAsync(U1, dto{otp:'123456'}) | H32: Thành công; PhoneVerifiedAt được set Gọi lại cùng OTP lần 2 -> bị từ chối (single-use) | I32: No | J32: Pass | M32: ✅ Pass (không đổi)
A33: L1-AUTH-22 | B33: BVA-Max+1 | C33: OTP tại đúng mốc 5 phút -> hết hạn | D33: FT-01 BV-02; NAC-02 | E33: P1 | F33: OTP tạo cách đây đúng 5:00 (mock clock) | G33: authService.VerifyPhoneOtpAsync(U1, dto{otp:'123456'}) | H33: Từ chối OTP_EXPIRED; số điện thoại KHÔNG đổi | I33: Yes | J33: Pass | M33: ✅ Pass (không đổi)
A34: L1-AUTH-23 | B34: BVA-Max+1 | C34: Sai OTP lần thứ 6 -> khoá theo giới hạn số lần | D34: FT-01 BV-02; NAC-02 | E34: P1 | F34: [Theory] số lần sai trước đó = 4, 5 | G34: authService.VerifyPhoneOtpAsync(U1, dto{otp:'999999'}) | H34: Lần 5 vẫn báo sai; lần 6 trả OTP_ATTEMPT_LIMIT_REACHED Số điện thoại không đổi | I34: Yes | J34: Pass | M34: ✅ ĐÃ FIX AuthService.cs:530-539 khoá sau 5 lần sai, trả OTP_ATTEMPT_LIMIT_REACHED ở lần 6.
A35: L1-AUTH-24 | B35: EP-Valid | C35: Đổi SĐT chỉ có hiệu lực SAU khi xác thực thành công | D35: FT-01 AC-04; BR-024 | E35: P1 | F35: U1 đang có SĐT cũ; yêu cầu đổi purpose='CHANGE_PHONE' | G35: Gửi OTP -> chưa xác thực -> đọc lại profile | H35: Trước khi xác thực: SĐT vẫn là số CŨ Sau khi xác thực đúng: SĐT mới thay thế | I35: No | J35: Pass | M35: ✅ Pass (không đổi)
A36: L1-AUTH-25 | B36: EP-Valid | C36: CompleteProfile sau Google login -> bổ sung thông tin còn thiếu | D36: FT-01 AC-02 | E36: P2 | F36: User tạo qua Google, thiếu SĐT/tên | G36: authService.CompleteProfileAsync(U1, dto) | H36: Thông tin được lưu; không tạo tài khoản thứ 2 | I36: No | J36: Pass | M36: ✅ Pass (không đổi)
A37: ▶ Template Row — copy khi thêm case mới
A38: L1-XX-[NN] | B38: [BC-TRUE | BC-FALSE | CC | EP-Valid | EP-Invalid | BVA-* | State-* | Guard-* | Concurrency | Idempotency | Atomicity] | C38: [Branch / condition / partition] | D38: [FT-xx AC/NAC/BV-xx; BR-xxx; NFR-xxx] | E38: P2 | F38: [Arrange: state + _mock.Setup(...)] | G38: service.Method(params) | H38: [result.Should().Be(...) / Throws / _mock.Verify(..., Times.Never)] | I38: No | J38: Not Run
A40: ▶ Block: ⊕ v2.3 — Gửi lại OTP qua email | ResendEmailOtpAsync (commit ec8f6cd) | FT-01 AC-04; BV-02; BR-024
A41: L1-AUTH-26 | B41: EP-Invalid | C41: Email không tồn tại -> từ chối, không gửi mail | D41: FT-01 NAC-02; BR-024 | E41: P1 | F41: Mock: userRepo.GetByEmailAsync('ghost@x.com') -> null | G41: authService.ResendEmailOtpAsync('ghost@x.com') | H41: Trả thất bại với thông điệp CHUNG (không tiết lộ email có tồn tại hay không) emailService.SendOtpEmailAsync NEVER called | I41: Yes | J41: Pass | M41: ✅ ĐÃ FIX ResendEmailOtpAsync (169-170) trả thông điệp CHUNG cho email không tồn tại, không gọi emailService.
A42: L1-AUTH-27 | B42: EP-Invalid | C42: User đã verify rồi -> từ chối, không gửi mail | D42: FT-01 AC-04; NAC-02 | E42: P1 | F42: User U1 tồn tại, IsVerified = true | G42: authService.ResendEmailOtpAsync(U1.Email) | H42: Trả thất bại (đã xác thực) emailService.SendOtpEmailAsync NEVER called; OTP cũ không bị ghi đè | I42: Yes | J42: Pass | M42: ✅ Pass (không đổi)
A43: L1-AUTH-28 | B43: EP-Valid | C43: Hợp lệ -> sinh OTP mới, hạn theo OTP_EXPIRE_MINUTES, gửi đúng 1 lần | D43: FT-01 AC-04; BV-02; BR-024 | E43: P1 | F43: User U1 tồn tại, IsVerified = false SystemConfig 'OTP_EXPIRE_MINUTES' = 5 (mock clock) | G43: authService.ResendEmailOtpAsync(U1.Email) | H43: OTP mới KHÁC OTP cũ; giá trị lưu là HASH (không phải OTP thô) Hạn = NOW + 5 phút, đọc từ config chứ không hard-code emailService.SendOtpEmailAsync gọi đúng 1 lần | I43: No | J43: Pass | M43: ⚠ FIX MỘT PHẦN OTP mới + hash + gửi đúng 1 lần OK, nhưng hạn dùng const cứng EmailOtpValidityMinutes=5 (dòng 155), KHÔNG đọc từ SystemConfig OTP_EXPIRE_MINUTES.
A44: L1-AUTH-29 | B44: BVA | C44: Resend tại 59s / 60s / 61s so với lần gửi trước | D44: FT-01 BV-02; BR-024 | E44: P1 | F44: SystemConfig 'OTP_RESEND_SECONDS' = 60 [Theory] lần gửi trước cách đây 59s / 60s / 61s | G44: authService.ResendEmailOtpAsync(U1.Email) | H44: 59s: từ chối (OTP_RESEND_TOO_SOON), KHÔNG gửi mail 60s và 61s: gửi thành công | I44: Yes | J44: Pass | M44: ⚠ FIX MỘT PHẦN Hành vi throttle 59/60/61s đúng nhưng ngưỡng là const cứng EmailOtpResendCooldownSeconds=60 (156), không đọc SystemConfig OTP_RESEND_SECONDS.
A45: L1-AUTH-30 | B45: BVA-Max+1 | C45: Lần gửi thứ 6 trong 30 phút -> chặn | D45: FT-01 BV-02; BR-024 | E45: P1 | F45: SystemConfig 'OTP_MAX_ATTEMPTS' = 5 [Theory] đã gửi 4 / 5 lần trong 30 phút | G45: authService.ResendEmailOtpAsync(U1.Email) | H45: Lần 5: vẫn gửi được Lần 6: từ chối theo rate limit; emailService NEVER called | I45: Yes | J45: Pass | M45: ⚠ FIX MỘT PHẦN Chặn đúng ở lần 6/30 phút nhưng giới hạn là const cứng EmailOtpMaxSendsPerWindow=5 (157), không đọc SystemConfig OTP_MAX_ATTEMPTS.
A46: L1-AUTH-31 | B46: BVA-Max+1 | C46: Lần gửi thứ 11 trong ngày -> chặn | D46: FT-01 BV-02; BR-024 | E46: P1 | F46: [Theory] đã gửi 9 / 10 lần trong 24 giờ | G46: authService.ResendEmailOtpAsync(U1.Email) | H46: Lần 10: vẫn gửi được Lần 11: từ chối; emailService NEVER called | I46: Yes | J46: Pass | M46: ⚠ FIX MỘT PHẦN Chặn đúng ở lần 11/ngày nhưng giới hạn là const cứng EmailOtpMaxSendsPerDay=10 (159), không đọc SystemConfig.
A47: L1-AUTH-32 | B47: EP-Invalid | C47: ForgotPasswordAsync với email không tồn tại -> không lộ thông tin | D47: NFR-SEC02; FT-01 NAC-02 | E47: P1 | F47: Mock: GetByEmailAsync -> null | G47: authService.ForgotPasswordAsync('ghost@x.com') | H47: Response giống hệt case email tồn tại (chống enumeration) emailService NEVER called; không tạo reset token | I47: Yes | J47: Pass | M47: ✅ Pass (không đổi)
A48: L1-AUTH-33 | B48: EP-Valid | C48: ForgotPasswordAsync hợp lệ -> sinh reset token single-use, gửi 1 mail | D48: NFR-SEC02 | E48: P1 | F48: User U1 tồn tại, đã verify | G48: authService.ForgotPasswordAsync(U1.Email) | H48: Reset token được sinh và lưu dạng không đoán được emailService.SendResetPasswordEmailAsync gọi đúng 1 lần Token chỉ dùng được 1 lần (kiểm bằng L1-AUTH-15) | I48: No | J48: Pass | M48: ✅ Pass (không đổi)

Sheet CartService
A1: CartService | methods: GetCartAsync, AddItemToCartAsync, UpdateCartItemAsync, RemoveItemFromCartAsync, ClearCartAsync | EF Core InMemory (service injects ApplicationDbContext)
A2: HOW TO USE: (1) Đọc Introduction (2) Trace theo SRS v2 (Part 3 + RTW Sheet 3/6/7) (3) Cập nhật Status sau mỗi lần chạy dotnet test / vitest (4) Ghi Defect ID khi Fail
A4: Test ID | B4: Coverage Technique | C4: Covers (Decision/Condition) | D4: SRS Reference | E4: Priority | F4: Given (Precondition / Mock Setup) | G4: When (Input / Act) | H4: Then (Expected Output / Assert) | I4: Negative? | J4: Status | K4: Defect ID | L4: Notes | M4: Fix Status
A5: ▶ Block: GetCartAsync() | FT-01 AC-02/AC-03, BV-01, BR-03
A6: L1-CART-01 | B6: EP-Valid | C6: Existing cart -> items and quantities restored from DB | D6: FT-01 AC-05; BR-025 | E6: P1 | F6: InMemory DB: cart with 2 items (qty 3 and 5) for user U1 | G6: cartService.GetCartAsync(U1) | H6: Returns CartDto with 2 items; quantities 3 and 5 preserved No exception | I6: No | J6: Pass | M6: ✅ Pass (không đổi)
A7: L1-CART-02 | B7: EP-Valid | C7: User without cart -> empty cart returned (no exception) | D7: FT-01 AC-05 | E7: P2 | F7: InMemory DB: no cart for user U2 | G7: cartService.GetCartAsync(U2) | H7: Returns empty CartDto (Items.Count = 0) Does not throw | I7: No | J7: Pass | M7: ✅ Pass (không đổi)
A8: L1-CART-03 | B8: BVA-Max | C8: Cart idle exactly 24h00m -> flagged Price Expired | D8: FT-01 BV-01; NAC-03; BR-025 | E8: P1 | F8: Cart.PriceLockedAt = NOW - 24h00m exactly (mock time source) | G8: cartService.GetCartAsync(U1) | H8: CartDto.IsPriceExpired = true Prompt flag present for FE to force price review | I8: No | J8: Pass | M8: ✅ Pass (không đổi)
A9: L1-CART-04 | B9: BVA-Max-1 | C9: Cart idle 23h59m -> prices still locked, not expired | D9: FT-01 BV-01; BR-025 | E9: P1 | F9: Cart.PriceLockedAt = NOW - 23h59m | G9: cartService.GetCartAsync(U1) | H9: CartDto.IsPriceExpired = false Unit prices = original snapshot (unchanged) | I9: No | J9: Pass | M9: ✅ Pass (không đổi)
A10: ▶ Block: AddItemToCartAsync()
A11: L1-CART-05 | B11: EP-Valid | C11: Add new product -> line item created with price snapshot | D11: FT-01 AC-05; FT-02 AC-02; BR-005 | E11: P1 | F11: InMemory DB: product P1 (Active, price 50,000); empty cart | G11: cartService.AddItemToCartAsync(U1, {P1, qty=2}) | H11: Cart has 1 item: ProductId=P1, Quantity=2, UnitPrice snapshot = 50,000 | I11: No | J11: Pass | M11: ✅ Pass (không đổi)
A12: L1-CART-06 | B12: EP-Valid | C12: Add product already in cart -> quantity accumulated, no duplicate line | D12: FT-01 AC-05 | E12: P1 | F12: Cart already contains P1 qty=2 | G12: cartService.AddItemToCartAsync(U1, {P1, qty=3}) | H12: Cart still has exactly 1 line for P1; Quantity = 5 | I12: No | J12: Pass | M12: ✅ Pass (không đổi)
A13: L1-CART-07 | B13: EP-Invalid | C13: Quantity <= 0 -> rejected | D13: FT-01 AC-05 | E13: P1 | F13: Product P1 active | G13: cartService.AddItemToCartAsync(U1, {P1, qty=0}) | H13: Throws validation exception / rejects No cart item persisted | I13: Yes | J13: Pass | M13: ✅ Pass (không đổi)
A14: L1-CART-08 | B14: EP-Invalid | C14: Discontinued product -> cannot be added | D14: FT-01 NAC-04; BR-047 | E14: P1 | F14: Product P2 status = Discontinued | G14: cartService.AddItemToCartAsync(U1, {P2, qty=1}) | H14: Rejected with error; no cart item persisted | I14: Yes | J14: Pass | M14: ✅ Pass (không đổi)
A15: ▶ Block: UpdateCartItemAsync() / RemoveItemFromCartAsync() / ClearCartAsync()
A16: L1-CART-09 | B16: EP-Invalid | C16: Update a cart item belonging to another user -> rejected | D16: FT-01 NAC-05; NFR-SEC03 | E16: P1 | F16: CartItem CI-9 belongs to user U9 | G16: cartService.UpdateCartItemAsync(U1, CI-9, {qty=10}) | H16: Throws not-found/forbidden CI-9.Quantity unchanged | I16: Yes | J16: Pass | M16: ✅ Pass (không đổi)
A17: L1-CART-10 | B17: EP-Valid | C17: Clear cart -> all items removed | D17: FT-01 AC-05 | E17: P2 | F17: Cart with 3 items for U1 | G17: cartService.ClearCartAsync(U1) | H17: Cart.Items.Count = 0 after call; cart record itself retained | I17: No | J17: Pass | M17: ✅ Pass (không đổi)
A18: ▶ Template Row — copy khi thêm case mới
A19: L1-XX-[NN] | B19: [BC-TRUE | BC-FALSE | CC | EP-Valid | EP-Invalid | BVA-* | State-* | Guard-* | Concurrency | Idempotency | Atomicity] | C19: [Branch / condition / partition] | D19: [FT-xx AC/NAC/BV-xx; BR-xxx; NFR-xxx] | E19: P2 | F19: [Arrange: state + _mock.Setup(...)] | G19: service.Method(params) | H19: [result.Should().Be(...) / Throws / _mock.Verify(..., Times.Never)] | I19: No | J19: Not Run

Sheet ProductService
A1: ProductService | methods: GetProductsAsync, GetProductByIdAsync, GetCategoriesAsync, CreateProductAsync | Mock: IUnitOfWork
A2: HOW TO USE: (1) Đọc Introduction (2) Trace theo SRS v2 (Part 3 + RTW Sheet 3/6/7) (3) Cập nhật Status sau mỗi lần chạy dotnet test / vitest (4) Ghi Defect ID khi Fail
A4: Test ID | B4: Coverage Technique | C4: Covers (Decision/Condition) | D4: SRS Reference | E4: Priority | F4: Given (Precondition / Mock Setup) | G4: When (Input / Act) | H4: Then (Expected Output / Assert) | I4: Negative? | J4: Status | K4: Defect ID | L4: Notes | M4: Fix Status
A5: ▶ Block: GetProductsAsync() | FT-01 SB-1 catalogue browsing; BR-26
A6: L1-PROD-01 | B6: EP-Valid | C6: Filter by categoryId -> only products of that category returned | D6: FT-01 AC-01 | E6: P2 | F6: Mock repo: 5 products, 2 in category C1 | G6: productService.GetProductsAsync(page=1, pageSize=12, categoryId=C1) | H6: Result.Items all have CategoryId = C1; TotalCount = 2 | I6: No | J6: Pass
A7: L1-PROD-02 | B7: EP-Valid | C7: searchKeyword matches product name (case-insensitive) | D7: FT-01 AC-01 | E7: P2 | F7: Mock repo returns products filtered by keyword 'bag' | G7: productService.GetProductsAsync(searchKeyword='bag') | H7: All returned product names contain 'bag' Repo called with the exact keyword | I7: No | J7: Pass
A8: L1-PROD-03 | B8: EP-Invalid | C8: Discontinued products hidden from public catalogue | D8: FT-01 AC-01; NAC-04; BR-047 | E8: P1 | F8: Mock repo: product P2 Discontinued among actives | G8: productService.GetProductsAsync(page=1) | H8: P2 NOT present in Result.Items Active products returned normally | I8: No | J8: Pass
A9: L1-PROD-04 | B9: BVA-Min-1 | C9: page = 0 or negative -> normalized to page 1 (or rejected) | D9: FT-01 AC-01 | E9: P3 | F9: Mock repo | G9: productService.GetProductsAsync(page=0) | H9: Repo receives page >= 1 (no negative offset); no exception | I9: No | J9: Pass
A10: ▶ Block: GetProductByIdAsync()
A11: L1-PROD-05 | B11: EP-Invalid | C11: Unknown product id -> null returned (no exception) | D11: FT-01 AC-01 | E11: P2 | F11: Mock repo: GetByIdAsync(Px) -> null | G11: productService.GetProductByIdAsync(Px) | H11: Returns null; controller maps to 404 | I11: No | J11: Pass
A12: ▶ Template Row — copy khi thêm case mới
A13: L1-XX-[NN] | B13: [BC-TRUE | BC-FALSE | CC | EP-Valid | EP-Invalid | BVA-* | State-* | Guard-* | Concurrency | Idempotency | Atomicity] | C13: [Branch / condition / partition] | D13: [FT-xx AC/NAC/BV-xx; BR-xxx; NFR-xxx] | E13: P2 | F13: [Arrange: state + _mock.Setup(...)] | G13: service.Method(params) | H13: [result.Should().Be(...) / Throws / _mock.Verify(..., Times.Never)] | I13: No | J13: Not Run

Sheet OrderService
A1: OrderService | methods: GetCheckoutSummaryAsync, PlaceOrderAsync, GenerateSePayQrAsync, ProcessSePayWebhookAsync, ConfirmOrderAsync, PlaceDirectOrderAsync, RequestVatInvoiceAsync, RejectOrder/Cancel flows, ScheduleDeliveryAsync, RecordDeliveryResultAsync, GetOrderHistoryAsync | EF Core InMemory + Mock: ICartService, IEmailService
A2: HOW TO USE: (1) Đọc Introduction (2) Trace theo SRS v2 (Part 3 + RTW Sheet 3/6/7) (3) Cập nhật Status sau mỗi lần chạy dotnet test / vitest (4) Ghi Defect ID khi Fail
A4: Test ID | B4: Coverage Technique | C4: Covers (Decision/Condition) | D4: SRS Reference | E4: Priority | F4: Given (Precondition / Mock Setup) | G4: When (Input / Act) | H4: Then (Expected Output / Assert) | I4: Negative? | J4: Status | K4: Defect ID | L4: Notes | M4: Fix Status
A5: ▶ Block: GetCheckoutSummaryAsync() — tiered pricing | FT-02 AC-01..03, NAC-02, BV-01, BR-01/BR-02
A6: L1-ORD-01 | B6: BVA-Max | C6: Cart total = 9,999,999 VND -> standard list price (Tier 1 max) | D6: FT-02 AC-01; BV-01; BR-006 | E6: P1 | F6: Cart totalling exactly 9,999,999 VND | G6: orderService.GetCheckoutSummaryAsync(U1) | H6: PricingTier = Standard; unit prices = list prices 'Proceed to Payment' enabled (CanCheckout = true) | I6: No | J6: Pass | M6: ✅ Pass (không đổi)
A7: L1-ORD-02 | B7: BVA-Min | C7: Cart total = 10,000,000 VND -> Tier 2 quantity discount applied | D7: FT-02 AC-01; BV-01; BR-006 | E7: P1 | F7: Cart totalling exactly 10,000,000 VND; discount matrix seeded | G7: orderService.GetCheckoutSummaryAsync(U1) | H7: PricingTier = QuantityDiscount; discounted unit prices per matrix Recalculated total < list-price total | I7: No | J7: Pass | M7: ✅ Pass (không đổi)
A8: L1-ORD-03 | B8: BVA-Max | C8: Cart total = 99,999,999 VND -> still Tier 2 | D8: FT-02 AC-01; BV-01; BR-006 | E8: P1 | F8: Cart totalling 99,999,999 VND | G8: orderService.GetCheckoutSummaryAsync(U1) | H8: PricingTier = QuantityDiscount (NOT negotiated flow) CanCheckout = true | I8: No | J8: Pass | M8: ✅ Pass (không đổi)
A9: L1-ORD-04 | B9: BVA-Min + Guard-TRUE | C9: Total = 100,000,000 VND + saved negotiated price -> auto-applied | D9: FT-02 AC-01; AC-05; BV-01; BR-026 | E9: P1 | F9: Cart = 100,000,000 VND; CustomerProfile.NegotiatedPrice saved (approved) | G9: orderService.GetCheckoutSummaryAsync(U1) | H9: Negotiated price auto-applied to total No quotation request required; CanCheckout = true | I9: No | J9: Pass | L9: auto-áp giá thỏa thuận cho đơn >= 100M chưa cài đặt — mọi đơn >= 100M đều bị chặn yêu cầu báo giá B2B. | M9: ✅ ĐÃ FIX [🟢 ĐÃ FIX HOÀN TOÀN — test unit viết lại, bỏ Skip, PASS thật (07/08/2026)] GH-13 đã fix ở code (Quotation/QuotationVersion.ProposedTotal, không phải SavedB2BPriceSnapshot như giả định gốc). Đã viết lại L1_ORD_04_Checkout_100M_WithAcceptedQuotation_NegotiatedPriceApplied (PASS) + thêm L1_ORD_04b (báo giá hết hạn vẫn bị chặn, PASS) trong OrderServiceTests.cs, bỏ [Fact(Skip=...)].
A10: L1-ORD-05 | B10: Guard-FALSE | C10: Total >= 100M, NO negotiated price -> payment hidden, quotation required | D10: FT-02 AC-03; BV-01; BR-026 | E10: P1 | F10: Cart = 120,000,000 VND; no saved negotiated price | G10: orderService.GetCheckoutSummaryAsync(U1) | H10: CanCheckout = false; RequiresQuotation = true No pricing applied beyond list snapshot | I10: No | J10: Pass | M10: ✅ Pass (không đổi)
A11: L1-ORD-06 | B11: EP-Invalid | C11: Negotiated price NOT applied to 80M order (below threshold) | D11: FT-02 NAC-02; BV-01 | E11: P1 | F11: Customer has negotiated price; cart total = 80,000,000 VND | G11: orderService.GetCheckoutSummaryAsync(U1) | H11: Negotiated price ignored; Tier-2 discount applied instead Tooltip flag: negotiated pricing only for >= 100M | I11: Yes | J11: Pass | M11: ✅ Pass (không đổi)
A12: ▶ Block: PlaceOrderAsync() | FT-01 AC-04/05, NAC-02/03/04; FT-02 NAC-01
A13: L1-ORD-07 | B13: EP-Valid | C13: Valid checkout -> order 'Order Received', invoice email queued, Sales notified | D13: FT-01 AC-05; FT-03 AC-04; BR-030 | E13: P1 | F13: Valid non-expired cart, all items in stock Mock: emailService | G13: orderService.PlaceOrderAsync(U1, request) | H13: Order persisted with Status = 'Order Received' emailService.SendOrderInvoiceEmailAsync() called once Sales notification created | I13: No | J13: Pass | M13: ✅ Pass (không đổi)
A14: L1-ORD-08 | B14: EP-Invalid | C14: Empty cart -> checkout rejected | D14: FT-01 AC-05 | E14: P1 | F14: Cart.Items = [] | G14: orderService.PlaceOrderAsync(U1, request) | H14: Throws validation exception; no Order persisted | I14: Yes | J14: Pass | M14: ✅ Pass (không đổi)
A15: L1-ORD-09 | B15: BC-TRUE | C15: Price-Expired cart (idle > 24h) -> checkout blocked | D15: FT-01 NAC-03; FT-02 NAC-03; BV-01; BR-025 | E15: P1 | F15: Cart.PriceLockedAt = NOW - 25h (mock time) | G15: orderService.PlaceOrderAsync(U1, request) | H15: Rejected: customer must re-confirm refreshed prices No Order persisted | I15: Yes | J15: Pass | L15: không có logic chặn checkout khi giá hết hạn — CartService tự refresh giá (xem L1-CART-03). Ghi Notes. | M15: ✅ ĐÃ FIX [🟢 ĐÃ FIX HOÀN TOÀN — test unit viết lại, bỏ Skip, PASS thật (07/08/2026)] GH-08 đã fix ở code (check hạn giữ giá TRƯỚC khi gọi CartService.GetCartAsync). Đã viết lại L1_ORD_09_PlaceOrder_PriceExpiredCart_Blocked (PASS) + thêm L1_ORD_09b (chưa hết hạn vẫn checkout được, PASS) trong OrderServiceTests.cs, bỏ [Fact(Skip=...)].
A16: L1-ORD-10 | B16: EP-Invalid | C16: Item went out of stock between add-to-cart and checkout -> blocked | D16: FT-01 NAC-03; FT-03 AC-01; BR-008 | E16: P1 | F16: Cart has P1 qty=5; current stock P1 = 0 | G16: orderService.PlaceOrderAsync(U1, request) | H16: Rejected with message naming the product No Order persisted; no stock change | I16: Yes | J16: Pass | M16: ✅ Pass (không đổi)
A17: L1-ORD-11 | B17: CC | C17: Tampered payload total (99,999,999) vs true total >= 100M -> HTTP 400 + security alert | D17: FT-02 NAC-01; BR-005 | E17: P1 | F17: Client payload claims total 99,999,999; server recalculation of cart = 105,000,000 | G17: orderService.PlaceOrderAsync(U1, tamperedRequest) | H17: Rejected (maps to HTTP 400) 'Pricing Bypass Attempt' security alert logged No Order persisted | I17: Yes | J17: Pass | M17: ✅ Pass (không đổi)
A18: ▶ Block: GenerateSePayQrAsync() | FT-03 AC-01, NAC-03; 4.4.2
A19: L1-ORD-12 | B19: State-Valid | C19: SePay selected -> unique QR + ref code, 'Pending Payment', 15-min timer | D19: FT-03 AC-01; BV-01; BR-008 | E19: P1 | F19: Order O1 total > 0, unpaid | G19: orderService.GenerateSePayQrAsync(O1) | H19: Returns QR payload + unique reference code Payment status = 'Pending Payment'; expiry timestamp = NOW + 15min | I19: No | J19: Pass | M19: ✅ Pass (không đổi)
A20: L1-ORD-13 | B20: State-Invalid | C20: Order already Paid -> QR generation blocked | D20: FT-03 NAC-02; BR-016; BR-029 | E20: P1 | F20: Order O1 payment status = Paid | G20: orderService.GenerateSePayQrAsync(O1) | H20: Throws conflict (maps to HTTP 409): 'This order has already been paid.' No new QR / no status change | I20: Yes | J20: Pass | L20: ℹ Cùng defect GH-05 với L1-REG-07 (GenerateSePayQrAsync không chặn đơn đã Paid) — log CHUNG 1 defect ID, đừng đếm thành 2 lỗi. | GenerateSePayQrAsync không chặn đơn đã thanh toán (Paid) — spec gap, đề xuất log defect. | M20: ✅ ĐÃ FIX OrderService.cs:296-297 throw nếu PaymentStatus=Paid trước khi sinh QR mới -> map 409.
A21: ▶ Block: ProcessSePayWebhookAsync() | FT-03 AC-02, NAC-01, BV-01/BV-02, BR-06/BR-07
A22: L1-ORD-14 | B22: Guard-TRUE | C22: Valid signature + exact amount within 15-min -> Paid, txn ID recorded | D22: FT-03 AC-02; BV-01; BR-009; NFR-SEC05 | E22: P1 | F22: Order Pending Payment, total 5,000,000; webhook amount = 5,000,000, valid HMAC token; within window | G22: orderService.ProcessSePayWebhookAsync(payload, validToken) | H22: Payment status = Paid (locked); external transaction ID stored Sales notification triggered | I22: No | J22: Pass | M22: ✅ Pass (không đổi)
A23: L1-ORD-15 | B23: Guard-FALSE | C23: Invalid signature/token -> rejected 401, status unchanged, alert logged | D23: FT-03 NAC-01; NFR-SEC05 | E23: P1 | F23: Order Pending Payment; providedToken = 'WRONG' | G23: orderService.ProcessSePayWebhookAsync(payload, 'WRONG') | H23: Throws unauthorized (maps to HTTP 401) Order status unchanged; security alert logged No transaction ID stored | I23: Yes | J23: Pass | M23: ✅ Pass (không đổi)
A24: L1-ORD-16 | B24: BVA-Max+1 | C24: Amount = order total + 1 VND -> rejected | D24: FT-03 NAC-01; BV-01 | E24: P1 | F24: Order total 5,000,000; webhook amount 5,000,001; valid token | G24: orderService.ProcessSePayWebhookAsync(payload) | H24: Rejected; status unchanged; alert logged | I24: Yes | J24: Pass | M24: ✅ Pass (không đổi)
A25: L1-ORD-17 | B25: BVA-Min-1 | C25: Amount = order total - 1 VND -> rejected | D25: FT-03 NAC-01; BV-01 | E25: P1 | F25: Order total 5,000,000; webhook amount 4,999,999; valid token | G25: orderService.ProcessSePayWebhookAsync(payload) | H25: Rejected; status unchanged | I25: Yes | J25: Pass | M25: ✅ Pass (không đổi)
A26: L1-ORD-18 | B26: EP-Valid | C26: Duplicate webhook (same txn ID) -> idempotent, not double-applied | D26: FT-03 NAC-02; BR-029 | E26: P1 | F26: Order already Paid via txn T1; identical webhook re-sent | G26: orderService.ProcessSePayWebhookAsync(samePayload) | H26: No state change; no duplicate payment record No second Sales notification | I26: No | J26: Pass | M26: ✅ Pass (không đổi)
A27: L1-ORD-19 | B27: State-Invalid | C27: Webhook after 15-min expiry / order cancelled -> not applied | D27: FT-03 NAC-03; BV-01; BR-033 | E27: P1 | F27: Order auto-cancelled at 15:00 timer expiry; late webhook arrives | G27: orderService.ProcessSePayWebhookAsync(payload) | H27: Order remains Cancelled (terminal) Flagged to manual-verification/exception list instead of auto-Paid | I27: Yes | J27: Pass | M27: ✅ Pass (không đổi)
A28: ▶ Block: ConfirmOrderAsync() | FT-04 AC-01; 4.4.1
A29: L1-ORD-20 | B29: State-Valid | C29: 'Order Received' + Paid/COD -> Confirmed, FIFO picking ticket | D29: FT-05 AC-01; BR-011 | E29: P1 | F29: Order O1 status 'Order Received', payment verified | G29: orderService.ConfirmOrderAsync(O1, salesStaffId) | H29: Status = Confirmed; picking ticket created with ascending FIFO sequence Warehouse queue notified | I29: No | J29: Pass | M29: ✅ Pass (không đổi)
A30: L1-ORD-21 | B30: State-Invalid | C30: Confirm a Cancelled order -> HTTP 409 | D30: FT-05 AC-01; NAC-05 | E30: P1 | F30: Order O1 status = Cancelled | G30: orderService.ConfirmOrderAsync(O1, staffId) | H30: Throws conflict (409) 'order is closed' No status change; no ticket created | I30: Yes | J30: Pass | M30: ✅ Pass (không đổi)
A31: ▶ Block: PlaceDirectOrderAsync() — walk-in | FT-08 AC-01..03, NAC-01/02/04, BV-01/02, BR-22/23
A32: L1-ORD-22 | B32: EP-Valid | C32: Known phone number -> customer profile auto-filled | D32: FT-01 AC-03; BR-030 | E32: P1 | F32: CustomerProfile exists for '0912345678' | G32: orderService.PlaceDirectOrderAsync(req{phone='0912345678'}) | H32: Existing profile reused (name/address auto-filled) No duplicate profile created | I32: No | J32: Pass | M32: ✅ Pass (không đổi)
A33: L1-ORD-23 | B33: EP-Invalid + BVA-Max+1 | C33: Line qty = available stock + 1 -> blocked | D33: FT-05 NAC-01; BV-02; BR-032 | E33: P1 | F33: Stock P1 = 10 | G33: orderService.PlaceDirectOrderAsync(req{P1, qty=11}) | H33: Rejected: 'Insufficient stock. Available: 10' No invoice; no stock change | I33: Yes | J33: Pass | M33: ✅ Pass (không đổi)
A34: L1-ORD-24 | B34: EP-Invalid | C34: Invalid phone format ('0912345678a', 9 digits) -> validation error | D34: FT-01 AC-04; NAC-02; BR-030 | E34: P1 | F34: — | G34: orderService.PlaceDirectOrderAsync(req{phone='0912345678a'}) | H34: Rejected: 'Invalid phone number format.' No profile lookup query executed | I34: Yes | J34: Pass | L34: BE không validate định dạng SĐT trong PlaceDirectOrderAsync (FT-08 NAC-04 chỉ chặn ở FE) | M34: ✅ ĐÃ FIX OrderService.cs:595-598 validate SĐT bằng regex ^0\d{9}$, throw nếu sai định dạng.
A35: L1-ORD-25 | B35: EP-Invalid | C35: Empty product list -> submission blocked | D35: FT-01 AC-05; BR-030 | E35: P1 | F35: req.Items = [] | G35: orderService.PlaceDirectOrderAsync(req) | H35: Rejected; missing fields highlighted; nothing persisted | I35: Yes | J35: Pass | M35: ✅ Pass (không đổi)
A36: L1-ORD-26 | B36: EP-Valid | C36: Confirm -> atomic: invoice + purchase history + stock deduction | D36: FT-05 AC-02; BR-032; NFR-A05 | E36: P1 | F36: Stock P1 = 10; req{P1, qty=4} | G36: orderService.PlaceDirectOrderAsync(req) | H36: Invoice persisted; customer history appended; stock P1 = 6 All three in one transaction (verify rollback on forced failure) | I36: No | J36: Pass | M36: ✅ Pass (không đổi)
A37: L1-ORD-27 | B37: BVA-Max | C37: Line qty = available stock exactly -> allowed, stock becomes 0 | D37: FT-05 BV-01; BR-032 | E37: P1 | F37: Stock P1 = 10 | G37: orderService.PlaceDirectOrderAsync(req{P1, qty=10}) | H37: Invoice created; stock P1 = 0 (not negative) | I37: No | J37: Pass | M37: ✅ Pass (không đổi)
A38: ▶ Block: RequestVatInvoiceAsync() | FT-06 NAC-01; BR-15
A39: L1-ORD-28 | B39: BVA-Max+1 | C39: Request at 169h (7d + 1h) after delivery -> blocked | D39: (chờ xác nhận) FT-01 AC-03 | E39: P1 | F39: Order Delivered at NOW - 169h (mock time) | G39: orderService.RequestVatInvoiceAsync(U1, O1) | H39: Rejected: 'VAT invoice requests must be made within 7 days of delivery.' No VAT request record created | I39: Yes | J39: Pass | M39: ✅ Pass (không đổi)
A40: L1-ORD-29 | B40: BVA-Max | C40: Request at 167h59m after delivery -> accepted (within 168h window) | D40: (chờ xác nhận) FT-01 AC-03 | E40: P1 | F40: Đơn O1 đã Delivered; khách có MST | G40: orderService.RequestVatInvoiceAsync(U1, O1) | H40: CHƯA CHỐT ĐƯỢC KỲ VỌNG: SRS v2 Part 3 không định nghĩa thuế suất, quy tắc làm tròn, hay cửa sổ thời gian Tạm assert: yêu cầu VAT được ghi nhận, RedInvoiceStatus = Pending | I40: Yes | J40: Pass | M40: ✅ Pass (không đổi)
A41: L1-ORD-30 | B41: State-Invalid | C41: Order not yet Delivered -> VAT request rejected | D41: (chờ xác nhận) FT-01 AC-03 | E41: P2 | F41: Order status = In Delivery | G41: orderService.RequestVatInvoiceAsync(U1, O1) | H41: Rejected; no request record | I41: Yes | J41: Pass | M41: ✅ Pass (không đổi)
A42: ▶ Block: GetOrderHistoryAsync() / GetOrderDetailForCustomerAsync()
A43: L1-ORD-31 | B43: EP-Invalid | C43: Customer requests another customer's order detail -> not found/forbidden | D43: FT-01 NAC-05; NFR-SEC03 | E43: P1 | F43: Order O9 belongs to customer U9 | G43: orderService.GetOrderDetailForCustomerAsync(U1, O9) | H43: Throws not-found/forbidden; no data leaked | I43: Yes | J43: Pass | M43: ✅ Pass (không đổi)
A44: L1-ORD-32 | B44: EP-Valid | C44: History returns only the caller's orders, paged | D44: FT-01 AC-05 | E44: P2 | F44: U1 has 3 orders; U9 has 2 | G44: orderService.GetOrderHistoryAsync(U1, query{page=1}) | H44: Result contains exactly U1's 3 orders; TotalCount = 3 | I44: No | J44: Pass | M44: ✅ Pass (không đổi)
A45: ▶ Block: RejectOrderAsync() / RequestCancelOrderAsync() / ProcessCancelRequestAsync() | cancellation flows
A46: L1-ORD-33 | B46: State-Valid | C46: Sales rejects 'Order Received' with reason -> order closed, customer notified | D46: FT-08 AC-01; BR-017 | E46: P2 | F46: Order O1 'Order Received'; reason provided | G46: orderService.RejectOrderAsync(O1, staffId, 'out of stock') | H46: Order moved to rejected/cancelled terminal state; reason stored Customer notification created; reserved stock released | I46: No | J46: Pass | M46: ✅ Pass (không đổi)
A47: L1-ORD-34 | B47: EP-Invalid | C47: Reject without a reason -> validation error | D47: FT-08 AC-01 | E47: P2 | F47: Order O1 'Order Received' | G47: orderService.RejectOrderAsync(O1, staffId, '') | H47: Rejected: reason required; status unchanged | I47: Yes | J47: Pass | L47: RejectOrderAsync không bắt buộc lý do (reason bị bỏ qua, không lưu) — spec gap FT-04 NAC-04, đề xuất log defect | M47: ✅ ĐÃ FIX OrderService.cs:1742-1745 throw nếu reason rỗng; lưu vào order.CancelReason (1765).
A48: L1-ORD-35 | B48: State-Valid | C48: Customer requests cancellation while order still 'Order Received' -> request recorded | D48: FT-08 AC-01; BR-017 | E48: P2 | F48: Order O1 'Order Received', owner U1 | G48: orderService.RequestCancelOrderAsync(O1, U1, req{reason}) | H48: Cancel request persisted, pending Sales decision Sales notified; order not yet cancelled | I48: No | J48: Pass | M48: ✅ Pass (không đổi)
A49: L1-ORD-36 | B49: State-Invalid | C49: Cancel request on an order already In Delivery -> rejected | D49: FT-08 AC-01; NAC-05 | E49: P1 | F49: Order O1 'In Delivery' | G49: orderService.RequestCancelOrderAsync(O1, U1, req) | H49: Throws conflict; no cancel request created | I49: Yes | J49: Pass | M49: ✅ Pass (không đổi)
A50: L1-ORD-37 | B50: State-Valid | C50: Sales approves cancel request -> order Cancelled, reserved stock released | D50: FT-08 AC-01; BR-017 | E50: P1 | F50: Order O1 with pending cancel request | G50: orderService.ProcessCancelRequestAsync(O1, staffId, req{approve=true}) | H50: Order Status = Cancelled (terminal); stock reservation released Customer notified of outcome | I50: No | J50: Pass | M50: ✅ Pass (không đổi)
A51: ▶ Block: ScheduleDeliveryAsync() | FT-04 AC-03, NAC-01, BV-01; BR-10
A52: L1-ORD-38 | B52: State-Valid | C52: Packed + free vehicle/shift -> In Delivery + SMS/Email to customer | D52: FT-07 AC-01; BV-01; BR-037 | E52: P1 | F52: Đơn O1: FulfillmentStatus = HandedOver (8), DeliveryStatus = NotScheduled (0) Xe V1 active, ca Morning còn trống | G52: orderService.ScheduleDeliveryAsync(staffId, dto{O1, vehicleId, shift}) | H52: DeliveryStatus = Scheduled (1) Ghi nhận xe + ca + ngày; khách nhận thông báo | I52: No | J52: Pass | M52: ✅ Pass (không đổi)
A53: L1-ORD-39 | B53: EP-Invalid | C53: Chosen vehicle/shift at max capacity -> blocked with 'fully booked' error | D53: FT-07 NAC-01; BV-01; BR-037 | E53: P1 | F53: V1/Morning already at configured max load | G53: orderService.ScheduleDeliveryAsync(staffId, dto{O1, V1, Morning}) | H53: Rejected: 'Selected shift/vehicle is fully booked. Please choose an alternative.' No assignment persisted; status unchanged | I53: Yes | J53: Pass | M53: ✅ Pass (không đổi)
A54: L1-ORD-40 | B54: BVA-Max / BVA-Max+1 | C54: Vehicle 5 assignable; vehicle id #6 (non-existent fleet slot) rejected | D54: FT-07 BV-01; BR-037 | E54: P1 | F54: Fleet = exactly 5 vehicles, 3 shifts ([Theory] both points) | G54: ScheduleDeliveryAsync with 5th vehicle, then a 6th vehicle id | H54: 5th vehicle: assignment succeeds 6th vehicle: rejected — fleet is fixed at 5 | I54: Yes | J54: Pass | M54: ✅ Pass (không đổi)
A55: L1-ORD-41 | B55: EP-Invalid | C55: Shift value outside {Morning, Midday, Afternoon} -> validation error | D55: FT-07 NAC-01; BV-01 | E55: P2 | F55: — | G55: orderService.ScheduleDeliveryAsync(staffId, dto{shift='Night'}) | H55: Rejected; no assignment | I55: Yes | J55: Pass | M55: ✅ Pass (không đổi)
A56: ▶ Block: RecordDeliveryResultAsync() | FT-04 AC-04, NAC-02, NAC-04; 4.4.1 rows 9-10; BR-11/BR-31
A57: L1-ORD-42 | B57: State-Valid | C57: COD: collected amount == total -> Paid + debt ledger + Delivered | D57: FT-07 AC-04; BV-02; BR-039 | E57: P1 | F57: Đơn O1 DeliveryStatus = InDelivery (2), PaymentMethod = COD, PaymentStatus = Unpaid, tổng 5.000.000đ | G57: orderService.RecordDeliveryResultAsync(O1, staffId, dto{collected: 5_000_000, signed:true}) | H57: PaymentStatus = Paid (2); DeliveryStatus = Delivered (3); OrderStatus = Completed (5) | I57: No | J57: Pass | M57: ✅ Pass (không đổi)
A58: L1-ORD-43 | B58: EP-Invalid | C58: Cash collection attempted on SePay-paid order -> 'Duplicate Collection Attempt' block | D58: FT-07 NAC-04; BR-016; BR-039 | E58: P1 | F58: Đơn O1 DeliveryStatus = InDelivery, PaymentStatus = Paid (đã trả qua SePay) | G58: orderService.RecordDeliveryResultAsync(O1, staffId, dto{collected: 5_000_000}) | H58: Từ chối thu tiền; PaymentStatus vẫn Paid; không tạo giao dịch thu thứ 2 | I58: Yes | J58: Pass | L58: RecordDeliveryResultAsync không chặn thu tiền COD trên đơn đã Paid qua SePay (FT-04 NAC-02) | M58: ✅ ĐÃ FIX OrderService.cs:2165-2166 throw nếu PaymentStatus=Paid và AmountCollected>0.
A59: L1-ORD-44 | B59: State-Invalid | C59: Customer rejected but staff marks Delivered WITHOUT reason code -> forced to select reason | D59: FT-07 NAC-03; BR-038 | E59: P1 | F59: Order O1 In Delivery; dto.rejected=true, reasonCode=null | G59: orderService.RecordDeliveryResultAsync(O1, staffId, dto) | H59: Rejected (maps to 422): 'Delivery Issue' reason code mandatory Status unchanged | I59: Yes | J59: Pass | L59: RecordDeliveryResultAsync chỉ nhận outcome delivered/partially_delivered/failed, không có reason code bắt buộc (FT-04 NAC-04/BR-31) — spec gap. | M59: ✅ ĐÃ FIX OrderService.cs:2169-2170 bắt buộc RejectionReasonCode khi CustomerRejected=true; lưu ở 2268-2269.
A60: L1-ORD-45 | B60: State-Valid | C60: Customer rejects + reason code -> Awaiting Return, return record created | D60: FT-07 AC-05; BV-03; BR-040; FT-08 AC-05 | E60: P1 | F60: Đơn O1 DeliveryStatus = InDelivery; FailedDeliveryCount = 0 | G60: orderService.RecordDeliveryResultAsync(O1, staffId, dto{failed:true, reasonCode}) | H60: FailedDeliveryCount tăng lên 1; DeliveryStatus = Failed (4) hoặc Rescheduled (6) Hàng trả về xử lý theo luồng đổi/trả | I60: No | J60: Pass | M60: ✅ Pass (không đổi)
A61: ▶ Block: RequestCancelPaidOrderAsync() / ApproveCancelAndCreateReplacementAsync() | no-refund replacement flow
A62: L1-ORD-46 | B62: EP-Valid | C62: Manager approves cancel of a PAID order -> replacement order created, NO monetary refund | D62: FT-08 AC-01; AC-02; BR-017; BR-041 | E62: P1 | F62: Order O1 Paid with pending paid-cancel request | G62: orderService.ApproveCancelAndCreateReplacementAsync(O1, managerId, dto{items}) | H62: Original order closed/cancelled; replacement order created referencing O1 Paid amount carried over as credit — NO refund transaction created | I62: No | J62: Pass | M62: ✅ Pass (không đổi)
A63: L1-ORD-47 | B63: EP-Invalid | C63: Non-manager attempts to approve paid-order cancellation -> forbidden | D63: FT-08 NAC-05; NFR-SEC03 | E63: P1 | F63: Caller role = Sales Staff | G63: orderService.ApproveCancelAndCreateReplacementAsync(O1, salesId, dto) | H63: Throws forbidden (403); no replacement created | I63: Yes | J63: Pass | L63: kiểm tra role Manager nằm ở controller [Authorize(Roles=...)], không unit-test được trong service — cần L3 API test. | M63: 🔒 CẦN L3 (không phải bug) ApproveCancelAndCreateReplacementAsync (2739-2860) không tự check role trong service, nhưng [Authorize(Roles="SalesManager,Admin")] ở DeliveryController.cs:124 đã chặn. Có test L3: VietTien.IntegrationTests/RoleGateTests.cs:21-42 (L1_ORD_47_...).
A64: ▶ Block: ⊕ v2.1 — Đổi/trả hàng | CreateReturnExchangeRequestAsync, ProcessReturnExchangeRequestAsync, CreateExchangeReplacementOrderAsync | FT-08
A65: L1-ORD-48 | B65: EP-Valid | C65: Khách tạo yêu cầu đổi/trả cho dòng hàng đã giao -> lưu kèm bằng chứng | D65: FT-08 AC-05; BR-019 | E65: P1 | F65: Đơn O1 đã Delivered; dòng P1 số lượng giao = 5; ảnh bằng chứng đính kèm | G65: orderService.CreateReturnExchangeRequestAsync(U1, O1, dto{P1, qty=2, reason, evidence}) | H65: Yêu cầu lưu trạng thái chờ duyệt; số lượng yêu cầu = 2 KHÔNG thay đổi tồn kho ở bước này | I65: No | J65: Pass | M65: ✅ Pass (không đổi)
A66: L1-ORD-49 | B66: EP-Invalid + BVA-Max+1 | C66: Số lượng đổi/trả > số lượng đã giao -> từ chối | D66: FT-08 BV-03 | E66: P1 | F66: Đơn O1 giao P1 = 5 | G66: orderService.CreateReturnExchangeRequestAsync(U1, O1, dto{P1, qty=6}) | H66: Từ chối; không tạo yêu cầu [Theory] cũng test qty = 0 và qty = 5 (hợp lệ) | I66: Yes | J66: Pass | M66: ✅ Pass (không đổi)
A67: L1-ORD-50 | B67: EP-Invalid | C67: Tạo yêu cầu đổi/trả trên đơn CHƯA giao -> từ chối | D67: FT-08 AC-05 | E67: P1 | F67: Đơn O1 trạng thái In Delivery | G67: orderService.CreateReturnExchangeRequestAsync(U1, O1, dto) | H67: Từ chối theo state guard; không tạo yêu cầu | I67: Yes | J67: Pass | M67: ✅ Pass (không đổi)
A68: L1-ORD-51 | B68: EP-Invalid | C68: Khách tạo yêu cầu trên đơn của khách khác -> forbidden | D68: FT-08 NAC-05; NFR-SEC03 | E68: P1 | F68: Đơn O9 thuộc khách U9 | G68: orderService.CreateReturnExchangeRequestAsync(U1, O9, dto) | H68: Ném forbidden/not-found; không lộ dữ liệu đơn O9 | I68: Yes | J68: Pass | M68: ✅ ĐÃ FIX OrderService.cs:2376-2385 check CustomerProfile.UserId == requestedByUserId, throw UnauthorizedAccessException nếu không khớp.
A69: L1-ORD-52 | B69: State-Valid | C69: Manager duyệt yêu cầu -> chuyển bước thu hồi hàng | D69: FT-08 AC-05; BR-019 | E69: P1 | F69: Yêu cầu R1 đang chờ duyệt; caller có vai trò Sales Manager | G69: orderService.ProcessReturnExchangeRequestAsync(R1, managerId, dto{approve=true}) | H69: R1 = Approved; tạo nhiệm vụ thu hồi hàng; khách được thông báo | I69: No | J69: Pass | M69: ✅ Pass (không đổi)
A70: L1-ORD-53 | B70: EP-Invalid | C70: Sales Staff tự duyệt yêu cầu đổi/trả -> forbidden | D70: FT-08 NAC-05; NFR-SEC03 | E70: P1 | F70: Caller vai trò Sales Staff | G70: orderService.ProcessReturnExchangeRequestAsync(R1, salesId, dto{approve=true}) | H70: Ném forbidden (403); trạng thái R1 không đổi | I70: Yes | J70: Pass | L70: Phân quyền ở [Authorize] Controller — chuyển L3 | M70: 🔒 CẦN L3 (không phải bug) ProcessReturnExchangeRequestAsync (2454-2471) không tự check role, nhưng [Authorize(Roles="SalesManager,Admin")] ở OrderController.cs:485 đã chặn. Có test L3: VietTien.IntegrationTests/RoleGateTests.cs:44-65 (L1_ORD_53_...).
A71: L1-ORD-54 | B71: State-Invalid | C71: Duyệt lại yêu cầu đã ở trạng thái kết thúc -> conflict | D71: FT-08 NAC-05 | E71: P1 | F71: R1 = Approved (hoặc Rejected) | G71: orderService.ProcessReturnExchangeRequestAsync(R1, managerId, dto) | H71: Ném conflict; không tạo nhiệm vụ thu hồi lần 2 | I71: Yes | J71: Pass | M71: ✅ Pass (không đổi)
A72: L1-ORD-55 | B72: EP-Valid | C72: Đổi CÙNG mã hàng -> giữ nguyên đơn giá gốc | D72: FT-08 AC-05; BR-043 | E72: P1 | F72: R1 approved, đổi P1 sang chính P1; đơn giá gốc 50.000 | G72: orderService.CreateExchangeReplacementOrderAsync(R1, staffId, dto) | H72: Đơn thay thế dùng đúng đơn giá 50.000 (không áp giá hiện hành) Không phát sinh khoản phải thu thêm | I72: No | J72: Pass | M72: ✅ Pass (không đổi)
A73: L1-ORD-56 | B73: EP-Valid | C73: Đổi SANG mã hàng khác -> áp giá hiện hành + xử lý chênh lệch | D73: FT-08 AC-03; BR-042; BR-043 | E73: P1 | F73: R1 approved, đổi P1 (50.000) sang P2 (70.000) | G73: orderService.CreateExchangeReplacementOrderAsync(R1, staffId, dto{P2}) | H73: Đơn thay thế dùng giá hiện hành của P2 Chênh lệch dương -> đơn ở trạng thái còn phải thu; chênh lệch âm -> tạo credit | I73: No | J73: Pass | M73: ✅ Pass (không đổi)
A74: ▶ Block: ⊕ v2.1 — Thu hồi hàng | GetPendingPickupsAsync, SchedulePickupAsync, ConfirmPickupAsync | FT-08
A75: L1-ORD-57 | B75: EP-Valid | C75: Danh sách chờ thu hồi chỉ chứa yêu cầu đã duyệt, chưa thu | D75: FT-08 AC-05 | E75: P2 | F75: 3 yêu cầu: 1 chờ duyệt, 1 đã duyệt chưa thu, 1 đã thu xong | G75: orderService.GetPendingPickupsAsync(query) | H75: Chỉ trả đúng 1 mục (đã duyệt, chưa thu) | I75: No | J75: Pass | M75: ✅ Pass (không đổi)
A76: L1-ORD-58 | B76: EP-Valid | C76: Lên lịch thu hồi -> lưu ngày/ca và người phụ trách | D76: FT-08 AC-05; FT-07 BV-01 | E76: P2 | F76: Yêu cầu R1 đã duyệt | G76: orderService.SchedulePickupAsync(R1, staffId, dto{date, shift}) | H76: Lịch thu hồi được lưu; khách nhận thông báo | I76: No | J76: Pass | M76: ✅ Pass (không đổi)
A77: L1-ORD-59 | B77: EP-Valid | C77: Xác nhận đã thu hồi -> hàng vào khu cách ly, KHÔNG vào tồn bán được | D77: FT-08 AC-05; BR-019; BR-032 | E77: P1 | F77: R1 đã lên lịch; tồn khả dụng P1 = 10 | G77: orderService.ConfirmPickupAsync(R1, staffId, dto{qty=2}) | H77: Tồn khả dụng P1 VẪN = 10 (hàng vào Quarantine, không cộng vào Available) Ghi nhận số lượng thu hồi thực tế | I77: No | J77: Pass | M77: ✅ Pass (không đổi)
A78: L1-ORD-60 | B78: EP-Invalid | C78: Xác nhận thu hồi khi chưa lên lịch -> từ chối | D78: FT-08 NAC-04 | E78: P2 | F78: R1 đã duyệt nhưng chưa có lịch thu hồi | G78: orderService.ConfirmPickupAsync(R1, staffId, dto) | H78: Từ chối theo state guard; không đổi tồn kho | I78: Yes | J78: Pass | M78: ✅ Pass (không đổi)
A79: ▶ Block: ⊕ v2.1 — Đổi chữ ký method (thêm tham số caller) | GenerateSePayQrAsync, GetPaymentStatusAsync, UploadInvoicePdfAsync, GetSalesDashboardStatsAsync
A80: L1-ORD-61 | B80: EP-Invalid | C80: GenerateSePayQr: khách khác gọi trên đơn không thuộc mình -> forbidden | D80: FT-01 NAC-05; NFR-SEC03 | E80: P1 | F80: Đơn O9 thuộc U9 | G80: orderService.GenerateSePayQrAsync(O9, callerUserId=U1, callerRole='Customer') | H80: Ném forbidden; KHÔNG sinh QR và không lộ mã tham chiếu | I80: Yes | J80: Pass | M80: ✅ Pass (không đổi)
A81: L1-ORD-62 | B81: EP-Invalid | C81: GetPaymentStatus: truy cập chéo khách hàng -> forbidden | D81: FT-01 NAC-05; NFR-SEC03 | E81: P1 | F81: Đơn O9 thuộc U9 | G81: orderService.GetPaymentStatusAsync(O9, callerUserId=U1, callerRole='Customer') | H81: Ném forbidden; không trả trạng thái thanh toán | I81: Yes | J81: Pass | M81: ✅ Pass (không đổi)
A82: L1-ORD-63 | B82: EP-Valid | C82: GetPaymentStatus: Sales Manager xem được đơn ngoài phạm vi khách | D82: NFR-SEC03 | E82: P2 | F82: Đơn O9 thuộc U9 | G82: orderService.GetPaymentStatusAsync(O9, callerUserId=M1, callerRole='SalesManager') | H82: Trả về trạng thái bình thường (vai trò nội bộ được phép) | I82: No | J82: Pass | M82: ✅ Pass (không đổi)
A83: L1-ORD-64 | B83: EP-Invalid | C83: UploadInvoicePdf: sai vai trò -> forbidden | D83: NFR-SEC03; NFR-SEC07 | E83: P1 | F83: Caller vai trò Customer | G83: orderService.UploadInvoicePdfAsync(O1, file, callerUserId=U1, callerRole='Customer') | H83: Ném forbidden; file không được lưu | I83: Yes | J83: Pass | M83: ✅ Pass (không đổi)
A84: L1-ORD-65 | B84: EP-Valid | C84: GetSalesDashboardStats: scopedSalesStaffId lọc đúng phạm vi | D84: FT-09 AC-01; NAC-01 | E84: P1 | F84: S1 có 3 đơn, S2 có 2 đơn | G84: orderService.GetSalesDashboardStatsAsync(scopedSalesStaffId=S1) | H84: Số liệu chỉ tính 3 đơn của S1; không lẫn đơn của S2 | I84: No | J84: Pass | M84: ✅ Pass (không đổi)
A85: L1-ORD-66 | B85: EP-Valid | C85: GetSalesDashboardStats: scopedSalesStaffId = null -> phạm vi toàn nhóm (Manager) | D85: FT-09 AC-01 | E85: P2 | F85: S1 có 3 đơn, S2 có 2 đơn | G85: orderService.GetSalesDashboardStatsAsync(scopedSalesStaffId: null) | H85: Số liệu tính đủ 5 đơn | I85: No | J85: Pass | M85: ✅ Pass (không đổi)
A86: ▶ Block: ⊕ v2.1 — Truy vấn công khai & thống kê | TrackOrderPublicAsync, GetSpendingStatsAsync, GetDeliveryOrdersAsync, GetSalesOrdersAsync
A87: L1-ORD-67 | B87: EP-Valid | C87: Tra cứu đơn công khai bằng mã -> chỉ trả thông tin không nhạy cảm | D87: FT-01 AC-05; NFR-SEC06 | E87: P1 | F87: Đơn O1 tồn tại | G87: orderService.TrackOrderPublicAsync('ORD-xxxx') | H87: Trả trạng thái + mốc thời gian KHÔNG trả số điện thoại/địa chỉ đầy đủ/giá vốn (PII được mask) | I87: No | J87: Pass | M87: ✅ ĐÃ FIX OrderService.cs:1317-1318 set null CustomerPhone/ShippingAddress cho tra cứu công khai; CostSnapshot không được trả.
A88: L1-ORD-68 | B88: EP-Invalid | C88: Tra cứu mã đơn không tồn tại -> không lộ sự tồn tại | D88: FT-01 NAC-05 | E88: P2 | F88: Không có đơn mã 'ORD-9999' | G88: orderService.TrackOrderPublicAsync('ORD-9999') | H88: Trả not-found chung; không phân biệt được đơn có tồn tại hay không | I88: Yes | J88: Pass | M88: ✅ Pass (không đổi)
A89: L1-ORD-69 | B89: EP-Valid | C89: Thống kê chi tiêu chỉ tính đơn của chính khách và không tính đơn huỷ | D89: FT-09 AC-01 | E89: P2 | F89: U1 có 2 đơn Delivered + 1 đơn Cancelled; U9 có 1 đơn | G89: orderService.GetSpendingStatsAsync(U1, query) | H89: Chỉ cộng 2 đơn Delivered của U1 | I89: No | J89: Pass | M89: ✅ Pass (không đổi)
A90: L1-ORD-70 | B90: EP-Valid | C90: Danh sách đơn giao cho Sales chỉ gồm đơn thuộc phạm vi phụ trách | D90: FT-04 AC-01; NFR-SEC03 | E90: P1 | F90: S1 phụ trách U1; S2 phụ trách U9 | G90: orderService.GetDeliveryOrdersAsync(S1, query) | H90: Chỉ trả đơn của khách do S1 phụ trách | I90: No | J90: Pass | M90: ✅ Pass (không đổi)
A91: L1-ORD-71 | B91: EP-Invalid | C91: GetSalesOrderDetail: Sales xem đơn ngoài phạm vi -> forbidden | D91: NFR-SEC03; FT-04 NAC-04 | E91: P1 | F91: Đơn O9 thuộc khách của S2 | G91: orderService.GetSalesOrderDetailAsync(S1, O9) | H91: Ném forbidden/not-found | I91: Yes | J91: Pass | L91: GetSalesOrderDetailAsync không có tham số caller — chuyển L3 | M91: ✅ ĐÃ FIX OrderService.cs:1481,1501-1506 nhận Guid? salesStaffId, throw nếu khác order.SalesStaffId — đúng theo commit 4517274.
A92: ▶ Template Row — copy khi thêm case mới
A93: L1-XX-[NN] | B93: [BC-TRUE | BC-FALSE | CC | EP-Valid | EP-Invalid | BVA-* | State-* | Guard-* | Concurrency | Idempotency | Atomicity] | C93: [Branch / condition / partition] | D93: [FT-xx AC/NAC/BV-xx; BR-xxx; NFR-xxx] | E93: P2 | F93: [Arrange: state + _mock.Setup(...)] | G93: service.Method(params) | H93: [result.Should().Be(...) / Throws / _mock.Verify(..., Times.Never)] | I93: No | J93: Not Run
A95: ▶ Block: ⊕ v2.2 — Ngưỡng giao hỏng | DELIVERY_FAILURE_MANAGER_THRESHOLD vs hard-code | FT-07 BV-03; BR-040
A96: L1-ORD-72 | B96: BVA | C96: FailedDeliveryCount tại 2 / 3 / 4 -> chặn giao và escalate | D96: FT-07 BV-03; BR-040 | E96: P1 | F96: [Theory] đơn O1 có FailedDeliveryCount = 2 / 3 trước khi ghi nhận lần hỏng tiếp theo | G96: orderService.RecordDeliveryResultAsync(O1, staffId, dto{failed:true, reasonCode}) | H96: Khi FailedDeliveryCount >= 3: IsBlockedForDelivery = true + tạo escalation cho Sales Manager Dưới 3: vẫn cho lên lịch giao lại | I96: Yes | J96: Pass | M96: ✅ Pass (không đổi)
A97: L1-ORD-73 | B97: EP-Invalid | C97: Ngưỡng giao hỏng KHÔNG đọc từ SystemConfig | D97: FT-07 BV-03; BR-040; BR-050 | E97: P1 | F97: Đổi SystemConfig 'DELIVERY_FAILURE_MANAGER_THRESHOLD' từ 3 thành 5 Đơn O1 có FailedDeliveryCount = 3 | G97: orderService.RecordDeliveryResultAsync(O1, staffId, dto{failed:true}) | H97: KỲ VỌNG THEO SPEC: chưa chặn (vì ngưỡng đã đổi thành 5) HÀNH VI HIỆN TẠI: vẫn chặn vì code hard-code >= 3 | I97: Yes | J97: Pass | M97: ✅ ĐÃ FIX OrderService.cs:2274-2277 đọc DELIVERY_FAILURE_MANAGER_THRESHOLD qua ISystemConfigService, fallback 3 chỉ khi parse lỗi.
A99: ▶ Block: ⊕ v2.3 — Đối soát webhook: nhánh trả THIẾU | OrderService.cs ~L314 | FT-03 BV-01; NAC-01; BR-009
A100: L1-ORD-74 | B100: BVA-Min-1 + Error Path | C100: transferAmount = FinalPayment - 1 -> hiện tại return IM LẶNG | D100: FT-03 BV-01; NAC-01; BR-009 | E100: P1 | F100: Đơn O1 PaymentStatus = Pending, FinalPayment = 5.000.000đ Webhook chữ ký hợp lệ, transferAmount = 4.999.999đ | G100: orderService.ProcessSePayWebhookAsync(payload, validToken) | H100: KỲ VỌNG THEO SRS: ghi PaymentException/SepayWebhookLog + tạo cảnh báo cho Sales Manager; PaymentStatus giữ Pending HÀNH VI HIỆN TẠI: hàm `return;` im lặng — không log, không cảnh báo, không ai biết khách đã chuyển thiếu | I100: Yes | J100: Pass | L100: ℹ Đối chiếu L2: OrderService.cs:323 nay dùng `!=` thay cho `<` — L2-PAY-03 xanh cả 3 nhánh trên SQL Server thật. Nếu bản build hiện tại đã có thay đổi đó thì case này chuyển Pass khi chạy lại. | M100: ✅ ĐÃ FIX OrderService.cs:337 dùng phép so sánh != thay vì <, tách nhánh UNDERPAYMENT ghi PaymentException + cảnh báo (341-345), không còn return im lặng.
A101: L1-ORD-75 | B101: BVA-Max+1 | C101: transferAmount = FinalPayment + 1 -> hiện tại vẫn ghi nhận Paid | D101: FT-03 BV-01; NAC-01 | E101: P1 | F101: Đơn O1 FinalPayment = 5.000.000đ; webhook transferAmount = 5.000.001đ | G101: orderService.ProcessSePayWebhookAsync(payload, validToken) | H101: KỲ VỌNG THEO SRS BV-01 (khớp CHÍNH XÁC): từ chối + đưa vào danh sách đối soát HÀNH VI HIỆN TẠI: điều kiện dùng `<` nên trả THỪA vẫn set Paid | I101: Yes | J101: Pass | L101: ℹ Như L1-ORD-74 — hồi quy chéo bởi L2-PAY-03. | M101: ✅ ĐÃ FIX Cùng vị trí OrderService.cs:337-351, nhánh OVERPAYMENT bị từ chối + ghi đối soát, không tự set Paid.
A102: L1-ORD-76 | B102: EP-Valid | C102: transferAmount = FinalPayment (khớp chính xác) -> Paid | D102: FT-03 AC-02; BV-01 | E102: P1 | F102: Đơn O1 FinalPayment = 5.000.000đ; webhook = 5.000.000đ, chữ ký hợp lệ | G102: orderService.ProcessSePayWebhookAsync(payload, validToken) | H102: PaymentStatus = Paid (2); tạo đúng 1 PaymentTransaction Điểm giữa của [Theory] 3 mốc: -1 / khớp / +1 | I102: No | J102: Pass | M102: ✅ Pass (không đổi)

Sheet QuotationService
A1: QuotationService | methods: CreateQuotationFromCartAsync, PickUpQuotationAsync, CreateVersionAsync, ManagerReviewVersionAsync, CeoReviewVersionAsync, CustomerDecisionAsync, CancelQuotationAsync, SendMessageAsync | Mock: IQuotationRepository, ICartRepository, IUserRepository, IUnitOfWork
A2: HOW TO USE: (1) Đọc Introduction (2) Trace theo SRS v2 (Part 3 + RTW Sheet 3/6/7) (3) Cập nhật Status sau mỗi lần chạy dotnet test / vitest (4) Ghi Defect ID khi Fail
A4: Test ID | B4: Coverage Technique | C4: Covers (Decision/Condition) | D4: SRS Reference | E4: Priority | F4: Given (Precondition / Mock Setup) | G4: When (Input / Act) | H4: Then (Expected Output / Assert) | I4: Negative? | J4: Status | K4: Defect ID | L4: Notes | M4: Fix Status
A5: ▶ Block: CreateQuotationFromCartAsync() | FT-02 SB-2; 4.4.3 row 1; BR-04
A6: L1-QUO-01 | B6: Guard-TRUE | C6: Cart >= 100M AND no saved negotiated price -> Quotation 'Requested', Sales notified | D6: FT-02 AC-03; BV-01; BR-026 | E6: P1 | F6: Mock: cart total = 120,000,000; profile has no negotiated price | G6: quotationService.CreateQuotationFromCartAsync(U1, request) | H6: quotationRepo.CreateAsync() called once; Status = Requested Sales notification triggered | I6: No | J6: Pass | M6: ✅ Pass (không đổi)
A7: L1-QUO-02 | B7: Guard-FALSE | C7: Cart < 100M -> quotation request rejected | D7: FT-02 NAC-02; BV-01 | E7: P1 | F7: Mock: cart total = 80,000,000 | G7: quotationService.CreateQuotationFromCartAsync(U1, request) | H7: Rejected (below threshold); CreateAsync NEVER called | I7: Yes | J7: Pass | M7: ✅ Pass (không đổi)
A8: ▶ Block: PickUpQuotationAsync() | 4.4.3 row 2
A9: L1-QUO-03 | B9: State-Valid | C9: Requested -> Under Sales Review when Sales picks up | D9: FT-02 AC-04; BR-027 | E9: P1 | F9: Mock: quotation Q1 Status = Requested, no assigned staff | G9: quotationService.PickUpQuotationAsync(Q1, staffS1) | H9: Status = Under Sales Review; AssignedSalesStaff = S1 COGS & margin data attached for pricing support | I9: No | J9: Pass | M9: ✅ Pass (không đổi)
A10: L1-QUO-04 | B10: EP-Invalid | C10: Pick up a quotation already assigned to another staff -> rejected | D10: FT-02 NAC-05; BR-027 | E10: P1 | F10: Q1 Status = Under Sales Review, AssignedSalesStaff = S2 | G10: quotationService.PickUpQuotationAsync(Q1, staffS1) | H10: Throws conflict; assignment unchanged (still S2) | I10: Yes | J10: Pass | M10: ✅ Pass (không đổi)
A11: ▶ Block: CreateVersionAsync() | 4.4.3 row 3
A12: L1-QUO-05 | B12: State-Valid | C12: Sales submits proposed price -> Waiting Admin Approval | D12: FT-02 AC-04; BR-007; BR-027 | E12: P1 | F12: Q1 Under Sales Review, assigned to S1 | G12: quotationService.CreateVersionAsync(Q1, S1, {proposedPrice}) | H12: New QuotationVersion persisted; Status = Waiting Admin Approval Routed to Approval Centre | I12: No | J12: Pass | M12: ✅ Pass (không đổi)
A13: L1-QUO-06 | B13: EP-Invalid | C13: Staff not assigned to the quotation submits a version -> forbidden | D13: FT-02 NAC-05; BR-027 | E13: P1 | F13: Q1 assigned to S2 | G13: quotationService.CreateVersionAsync(Q1, S1, req) | H13: Throws forbidden (403); no version created | I13: Yes | J13: Pass | M13: ✅ Pass (không đổi)
A14: ▶ Block: ManagerReviewVersionAsync() / CeoReviewVersionAsync() | 4.4.3 rows 4-5; BR-04
A15: L1-QUO-07 | B15: State-Valid | C15: Approval by authorised approver -> Proposed to Customer | D15: FT-02 AC-04; BR-027 | E15: P1 | F15: Q1 Waiting Admin Approval; reviewer has Manager/CEO role | G15: quotationService.ManagerReviewVersionAsync(Q1, mgr, {approve=true}) | H15: Version approved; proposal returned to customer Status advances per approval chain | I15: No | J15: Pass | M15: ✅ Pass (không đổi)
A16: L1-QUO-08 | B16: State-Valid | C16: Rejection -> back to Under Sales Review with reason | D16: FT-02 AC-04; BR-027 | E16: P1 | F16: Q1 Waiting Admin Approval | G16: quotationService.ManagerReviewVersionAsync(Q1, mgr, {approve=false, reason}) | H16: Status = Under Sales Review; rejection reason stored and visible to Sales | I16: No | J16: Pass | M16: ✅ Pass (không đổi)
A17: L1-QUO-09 | B17: EP-Invalid | C17: Approval attempted by non-approver role -> HTTP 403 | D17: FT-02 NAC-05; NFR-SEC03 | E17: P1 | F17: Caller role = Sales Staff | G17: quotationService.CeoReviewVersionAsync(Q1, salesUser, req) | H17: Throws forbidden (403); status unchanged | I17: Yes | J17: Pass | L17: role gate được enforce ở QuotationController [Authorize], không nằm trong service — cần integration test (L2/L3). | M17: 🔒 CẦN L3 (không phải bug) CeoReviewVersionAsync (253-286) không tự check role, nhưng [Authorize(Roles="CEO")] ở QuotationController.cs:187 đã chặn. Có test L3: VietTien.IntegrationTests/RoleGateTests.cs:91-112 (L1_QUO_09_...).
A18: ▶ Block: CustomerDecisionAsync() | 4.4.3 rows 6-8; FT-02 AC-06, NAC-06, BV-03
A19: L1-QUO-10 | B19: State-Valid | C19: Customer accepts (round <= 5) -> Accepted, negotiated price saved to account | D19: FT-02 AC-05; BR-026 | E19: P1 | F19: Q1 Proposed to Customer, round = 2 | G19: quotationService.CustomerDecisionAsync(Q1, U1, {accept=true}) | H19: Status = Accepted (terminal) Negotiated price persisted on CustomerProfile for future >= 100M orders | I19: No | J19: Pass | M19: ✅ Pass (không đổi)
A20: L1-QUO-11 | B20: BVA-Max | C20: Reject at round < 5 -> next negotiation round opens | D20: FT-02 AC-04; NAC-04 | E20: P1 | F20: Q1 Proposed to Customer, round = 4 | G20: quotationService.CustomerDecisionAsync(Q1, U1, {accept=false}) | H20: Status = Under Sales Review; round counter = 5 Negotiation continues | I20: No | J20: Pass | M20: ✅ Pass (không đổi)
A21: L1-QUO-12 | B21: BVA-Max+1 | C21: 5th consecutive rejection -> Cancelled, further rounds blocked | D21: FT-02 AC-04; NAC-04 | E21: P1 | F21: Q1 Proposed to Customer, round = 5 | G21: quotationService.CustomerDecisionAsync(Q1, U1, {accept=false}) | H21: Status = Cancelled; no round 6 permitted Escalation/notification recorded | I21: Yes | J21: Pass | L21: giới hạn 5 vòng đàm phán (BV-03) chưa được cài đặt trong QuotationService — spec gap, ghi nhận vào Notes. | M21: ✅ ĐÃ FIX QuotationService.cs:288,290,319-330 MaxNegotiationRounds=5; ở vòng thứ 5 bị từ chối thì set Cancelled, chặn vòng 6.
A22: L1-QUO-13 | B22: EP-Invalid | C22: Decision by a customer who does not own the quotation -> forbidden | D22: FT-02 NAC-05; NFR-SEC03 | E22: P1 | F22: Q1 belongs to customer U9 | G22: quotationService.CustomerDecisionAsync(Q1, U1, req) | H22: Throws forbidden/not-found; status unchanged | I22: Yes | J22: Pass | M22: ✅ Pass (không đổi)
A23: ▶ Block: CancelQuotationAsync() | 4.4.3 terminal-state rules
A24: L1-QUO-14 | B24: State-Valid | C24: Customer cancels an open quotation -> Cancelled | D24: FT-02 NAC-05 | E24: P2 | F24: Q1 Status = Requested, owner U1 | G24: quotationService.CancelQuotationAsync(Q1, U1) | H24: Status = Cancelled; Sales notified | I24: No | J24: Pass | M24: ✅ Pass (không đổi)
A25: L1-QUO-15 | B25: State-Invalid | C25: Cancel an Accepted quotation -> conflict (terminal state) | D25: FT-02 NAC-05; BR-007 | E25: P1 | F25: Q1 Status = Accepted | G25: quotationService.CancelQuotationAsync(Q1, U1) | H25: Throws conflict (409) 'quotation closed'; negotiated price remains saved | I25: Yes | J25: Pass | M25: ✅ Pass (không đổi)
A26: ▶ Block: SendMessageAsync() / GetMessagesAsync()
A27: L1-QUO-16 | B27: EP-Valid | C27: Participant sends negotiation message -> persisted and returned in thread | D27: FT-02 AC-04; BR-020; NFR-P04 | E27: P2 | F27: Q1 open; sender = assigned Sales S1 | G27: quotationService.SendMessageAsync(Q1, S1, {content}) | H27: quotationRepo.AddMessageAsync() called once; DTO returned with sender info | I27: No | J27: Pass | M27: ✅ Pass (không đổi)
A28: L1-QUO-17 | B28: EP-Invalid | C28: Non-participant reads quotation messages -> forbidden | D28: FT-02 NAC-05; NFR-SEC03 | E28: P1 | F28: U5 is neither owner nor assigned staff of Q1 | G28: quotationService.GetMessagesAsync(Q1, U5, 'Customer') | H28: Throws forbidden; no messages returned | I28: Yes | J28: Pass | M28: ✅ Pass (không đổi)
A29: ▶ Template Row — copy khi thêm case mới
A30: L1-XX-[NN] | B30: [BC-TRUE | BC-FALSE | CC | EP-Valid | EP-Invalid | BVA-* | State-* | Guard-* | Concurrency | Idempotency | Atomicity] | C30: [Branch / condition / partition] | D30: [FT-xx AC/NAC/BV-xx; BR-xxx; NFR-xxx] | E30: P2 | F30: [Arrange: state + _mock.Setup(...)] | G30: service.Method(params) | H30: [result.Should().Be(...) / Throws / _mock.Verify(..., Times.Never)] | I30: No | J30: Not Run

Sheet ManualPaymentService
A1: ManualPaymentService | methods: ManualConfirmAsync, RetryAllocationAsync, GetExceptionsAsync | EF Core InMemory (injects ApplicationDbContext)
A2: HOW TO USE: (1) Đọc Introduction (2) Trace theo SRS v2 (Part 3 + RTW Sheet 3/6/7) (3) Cập nhật Status sau mỗi lần chạy dotnet test / vitest (4) Ghi Defect ID khi Fail
A4: Test ID | B4: Coverage Technique | C4: Covers (Decision/Condition) | D4: SRS Reference | E4: Priority | F4: Given (Precondition / Mock Setup) | G4: When (Input / Act) | H4: Then (Expected Output / Assert) | I4: Negative? | J4: Status | K4: Defect ID | L4: Notes | M4: Fix Status
A5: ▶ Block: ManualConfirmAsync() | FT-03 AC-03, NAC-02; 4.4.2 rows 5-6; BR-08
A6: L1-MP-01 | B6: State-Valid | C6: Awaiting Manual Verify + matching bank record -> Paid + 'PAID - DO NOT COLLECT' lock | D6: FT-03 AC-05; NAC-03; BR-016 | E6: P1 | F6: Order O1 'Awaiting Manual Verify'; request contains verified bank transfer reference | G6: manualPaymentService.ManualConfirmAsync(O1, req, adminId) | H6: Payment status = Paid (permanently locked) PaidFlag set for delivery invoice; confirmedBy recorded | I6: No | J6: Pass | M6: ✅ Pass (không đổi)
A7: L1-MP-02 | B7: State-Invalid | C7: Manual confirm with NO matching transfer record -> rejected, temp order cancelled | D7: FT-03 NAC-04; BR-016 | E7: P1 | F7: Order O1 'Awaiting Manual Verify'; manual override log empty | G7: manualPaymentService.ManualConfirmAsync(O1, req{noBankRef}, adminId) | H7: Confirmation rejected (maps to 422) Order cancelled; reserved stock released | I7: Yes | J7: Pass | M7: ✅ Pass (không đổi)
A8: L1-MP-03 | B8: State-Invalid | C8: Manual confirm on an already-Paid order -> conflict | D8: FT-03 NAC-02; BR-016; BR-029 | E8: P1 | F8: Order O1 Paid | G8: manualPaymentService.ManualConfirmAsync(O1, req, adminId) | H8: Throws conflict (409); payment record unchanged No duplicate ledger entry | I8: Yes | J8: Pass | M8: ✅ Pass (không đổi)
A9: ▶ Block: RetryAllocationAsync() / GetExceptionsAsync()
A10: L1-MP-04 | B10: EP-Valid | C10: Retry allocation of an unmatched SePay transaction -> re-matched to correct order | D10: FT-03 AC-03; AC-05 | E10: P2 | F10: Exception item E1 (webhook arrived without matched order); order now identifiable | G10: manualPaymentService.RetryAllocationAsync(O1, adminId, note) | H10: Transaction allocated to O1; removed from exception list; note stored | I10: No | J10: Pass | M10: ✅ Pass (không đổi)
A11: L1-MP-05 | B11: EP-Valid | C11: GetExceptions returns ONLY unresolved SePay exceptions | D11: FT-03 AC-03 | E11: P2 | F11: DB: 2 unresolved + 1 resolved exception items | G11: manualPaymentService.GetExceptionsAsync() | H11: Returns exactly the 2 unresolved items | I11: No | J11: Pass | M11: ✅ Pass (không đổi)
A12: ▶ Template Row — copy khi thêm case mới
A13: L1-XX-[NN] | B13: [BC-TRUE | BC-FALSE | CC | EP-Valid | EP-Invalid | BVA-* | State-* | Guard-* | Concurrency | Idempotency | Atomicity] | C13: [Branch / condition / partition] | D13: [FT-xx AC/NAC/BV-xx; BR-xxx; NFR-xxx] | E13: P2 | F13: [Arrange: state + _mock.Setup(...)] | G13: service.Method(params) | H13: [result.Should().Be(...) / Throws / _mock.Verify(..., Times.Never)] | I13: No | J13: Not Run

Sheet WarehouseService
A1: WarehouseService | methods: GetOrdersForWarehouseAsync, GetOrderDetailAsync, AcceptOrderAsync, ReportShortageAsync, CompletePickTaskAsync, ConsolidateOrderAsync, HandoverOrderAsync, PostGoodsIssueAsync | EF Core InMemory + Mock: IHubContext<SalesHub>
A2: HOW TO USE: (1) Đọc Introduction (2) Trace theo SRS v2 (Part 3 + RTW Sheet 3/6/7) (3) Cập nhật Status sau mỗi lần chạy dotnet test / vitest (4) Ghi Defect ID khi Fail
A4: Test ID | B4: Coverage Technique | C4: Covers (Decision/Condition) | D4: SRS Reference | E4: Priority | F4: Given (Precondition / Mock Setup) | G4: When (Input / Act) | H4: Then (Expected Output / Assert) | I4: Negative? | J4: Status | K4: Defect ID | L4: Notes | M4: Fix Status
A5: ▶ Block: GetOrdersForWarehouseAsync() | FT-04 BV-03 FIFO; BR-09
A6: L1-WH-01 | B6: EP-Valid | C6: FIFO ordering: order confirmed 08:00 listed before order confirmed 08:05 | D6: FT-05 AC-01; BR-011 | E6: P1 | F6: Order A confirmed 08:00, Order B confirmed 08:05 (both Confirmed) | G6: warehouseService.GetOrdersForWarehouseAsync('pending', 1, 20) | H6: Result[0] = Order A, Result[1] = Order B (strict ascending confirmation time) | I6: No | J6: Pass | M6: ✅ Pass (không đổi)
A7: L1-WH-02 | B7: EP-Valid | C7: tabType filter returns only orders in matching status | D7: FT-05 AC-01 | E7: P2 | F7: Orders in Confirmed, Packing, Packed states | G7: warehouseService.GetOrdersForWarehouseAsync('packing', 1, 20) | H7: Only Packing-state orders returned | I7: No | J7: Pass | M7: ✅ Pass (không đổi)
A8: ▶ Block: AcceptOrderAsync() | 4.4.1 row 4
A9: L1-WH-03 | B9: State-Valid | C9: Confirmed order accepted by Warehouse -> Packing, ticket locked to staff | D9: FT-05 AC-01; AC-04 | E9: P1 | F9: Order O1 Confirmed, stock sufficient | G9: warehouseService.AcceptOrderAsync(O1, whStaffId) | H9: Status = Packing; ticket locked to whStaffId SalesHub notification pushed | I9: No | J9: Pass | M9: ✅ Pass (không đổi)
A10: L1-WH-04 | B10: State-Invalid | C10: Accept an order not in Confirmed state -> conflict | D10: FT-05 NAC-05; BR-021 | E10: P1 | F10: Order O1 status = In Delivery | G10: warehouseService.AcceptOrderAsync(O1, whStaffId) | H10: Throws conflict (409) illegal state transition; no lock created | I10: Yes | J10: Pass | M10: ✅ Pass (không đổi)
A11: ▶ Block: ReportShortageAsync() | 4.4.1 row 6; FT-04 SB-1
A12: L1-WH-05 | B12: State-Valid | C12: Packing + insufficient line item -> Shortage, packing halted, Sales notified | D12: FT-05 NAC-04; BR-032 | E12: P1 | F12: Order O1 Packing; alert lists short SKU + quantities | G12: warehouseService.ReportShortageAsync(O1, staff, alert) | H12: Status = Shortage; packing flow halted Sales notified immediately to contact customer | I12: No | J12: Pass | M12: ✅ Pass (không đổi)
A13: L1-WH-06 | B13: EP-Invalid | C13: Report shortage on an order not in Packing -> rejected | D13: FT-05 NAC-04 | E13: P2 | F13: Order O1 status = Packed | G13: warehouseService.ReportShortageAsync(O1, staff, alert) | H13: Rejected; status unchanged; no notification | I13: Yes | J13: Pass | M13: ✅ Pass (không đổi)
A14: ▶ Block: CompletePickTaskAsync() / ConsolidateOrderAsync() | fulfilment pipeline (v6.0 picking flow)
A15: L1-WH-07 | B15: State-Valid | C15: Complete pick task on a Packing order -> pick completed, next stage enabled | D15: FT-05 AC-04; NAC-04 | E15: P1 | F15: Order O1 Packing, pick task locked to staff W1 | G15: warehouseService.CompletePickTaskAsync(O1, W1) | H15: Pick task marked completed; order eligible for consolidation Progress notification pushed | I15: No | J15: Pass | M15: ✅ Pass (không đổi)
A16: L1-WH-08 | B16: EP-Invalid | C16: Complete pick task by a staff who does not own the lock -> rejected | D16: FT-05 NAC-05; NFR-SEC03 | E16: P1 | F16: Pick task locked to W2 | G16: warehouseService.CompletePickTaskAsync(O1, W1) | H16: Throws forbidden/conflict; task state unchanged | I16: Yes | J16: Pass | M16: ✅ Pass (không đổi)
A17: L1-WH-09 | B17: State-Valid | C17: Consolidate after all pick tasks complete -> order consolidated/Packed | D17: FT-05 AC-04; AC-03; BR-012 | E17: P2 | F17: Order O1 with all pick tasks completed | G17: warehouseService.ConsolidateOrderAsync(O1, W1) | H17: Order advances to consolidated/Packed; Sales notified ready for dispatch | I17: No | J17: Pass | M17: ✅ Pass (không đổi)
A18: ▶ Block: HandoverOrderAsync() / PostGoodsIssueAsync() | FT-04 AC-02, NAC-03; BV-02
A19: L1-WH-10 | B19: EP-Valid | C19: Handover with signature -> HandoverRecord created, order released to delivery | D19: FT-05 AC-05; BV-03; BR-034 | E19: P2 | F19: Order O1 Packed/consolidated; signature payload provided | G19: warehouseService.HandoverOrderAsync(O1, W1, signatureBase64) | H19: HandoverRecord persisted with signature + staff + timestamp Order released to delivery scheduling | I19: No | J19: Pass | M19: ✅ Pass (không đổi)
A20: L1-WH-11 | B20: State-Valid | C20: Post goods issue -> finished-goods stock decremented atomically | D20: FT-05 AC-05; BV-01; BV-02; BR-032; NFR-A05 | E20: P1 | F20: Order O1 lines: P1 qty=4; stock P1 = 10 | G20: warehouseService.PostGoodsIssueAsync(O1, W1) | H20: Stock P1 = 6; StockTransaction logged Decrement + status update in ONE transaction | I20: No | J20: Pass | M20: ✅ Pass (không đổi)
A21: L1-WH-12 | B21: EP-Invalid | C21: Post goods issue when stock would go negative -> blocked, no partial decrement | D21: FT-05 NAC-01; BV-01; BR-032 | E21: P1 | F21: Order O1 lines: P1 qty=4, P2 qty=2; stock P1=10, P2=1 | G21: warehouseService.PostGoodsIssueAsync(O1, W1) | H21: Rejected: insufficient stock P1 stock still 10 (full rollback — all-or-nothing) | I21: Yes | J21: Pass | M21: ✅ Pass (không đổi)
A22: ▶ Template Row — copy khi thêm case mới
A23: L1-XX-[NN] | B23: [BC-TRUE | BC-FALSE | CC | EP-Valid | EP-Invalid | BVA-* | State-* | Guard-* | Concurrency | Idempotency | Atomicity] | C23: [Branch / condition / partition] | D23: [FT-xx AC/NAC/BV-xx; BR-xxx; NFR-xxx] | E23: P2 | F23: [Arrange: state + _mock.Setup(...)] | G23: service.Method(params) | H23: [result.Should().Be(...) / Throws / _mock.Verify(..., Times.Never)] | I23: No | J23: Not Run

Sheet PurchaseOrderService
A1: PurchaseOrderService | methods: CreateAsync, UpdateDraftAsync, IssueAsync, SendToWarehouseAsync, CancelAsync, ResolveDiscrepancyAsync, ClosePurchaseOrderAsync | EF Core InMemory | ⚠ SRS trace TBD (purchasing domain pending BRD v6.0 scope)
A2: HOW TO USE: (1) Đọc Introduction (2) Trace theo SRS v2 (Part 3 + RTW Sheet 3/6/7) (3) Cập nhật Status sau mỗi lần chạy dotnet test / vitest (4) Ghi Defect ID khi Fail
A4: Test ID | B4: Coverage Technique | C4: Covers (Decision/Condition) | D4: SRS Reference | E4: Priority | F4: Given (Precondition / Mock Setup) | G4: When (Input / Act) | H4: Then (Expected Output / Assert) | I4: Negative? | J4: Status | K4: Defect ID | L4: Notes | M4: Fix Status
A5: ▶ Block: Draft lifecycle: CreateAsync() / UpdateDraftAsync()
A6: L1-PO-01 | B6: EP-Valid | C6: Create PO -> status Draft with line items persisted | D6: FT-06 AC-01 | E6: P2 | F6: Valid request with supplier + 2 line items; caller = CEO | G6: purchaseOrderService.CreateAsync(ceoId, request) | H6: PO persisted; Status = Draft; 2 lines with qty/price as submitted | I6: No | J6: Pass | M6: ✅ Pass (không đổi)
A7: L1-PO-02 | B7: State-Invalid | C7: UpdateDraft on an Issued PO -> rejected | D7: FT-06 NAC-04; BR-021 | E7: P1 | F7: PO-1 Status = Issued | G7: purchaseOrderService.UpdateDraftAsync(PO-1, ceoId, request) | H7: Throws conflict; PO content unchanged | I7: Yes | J7: Pass | M7: ✅ Pass (không đổi)
A8: ▶ Block: IssueAsync() / SendToWarehouseAsync()
A9: L1-PO-03 | B9: State-Valid | C9: Issue a Draft PO -> Issued | D9: FT-06 AC-01 | E9: P1 | F9: PO-1 Status = Draft with >= 1 line | G9: purchaseOrderService.IssueAsync(PO-1, ceoId) | H9: Status = Issued; issue timestamp recorded | I9: No | J9: Pass | M9: ✅ Pass (không đổi)
A10: L1-PO-04 | B10: State-Invalid | C10: Issue a PO not in Draft -> rejected | D10: FT-06 NAC-04 | E10: P1 | F10: PO-1 Status = Cancelled | G10: purchaseOrderService.IssueAsync(PO-1, ceoId) | H10: Throws conflict; status unchanged | I10: Yes | J10: Pass | M10: ✅ Pass (không đổi)
A11: L1-PO-05 | B11: State-Valid | C11: SendToWarehouse on Issued PO -> visible to warehouse for goods receipt | D11: FT-06 AC-01; AC-04 | E11: P2 | F11: PO-1 Status = Issued | G11: purchaseOrderService.SendToWarehouseAsync(PO-1, ceoId) | H11: Status advances to SentToWarehouse; GoodsReceipt creation now allowed | I11: No | J11: Pass | M11: ✅ Pass (không đổi)
A12: ▶ Block: CancelAsync() / ResolveDiscrepancyAsync() / ClosePurchaseOrderAsync()
A13: L1-PO-06 | B13: State-Valid | C13: Cancel a Draft PO -> Cancelled (terminal) | D13: FT-06 AC-01 | E13: P2 | F13: PO-1 Status = Draft | G13: purchaseOrderService.CancelAsync(PO-1, ceoId) | H13: Status = Cancelled; further Issue/Update rejected | I13: No | J13: Pass | M13: ✅ Pass (không đổi)
A14: L1-PO-07 | B14: State-Invalid | C14: Close PO with unresolved receipt discrepancy -> blocked | D14: FT-06 AC-05; NAC-03; BR-036 | E14: P1 | F14: PO-1 has GoodsReceipt with qty discrepancy, not yet resolved | G14: purchaseOrderService.ClosePurchaseOrderAsync(PO-1, ceoId) | H14: Rejected: discrepancy must be resolved first; status unchanged | I14: Yes | J14: Pass | M14: ✅ Pass (không đổi)
A15: ▶ Template Row — copy khi thêm case mới
A16: L1-XX-[NN] | B16: [BC-TRUE | BC-FALSE | CC | EP-Valid | EP-Invalid | BVA-* | State-* | Guard-* | Concurrency | Idempotency | Atomicity] | C16: [Branch / condition / partition] | D16: [FT-xx AC/NAC/BV-xx; BR-xxx; NFR-xxx] | E16: P2 | F16: [Arrange: state + _mock.Setup(...)] | G16: service.Method(params) | H16: [result.Should().Be(...) / Throws / _mock.Verify(..., Times.Never)] | I16: No | J16: Not Run

Sheet GoodsReceiptService
A1: GoodsReceiptService | methods: CreateFromPOAsync, PostReceiptAsync, GetByPurchaseOrderIdAsync | EF Core InMemory | ⚠ SRS trace TBD (purchasing domain)
A2: HOW TO USE: (1) Đọc Introduction (2) Trace theo SRS v2 (Part 3 + RTW Sheet 3/6/7) (3) Cập nhật Status sau mỗi lần chạy dotnet test / vitest (4) Ghi Defect ID khi Fail
A4: Test ID | B4: Coverage Technique | C4: Covers (Decision/Condition) | D4: SRS Reference | E4: Priority | F4: Given (Precondition / Mock Setup) | G4: When (Input / Act) | H4: Then (Expected Output / Assert) | I4: Negative? | J4: Status | K4: Defect ID | L4: Notes | M4: Fix Status
A5: ▶ Block: CreateFromPOAsync()
A6: L1-GR-01 | B6: EP-Valid | C6: Create receipt from a SentToWarehouse PO -> draft receipt with PO lines | D6: FT-06 AC-03; NAC-01; BR-014 | E6: P2 | F6: PO-1 Status = SentToWarehouse with 2 lines | G6: goodsReceiptService.CreateFromPOAsync(PO-1, whStaff, request) | H6: Receipt persisted referencing PO-1; lines mirror PO quantities as expected qty | I6: No | J6: Pass | M6: ✅ Pass (không đổi)
A7: L1-GR-02 | B7: State-Invalid | C7: Create receipt from PO not sent to warehouse -> rejected | D7: FT-06 NAC-01; BR-014 | E7: P1 | F7: PO-1 Status = Draft | G7: goodsReceiptService.CreateFromPOAsync(PO-1, whStaff, request) | H7: Throws conflict; no receipt created | I7: Yes | J7: Pass | M7: ✅ Pass (không đổi)
A8: ▶ Block: PostReceiptAsync()
A9: L1-GR-03 | B9: EP-Valid | C9: Post receipt -> inventory increased atomically by received qty | D9: FT-06 AC-03; BV-01; BR-014 | E9: P1 | F9: Receipt R1 draft: P1 received qty = 50; stock P1 = 10 | G9: goodsReceiptService.PostReceiptAsync(R1, whStaff) | H9: Stock P1 = 60; receipt Status = Posted Inventory + receipt updated in one transaction | I9: No | J9: Pass | M9: ✅ Pass (không đổi)
A10: L1-GR-04 | B10: State-Invalid | C10: Post an already-posted receipt -> rejected (idempotency) | D10: FT-06 NAC-05; BR-029 | E10: P1 | F10: Receipt R1 Status = Posted; stock P1 = 60 | G10: goodsReceiptService.PostReceiptAsync(R1, whStaff) | H10: Throws conflict; stock remains 60 (no double increment) | I10: Yes | J10: Pass | M10: ✅ Pass (không đổi)
A11: ▶ Block: ⊕ v2.1 — Chứng từ & danh sách | UploadProofAsync, GetAllAsync | FT-06; NFR-SEC07
A12: L1-GR-05 | B12: EP-Valid | C12: Upload chứng từ nhận hàng -> lưu URL vào phiếu | D12: FT-06 AC-05; NFR-SEC07 | E12: P2 | F12: Phiếu R1 Draft; mock cloudinary trả url | G12: goodsReceiptService.UploadProofAsync(R1, file) | H12: cloudinary được gọi 1 lần; R1.ProofUrl = url trả về | I12: No | J12: Pass | M12: ✅ Pass (không đổi)
A13: L1-GR-06 | B13: EP-Invalid | C13: Upload file ngoài allowlist / vượt kích thước -> từ chối | D13: NFR-SEC07 | E13: P1 | F13: File .exe hoặc vượt giới hạn cấu hình | G13: goodsReceiptService.UploadProofAsync(R1, badFile) | H13: Từ chối; không gọi cloudinary; không lưu URL | I13: Yes | J13: Pass | M13: ✅ Pass (không đổi)
A14: L1-GR-07 | B14: EP-Valid | C14: GetAll lọc theo trạng thái và phân trang đúng | D14: FT-06 AC-04 | E14: P3 | F14: 5 phiếu: 3 Posted, 2 Draft | G14: goodsReceiptService.GetAllAsync(query{status:'Posted', page:1}) | H14: Trả đúng 3 phiếu Posted; TotalCount = 3 | I14: No | J14: Pass | M14: ✅ Pass (không đổi)
A15: ▶ Template Row — copy khi thêm case mới
A16: L1-XX-[NN] | B16: [BC-TRUE | BC-FALSE | CC | EP-Valid | EP-Invalid | BVA-* | State-* | Guard-* | Concurrency | Idempotency | Atomicity] | C16: [Branch / condition / partition] | D16: [FT-xx AC/NAC/BV-xx; BR-xxx; NFR-xxx] | E16: P2 | F16: [Arrange: state + _mock.Setup(...)] | G16: service.Method(params) | H16: [result.Should().Be(...) / Throws / _mock.Verify(..., Times.Never)] | I16: No | J16: Not Run

Sheet SalesAllocationService
A1: SalesAllocationService | methods: AutoAssignCustomerAsync, AssignUnassignedCustomersAsync, GetMyCustomersAsync, GetMyCustomerDetailAsync, UpdateCustomerNoteAsync, UpdateRoundRobinAsync | EF Core InMemory | ⚠ SRS trace TBD (round-robin allocation not in SRS v1.5)
A2: HOW TO USE: (1) Đọc Introduction (2) Trace theo SRS v2 (Part 3 + RTW Sheet 3/6/7) (3) Cập nhật Status sau mỗi lần chạy dotnet test / vitest (4) Ghi Defect ID khi Fail
A4: Test ID | B4: Coverage Technique | C4: Covers (Decision/Condition) | D4: SRS Reference | E4: Priority | F4: Given (Precondition / Mock Setup) | G4: When (Input / Act) | H4: Then (Expected Output / Assert) | I4: Negative? | J4: Status | K4: Defect ID | L4: Notes | M4: Fix Status
A5: ▶ Block: AutoAssignCustomerAsync() — round-robin
A6: L1-SA-01 | B6: EP-Valid | C6: New customer auto-assigned to next staff in round-robin order | D6: FT-04 AC-02; BV-02; BR-002 | E6: P2 | F6: Staff S1, S2 active; round-robin pointer at S1 | G6: salesAllocationService.AutoAssignCustomerAsync(newUserId) | H6: Customer assigned to S1; pointer advances to S2 | I6: No | J6: Pass | M6: ✅ Pass (không đổi)
A7: L1-SA-02 | B7: EP-Valid | C7: Round-robin wraps: pointer at last staff -> next assignment returns to first | D7: FT-04 BV-02; BR-002 | E7: P2 | F7: Staff S1, S2; pointer at S2 | G7: salesAllocationService.AutoAssignCustomerAsync(newUserId) | H7: Customer assigned to S2; pointer wraps back to S1 | I7: No | J7: Pass | M7: ✅ Pass (không đổi)
A8: ▶ Block: AssignUnassignedCustomersAsync()
A9: L1-SA-03 | B9: EP-Valid | C9: Bulk-assign distributes ALL unassigned customers and reports count | D9: FT-04 AC-02; AC-03; BR-002 | E9: P2 | F9: 3 unassigned customers; 2 active staff | G9: salesAllocationService.AssignUnassignedCustomersAsync(managerId) | H9: Result.AssignedCount = 3; no customer left unassigned Distribution follows round-robin sequence | I9: No | J9: Pass | M9: ✅ Pass (không đổi)
A10: ▶ Block: GetMyCustomerDetailAsync() / UpdateCustomerNoteAsync()
A11: L1-SA-04 | B11: EP-Invalid | C11: Staff opens detail of a customer NOT allocated to them -> forbidden | D11: FT-04 NAC-04; NFR-SEC03 | E11: P1 | F11: Customer C9 allocated to staff S2 | G11: salesAllocationService.GetMyCustomerDetailAsync(S1, C9) | H11: Throws forbidden/not-found; no data returned | I11: Yes | J11: Pass | M11: ✅ Pass (không đổi)
A12: L1-SA-05 | B12: EP-Valid | C12: Update note persists against the correct customer only | D12: FT-04 AC-04 | E12: P3 | F12: Customer C1 allocated to S1 | G12: salesAllocationService.UpdateCustomerNoteAsync(S1, C1, 'VIP') | H12: C1.Note = 'VIP'; other customers untouched | I12: No | J12: Pass | M12: ✅ Pass (không đổi)
A13: ▶ Block: ⊕ v2.1 — Referral & cấu hình round-robin | ResolveReferralStaffAsync, EnsureCustomerProfileAsync, UpdateRoundRobinAsync, GetRoundRobinStateAsync | FT-04
A14: L1-SA-06 | B14: EP-Valid | C14: Mã giới thiệu hợp lệ, duy nhất -> trả đúng Sales được giới thiệu | D14: FT-04 AC-02; BR-002 | E14: P1 | F14: Mã 'S1-REF' thuộc Sales S1 đang hoạt động | G14: salesAllocationService.ResolveReferralStaffAsync('S1-REF') | H14: Trả về S1; nguồn phân công = REFERRAL | I14: No | J14: Pass | M14: ✅ Pass (không đổi)
A15: L1-SA-07 | B15: EP-Invalid | C15: Mã giới thiệu không tồn tại -> không gán sai người | D15: FT-04 NAC-02 | E15: P1 | F15: Không có mã 'XXX' | G15: salesAllocationService.ResolveReferralStaffAsync('XXX') | H15: Trả null / báo lỗi; KHÔNG chọn bừa một Sales bất kỳ | I15: Yes | J15: Pass | M15: ✅ Pass (không đổi)
A16: L1-SA-08 | B16: EP-Invalid | C16: Mã giới thiệu thuộc Sales đã ngừng hoạt động -> không gán | D16: FT-04 NAC-02 | E16: P1 | F16: S3 inactive nhưng còn mã 'S3-REF' | G16: salesAllocationService.ResolveReferralStaffAsync('S3-REF') | H16: Không gán S3; chuyển sang xử lý theo quy tắc khác | I16: Yes | J16: Pass | M16: ✅ ĐÃ FIX SalesAllocationService.cs:373-374 lọc IsActive trong ResolveReferralStaffAsync, referral của NV nghỉ việc không được gán.
A17: L1-SA-09 | B17: EP-Invalid | C17: Mã giới thiệu khớp NHIỀU Sales -> yêu cầu làm rõ, không tự chọn | D17: FT-04 NAC-02 | E17: P1 | F17: 2 Sales cùng khớp mã nhập vào | G17: salesAllocationService.ResolveReferralStaffAsync(ambiguousCode) | H17: Báo mơ hồ; KHÔNG tự chọn một trong hai | I17: Yes | J17: Pass | M17: ✅ Pass (không đổi)
A18: L1-SA-10 | B18: EP-Valid | C18: EnsureCustomerProfile: gọi 2 lần không tạo profile trùng | D18: FT-04 AC-01; BV-01 | E18: P1 | F18: U1 chưa có CustomerProfile | G18: Gọi EnsureCustomerProfileAsync(U1) hai lần liên tiếp | H18: Chỉ tồn tại đúng 1 CustomerProfile cho U1 | I18: No | J18: Pass | M18: ✅ Pass (không đổi)
A19: L1-SA-11 | B19: EP-Valid | C19: UpdateRoundRobin: bỏ staff khỏi danh sách -> lần gán sau không rơi vào staff đó | D19: FT-04 BV-02; BR-002 | E19: P1 | F19: Danh sách tham gia: S1, S2, S3; con trỏ ở S1 | G19: salesAllocationService.UpdateRoundRobinAsync(dto{participants:[S1,S3]}) | H19: S2 bị loại; lần gán kế tiếp chỉ chọn trong S1/S3 Con trỏ vẫn hợp lệ (không trỏ ra ngoài danh sách) | I19: No | J19: Pass | M19: ✅ Pass (không đổi)
A20: L1-SA-12 | B20: EP-Invalid | C20: UpdateRoundRobin với danh sách rỗng -> từ chối | D20: FT-04 BV-02; NAC-03 | E20: P1 | F20: Đang có 3 staff tham gia | G20: salesAllocationService.UpdateRoundRobinAsync(dto{participants:[]}) | H20: Từ chối; cấu hình cũ giữ nguyên (tránh không còn ai để phân công) | I20: Yes | J20: Pass | M20: ✅ Pass (không đổi)
A21: L1-SA-13 | B21: EP-Valid | C21: GetRoundRobinState trả đúng vị trí con trỏ và danh sách hiện hành | D21: FT-04 BV-02 | E21: P2 | F21: Con trỏ đang ở S2 | G21: salesAllocationService.GetRoundRobinStateAsync() | H21: Trả danh sách tham gia + con trỏ = S2 (khớp với lần gán kế tiếp) | I21: No | J21: Pass | M21: ✅ Pass (không đổi)
A22: ▶ Template Row — copy khi thêm case mới
A23: L1-XX-[NN] | B23: [BC-TRUE | BC-FALSE | CC | EP-Valid | EP-Invalid | BVA-* | State-* | Guard-* | Concurrency | Idempotency | Atomicity] | C23: [Branch / condition / partition] | D23: [FT-xx AC/NAC/BV-xx; BR-xxx; NFR-xxx] | E23: P2 | F23: [Arrange: state + _mock.Setup(...)] | G23: service.Method(params) | H23: [result.Should().Be(...) / Throws / _mock.Verify(..., Times.Never)] | I23: No | J23: Not Run

Sheet JwtService
A1: JwtService | methods: GenerateAccessToken, GenerateRefreshToken, GetPrincipalFromExpiredToken, GetAccessTokenExpiry | Pure logic — Mock: IOptions<JwtSettings>
A2: HOW TO USE: (1) Đọc Introduction (2) Trace theo SRS v2 (Part 3 + RTW Sheet 3/6/7) (3) Cập nhật Status sau mỗi lần chạy dotnet test / vitest (4) Ghi Defect ID khi Fail
A4: Test ID | B4: Coverage Technique | C4: Covers (Decision/Condition) | D4: SRS Reference | E4: Priority | F4: Given (Precondition / Mock Setup) | G4: When (Input / Act) | H4: Then (Expected Output / Assert) | I4: Negative? | J4: Status | K4: Defect ID | L4: Notes | M4: Fix Status
A5: ▶ Block: GenerateAccessToken() / GetAccessTokenExpiry() | NFR-SEC04
A6: L1-JWT-01 | B6: EP-Valid | C6: Token contains correct userId + role claims, signed with configured key | D6: NFR-SEC03 | E6: P1 | F6: JwtSettings{key, issuer, expiry=15min}; user U1 role='Customer' | G6: jwtService.GenerateAccessToken(user) | H6: Decoded token: sub/nameid = U1; role claim = 'Customer' Issuer/audience match settings; signature valid | I6: No | J6: Pass | M6: ✅ Pass (không đổi)
A7: L1-JWT-02 | B7: EP-Valid | C7: Access token expiry equals configured lifetime | D7: NFR-SEC02 | E7: P2 | F7: JwtSettings.ExpiryMinutes = 15 (mock clock) | G7: jwtService.GetAccessTokenExpiry() | H7: Expiry = NOW + 15min (within 1s tolerance) | I7: No | J7: Pass | M7: ✅ Pass (không đổi)
A8: ▶ Block: GenerateRefreshToken()
A9: L1-JWT-03 | B9: EP-Valid | C9: Two consecutive refresh tokens are distinct and cryptographically sized | D9: NFR-SEC02 | E9: P2 | F9: — | G9: var a = GenerateRefreshToken(); var b = GenerateRefreshToken() | H9: a != b; length >= 32 bytes base64 (non-guessable) | I9: No | J9: Pass | M9: ✅ Pass (không đổi)
A10: ▶ Block: GetPrincipalFromExpiredToken() | silent-refresh support
A11: L1-JWT-04 | B11: EP-Valid | C11: Expired-but-correctly-signed token -> principal extracted (lifetime NOT validated) | D11: NFR-SEC02 | E11: P1 | F11: Token generated with settings key, expiry in the past | G11: jwtService.GetPrincipalFromExpiredToken(expiredToken) | H11: Returns ClaimsPrincipal with original userId claim No exception despite expiry | I11: No | J11: Pass | M11: ✅ Pass (không đổi)
A12: L1-JWT-05 | B12: EP-Invalid | C12: Token signed with a DIFFERENT key -> rejected (null/exception) | D12: NFR-SEC02 | E12: P1 | F12: Token signed with attacker key | G12: jwtService.GetPrincipalFromExpiredToken(forgedToken) | H12: Returns null or throws SecurityTokenException No principal issued | I12: Yes | J12: Pass | M12: ✅ Pass (không đổi)
A13: ▶ Template Row — copy khi thêm case mới
A14: L1-XX-[NN] | B14: [BC-TRUE | BC-FALSE | CC | EP-Valid | EP-Invalid | BVA-* | State-* | Guard-* | Concurrency | Idempotency | Atomicity] | C14: [Branch / condition / partition] | D14: [FT-xx AC/NAC/BV-xx; BR-xxx; NFR-xxx] | E14: P2 | F14: [Arrange: state + _mock.Setup(...)] | G14: service.Method(params) | H14: [result.Should().Be(...) / Throws / _mock.Verify(..., Times.Never)] | I14: No | J14: Not Run

Sheet AddressService
A1: AddressService | methods: GetAddressesAsync, CreateAddressAsync, UpdateAddressAsync, DeleteAddressAsync, SetDefaultAddressAsync | Mock: IUnitOfWork
A2: HOW TO USE: (1) Đọc Introduction (2) Trace theo SRS v2 (Part 3 + RTW Sheet 3/6/7) (3) Cập nhật Status sau mỗi lần chạy dotnet test / vitest (4) Ghi Defect ID khi Fail
A4: Test ID | B4: Coverage Technique | C4: Covers (Decision/Condition) | D4: SRS Reference | E4: Priority | F4: Given (Precondition / Mock Setup) | G4: When (Input / Act) | H4: Then (Expected Output / Assert) | I4: Negative? | J4: Status | K4: Defect ID | L4: Notes | M4: Fix Status
A5: ▶ Block: SetDefaultAddressAsync()
A6: L1-ADDR-01 | B6: EP-Valid | C6: Set default -> chosen address default=true, ALL others reset to false | D6: FT-01 AC-03; BV-03; BR-028 | E6: P1 | F6: User U1 has A1 (default) and A2; mock ResetDefaultAsync | G6: addressService.SetDefaultAddressAsync(U1, A2) | H6: addressRepo.ClearDefaultAsync(userId) called once, then A2.IsDefault = true Exactly one default exists | I6: No | J6: Pass | M6: ✅ Pass (không đổi)
A7: ▶ Block: CreateAddressAsync() / UpdateAddressAsync() / DeleteAddressAsync()
A8: L1-ADDR-02 | B8: EP-Invalid | C8: Update an address belonging to another user -> rejected | D8: FT-01 NAC-05; NFR-SEC03 | E8: P1 | F8: Address A9 belongs to user U9 | G8: addressService.UpdateAddressAsync(U1, A9, dto) | H8: Throws not-found/forbidden; A9 unchanged | I8: Yes | J8: Pass | M8: ✅ Pass (không đổi)
A9: L1-ADDR-03 | B9: EP-Valid | C9: Delete removes the address from the user's list | D9: FT-01 NAC-05; BR-028 | E9: P3 | F9: U1 has A1, A2 | G9: addressService.DeleteAddressAsync(U1, A2) | H9: addressRepo.Remove(A2) called; GetAddresses returns only A1 | I9: No | J9: Pass | M9: ✅ Pass (không đổi)
A10: L1-ADDR-04 | B10: EP-Valid | C10: First address created for a profile becomes default | D10: FT-01 AC-03; BV-03 | E10: P3 | F10: U1 has 0 addresses | G10: addressService.CreateAddressAsync(U1, dto) | H10: Created address IsDefault = true | I10: No | J10: Pass | M10: ✅ Pass (không đổi)
A11: ▶ Template Row — copy khi thêm case mới
A12: L1-XX-[NN] | B12: [BC-TRUE | BC-FALSE | CC | EP-Valid | EP-Invalid | BVA-* | State-* | Guard-* | Concurrency | Idempotency | Atomicity] | C12: [Branch / condition / partition] | D12: [FT-xx AC/NAC/BV-xx; BR-xxx; NFR-xxx] | E12: P2 | F12: [Arrange: state + _mock.Setup(...)] | G12: service.Method(params) | H12: [result.Should().Be(...) / Throws / _mock.Verify(..., Times.Never)] | I12: No | J12: Not Run

Sheet UserProfileService
A1: UserProfileService | methods: GetProfileAsync, UpdateProfileAsync, UploadAvatarAsync, DeleteAvatarAsync, ChangePasswordAsync | Mock: IUnitOfWork, ICloudinaryService
A2: HOW TO USE: (1) Đọc Introduction (2) Trace theo SRS v2 (Part 3 + RTW Sheet 3/6/7) (3) Cập nhật Status sau mỗi lần chạy dotnet test / vitest (4) Ghi Defect ID khi Fail
A4: Test ID | B4: Coverage Technique | C4: Covers (Decision/Condition) | D4: SRS Reference | E4: Priority | F4: Given (Precondition / Mock Setup) | G4: When (Input / Act) | H4: Then (Expected Output / Assert) | I4: Negative? | J4: Status | K4: Defect ID | L4: Notes | M4: Fix Status
A5: ▶ Block: ChangePasswordAsync() | NFR-SEC03
A6: L1-UP-01 | B6: EP-Invalid | C6: Wrong current password -> change rejected, hash unchanged | D6: NFR-SEC02 | E6: P1 | F6: User hash = BCrypt('Old!123') | G6: userProfileService.ChangePasswordAsync(U1, dto{current='WRONG', new='New!123'}) | H6: Throws/returns failure; PasswordHash unchanged SaveChangesAsync NEVER called | I6: Yes | J6: Pass | M6: ✅ Pass (không đổi)
A7: L1-UP-02 | B7: EP-Valid | C7: Correct current password -> new BCrypt hash stored, never plaintext | D7: NFR-SEC02 | E7: P1 | F7: User hash = BCrypt('Old!123') | G7: userProfileService.ChangePasswordAsync(U1, dto{current='Old!123', new='New!123'}) | H7: New hash verifies against 'New!123'; stored value != 'New!123' Old password no longer valid | I7: No | J7: Pass | M7: ✅ Pass (không đổi)
A8: ▶ Block: UpdateProfileAsync() / avatar methods
A9: L1-UP-03 | B9: EP-Valid | C9: Update changes only permitted profile fields | D9: FT-01 AC-03; NFR-SEC06 | E9: P2 | F9: User U1 existing profile | G9: userProfileService.UpdateProfileAsync(U1, dto{name,phone}) | H9: Name/phone updated; Role/Email/PasswordHash untouched | I9: No | J9: Pass | M9: ✅ Pass (không đổi)
A10: L1-UP-04 | B10: EP-Valid | C10: Upload avatar delegates to Cloudinary and stores returned URL | D10: FT-01 AC-03; NFR-SEC07 | E10: P3 | F10: Mock: cloudinaryService.UploadImageAsync -> 'https://cdn/x.png' | G10: userProfileService.UploadAvatarAsync(U1, file) | H10: UploadImageAsync called once with the file; profile.AvatarUrl = returned URL | I10: No | J10: Pass | M10: ✅ Pass (không đổi)
A11: L1-UP-05 | B11: EP-Valid | C11: Delete avatar removes Cloudinary asset by extracted publicId | D11: FT-01 AC-03; NFR-SEC07 | E11: P3 | F11: Profile.AvatarUrl set; mock ExtractPublicId -> 'pid'; DeleteImageAsync -> true | G11: userProfileService.DeleteAvatarAsync(U1) | H11: cloudinaryService.DeleteImageAsync('pid') called once; AvatarUrl cleared | I11: No | J11: Pass | M11: ✅ Pass (không đổi)
A12: ▶ Template Row — copy khi thêm case mới
A13: L1-XX-[NN] | B13: [BC-TRUE | BC-FALSE | CC | EP-Valid | EP-Invalid | BVA-* | State-* | Guard-* | Concurrency | Idempotency | Atomicity] | C13: [Branch / condition / partition] | D13: [FT-xx AC/NAC/BV-xx; BR-xxx; NFR-xxx] | E13: P2 | F13: [Arrange: state + _mock.Setup(...)] | G13: service.Method(params) | H13: [result.Should().Be(...) / Throws / _mock.Verify(..., Times.Never)] | I13: No | J13: Not Run

Sheet SupplierService
A1: SupplierService | methods: GetAllAsync, GetByIdAsync, CreateAsync, UpdateAsync | EF Core InMemory | ⚠ SRS trace TBD (purchasing domain)
A2: HOW TO USE: (1) Đọc Introduction (2) Trace theo SRS v2 (Part 3 + RTW Sheet 3/6/7) (3) Cập nhật Status sau mỗi lần chạy dotnet test / vitest (4) Ghi Defect ID khi Fail
A4: Test ID | B4: Coverage Technique | C4: Covers (Decision/Condition) | D4: SRS Reference | E4: Priority | F4: Given (Precondition / Mock Setup) | G4: When (Input / Act) | H4: Then (Expected Output / Assert) | I4: Negative? | J4: Status | K4: Defect ID | L4: Notes | M4: Fix Status
A5: ▶ Block: CreateAsync() / UpdateAsync() / GetByIdAsync()
A6: L1-SUP-01 | B6: EP-Valid | C6: Create supplier with valid data -> persisted and returned | D6: FT-09 AC-03; FT-06 AC-01 | E6: P3 | F6: Valid CreateSupplierRequest | G6: supplierService.CreateAsync(request) | H6: Supplier persisted; DTO fields echo request | I6: No | J6: Pass | M6: ✅ Pass (không đổi)
A7: L1-SUP-02 | B7: EP-Invalid | C7: GetById with unknown id -> not-found | D7: FT-09 AC-03 | E7: P3 | F7: No supplier with id Sx | G7: supplierService.GetByIdAsync(Sx) | H7: Throws not-found (or returns null) — controller maps to 404 | I7: Yes | J7: Pass | M7: ✅ Pass (không đổi)
A8: L1-SUP-03 | B8: EP-Invalid | C8: Update a non-existent supplier -> rejected, nothing created | D8: FT-09 AC-03 | E8: P3 | F8: No supplier Sx | G8: supplierService.UpdateAsync(Sx, request) | H8: Throws not-found; no upsert side effect | I8: Yes | J8: Pass | M8: ✅ Pass (không đổi)
A9: ▶ Template Row — copy khi thêm case mới
A10: L1-XX-[NN] | B10: [BC-TRUE | BC-FALSE | CC | EP-Valid | EP-Invalid | BVA-* | State-* | Guard-* | Concurrency | Idempotency | Atomicity] | C10: [Branch / condition / partition] | D10: [FT-xx AC/NAC/BV-xx; BR-xxx; NFR-xxx] | E10: P2 | F10: [Arrange: state + _mock.Setup(...)] | G10: service.Method(params) | H10: [result.Should().Be(...) / Throws / _mock.Verify(..., Times.Never)] | I10: No | J10: Not Run

Sheet InventoryService
A1: InventoryService | methods: GetInventoryByWarehouseAsync, AdjustInventoryAsync, AddProductToWarehouseAsync | EF Core InMemory
A2: HOW TO USE: (1) Đọc Introduction (2) Trace theo SRS v2 (Part 3 + RTW Sheet 3/6/7) (3) Cập nhật Status sau mỗi lần chạy dotnet test / vitest (4) Ghi Defect ID khi Fail
A4: Test ID | B4: Coverage Technique | C4: Covers (Decision/Condition) | D4: SRS Reference | E4: Priority | F4: Given (Precondition / Mock Setup) | G4: When (Input / Act) | H4: Then (Expected Output / Assert) | I4: Negative? | J4: Status | K4: Defect ID | L4: Notes | M4: Fix Status
A5: ▶ Block: GetInventoryByWarehouseAsync() | FT-11 (inventory visibility)
A6: L1-INV-01 | B6: EP-Valid | C6: Filter by warehouse + search + qty range returns matching rows only | D6: FT-12 AC-04; FT-09 AC-01 | E6: P2 | F6: W1 has 3 inventory rows, W2 has 2; search 'bag' matches 1 in W1 | G6: inventoryService.GetInventoryByWarehouseAsync(W1, 'bag', minQty=0, maxQty=100, ...) | H6: Only the matching W1 row returned; paging metadata correct | I6: No | J6: Pass | M6: ✅ Pass (không đổi)
A7: ▶ Block: AdjustInventoryAsync() | FT-04 BV-02 (stock >= 0); auditability
A8: L1-INV-02 | B8: EP-Valid | C8: Adjust to new quantity -> inventory updated + StockTransaction audit row with note/staff | D8: FT-12 AC-02; AC-03; BR-044; BR-022 | E8: P1 | F8: Inventory I1 (P1@W1) qty = 10 | G8: inventoryService.AdjustInventoryAsync(I1, newQuantity=7, 'stocktake', staffId) | H8: I1.Quantity = 7; StockTransaction logged (delta -3, note, staffId) | I8: No | J8: Pass | M8: ✅ Pass (không đổi)
A9: L1-INV-03 | B9: EP-Invalid + BVA-Min-1 | C9: Adjust to negative quantity -> rejected | D9: FT-12 NAC-03; BV-01; BR-032 | E9: P1 | F9: Inventory I1 qty = 10 | G9: inventoryService.AdjustInventoryAsync(I1, newQuantity=-1, note, staffId) | H9: Từ chối; quantity không đổi; không ghi audit row Assert OnHandQuantity và RawAvailable(), KHÔNG assert AvailableQuantity >= 0 (luôn xanh do Math.Max) | I9: Yes | J9: Pass | L9: 🟠 BẪY ASSERTION: Inventory.AvailableQuantity (Inventory.cs:24) bọc Math.Max(0, ...) nên assert "không âm" LUÔN XANH kể cả khi đã oversell. Phải assert OnHandQuantity VÀ biểu thức thô RawAvailable() (= OnHand - Reserved - Allocated - Damaged - Quarantine, CHƯA kẹp). | M9: ✅ Pass (không đổi)
A10: ▶ Block: AddProductToWarehouseAsync()
A11: L1-INV-04 | B11: EP-Valid | C11: Add product to a warehouse -> inventory row created with qty >= 0 | D11: FT-12 AC-01 | E11: P2 | F11: P1 not yet stocked in W2 | G11: inventoryService.AddProductToWarehouseAsync(req{P1,W2,qty=20}, staffId) | H11: Inventory row (P1,W2) created qty=20; StockTransaction logged | I11: No | J11: Pass | M11: ✅ Pass (không đổi)
A12: L1-INV-05 | B12: EP-Invalid | C12: Add a product that already has an inventory row in that warehouse -> rejected (no duplicate row) | D12: FT-12 NAC-01 | E12: P2 | F12: Inventory (P1,W1) already exists | G12: inventoryService.AddProductToWarehouseAsync(req{P1,W1,qty=5}, staffId) | H12: Rejected/conflict; no second row for (P1,W1) | I12: Yes | J12: Pass | M12: ✅ Pass (không đổi)
A13: ▶ Template Row — copy khi thêm case mới
A14: L1-XX-[NN] | B14: [BC-TRUE | BC-FALSE | CC | EP-Valid | EP-Invalid | BVA-* | State-* | Guard-* | Concurrency | Idempotency | Atomicity] | C14: [Branch / condition / partition] | D14: [FT-xx AC/NAC/BV-xx; BR-xxx; NFR-xxx] | E14: P2 | F14: [Arrange: state + _mock.Setup(...)] | G14: service.Method(params) | H14: [result.Should().Be(...) / Throws / _mock.Verify(..., Times.Never)] | I14: No | J14: Not Run

Sheet GoodsIssueService
A1: GoodsIssueService | methods: CreateGoodsIssueAsync, UploadProofAsync, PostGoodsIssueAsync | EF Core InMemory + Mock: ICloudinaryService
A2: HOW TO USE: (1) Đọc Introduction (2) Trace theo SRS v2 (Part 3 + RTW Sheet 3/6/7) (3) Cập nhật Status sau mỗi lần chạy dotnet test / vitest (4) Ghi Defect ID khi Fail
A4: Test ID | B4: Coverage Technique | C4: Covers (Decision/Condition) | D4: SRS Reference | E4: Priority | F4: Given (Precondition / Mock Setup) | G4: When (Input / Act) | H4: Then (Expected Output / Assert) | I4: Negative? | J4: Status | K4: Defect ID | L4: Notes | M4: Fix Status
A5: ▶ Block: CreateGoodsIssueAsync() / UploadProofAsync()
A6: L1-GI-01 | B6: EP-Valid | C6: Create goods issue draft with line items | D6: FT-05 AC-04 | E6: P2 | F6: Valid request with 2 lines; staff W1 | G6: goodsIssueService.CreateGoodsIssueAsync(req, W1) | H6: GoodsIssue persisted status Draft; 2 GoodsIssueItems stored | I6: No | J6: Pass | M6: ✅ Pass (không đổi)
A7: L1-GI-02 | B7: EP-Valid | C7: Upload proof image delegates to Cloudinary and stores URL | D7: FT-05 AC-04; NFR-SEC07 | E7: P3 | F7: Issue GI-1 Draft; mock UploadEvidenceAsync -> url | G7: goodsIssueService.UploadProofAsync(GI-1, file) | H7: cloudinary.UploadEvidenceAsync called once; GI-1.ProofUrl = url | I7: No | J7: Pass | M7: ✅ Pass (không đổi)
A8: ▶ Block: PostGoodsIssueAsync() | FT-04 AC-02, NAC-03; BV-02
A9: L1-GI-03 | B9: State-Valid | C9: Post issue -> stock decremented per line, status Posted, atomic | D9: FT-05 AC-05; BV-02; BR-032 | E9: P1 | F9: GI-1 Draft: P1 qty=3; stock P1 = 10 | G9: goodsIssueService.PostGoodsIssueAsync(GI-1, W1) | H9: Stock P1 = 7; GI-1 = Posted; StockTransaction rows created All in one transaction | I9: No | J9: Pass | M9: ✅ Pass (không đổi)
A10: L1-GI-04 | B10: State-Invalid | C10: Post an already-Posted issue -> conflict (no double decrement) | D10: FT-05 NAC-05; BR-021; BR-029 | E10: P1 | F10: GI-1 Posted; stock P1 = 7 | G10: goodsIssueService.PostGoodsIssueAsync(GI-1, W1) | H10: Throws conflict; stock remains 7 | I10: Yes | J10: Pass | M10: ✅ Pass (không đổi)
A11: ▶ Block: ⊕ v2.1 — Bàn giao & phiếu đảo | UpdateHandoverInfoAsync, CreateReversalAsync | FT-05; BR-021; BR-034
A12: L1-GI-05 | B12: EP-Valid | C12: Cập nhật thông tin bàn giao trên phiếu CHƯA post | D12: FT-05 AC-05; BR-034 | E12: P1 | F12: GI-1 trạng thái Draft | G12: goodsIssueService.UpdateHandoverInfoAsync(GI-1, staffId, dto{packageCount, signature}) | H12: Thông tin bàn giao được lưu; phiếu vẫn Draft | I12: No | J12: Pass | M12: ✅ Pass (không đổi)
A13: L1-GI-06 | B13: State-Invalid | C13: Cập nhật bàn giao trên phiếu ĐÃ post -> conflict | D13: FT-05 NAC-05; BR-021 | E13: P1 | F13: GI-1 trạng thái Posted | G13: goodsIssueService.UpdateHandoverInfoAsync(GI-1, staffId, dto) | H13: Ném conflict (chứng từ đã ghi sổ bất biến); dữ liệu không đổi | I13: Yes | J13: Pass | M13: ✅ Pass (không đổi)
A14: L1-GI-07 | B14: EP-Valid | C14: Tạo phiếu đảo -> hoàn lại đúng số lượng đã xuất, KHÔNG sửa phiếu gốc | D14: FT-05 NAC-05; BR-021 | E14: P1 | F14: GI-1 Posted, đã trừ P1 = 3; tồn hiện tại = 7 | G14: goodsIssueService.CreateReversalAsync(GI-1, staffId, dto{reason}) | H14: Tồn P1 = 10; phiếu gốc GI-1 GIỮ NGUYÊN Phiếu đảo là chứng từ mới có tham chiếu tới GI-1 | I14: No | J14: Pass | M14: ✅ Pass (không đổi)
A15: L1-GI-08 | B15: State-Invalid | C15: Tạo phiếu đảo cho phiếu chưa post -> từ chối | D15: BR-021 | E15: P1 | F15: GI-1 Draft | G15: goodsIssueService.CreateReversalAsync(GI-1, staffId, dto) | H15: Từ chối; không tạo chứng từ đảo | I15: Yes | J15: Pass | M15: ✅ Pass (không đổi)
A16: L1-GI-09 | B16: Idempotency | C16: Tạo phiếu đảo lần 2 cho cùng phiếu gốc -> chặn hoàn kép | D16: BR-029; BR-032 | E16: P1 | F16: GI-1 đã có phiếu đảo, tồn P1 = 10 | G16: goodsIssueService.CreateReversalAsync(GI-1, staffId, dto) | H16: Từ chối; tồn P1 vẫn = 10 (không cộng thêm lần nữa) | I16: Yes | J16: Pass | M16: ✅ Pass (không đổi)
A17: ▶ Template Row — copy khi thêm case mới
A18: L1-XX-[NN] | B18: [BC-TRUE | BC-FALSE | CC | EP-Valid | EP-Invalid | BVA-* | State-* | Guard-* | Concurrency | Idempotency | Atomicity] | C18: [Branch / condition / partition] | D18: [FT-xx AC/NAC/BV-xx; BR-xxx; NFR-xxx] | E18: P2 | F18: [Arrange: state + _mock.Setup(...)] | G18: service.Method(params) | H18: [result.Should().Be(...) / Throws / _mock.Verify(..., Times.Never)] | I18: No | J18: Not Run

Sheet StockTransferService
A1: StockTransferService | methods: CreateAsync, UpdateAsync, DispatchAsync, ReceiveAsync, CancelAsync | EF Core InMemory | ⚠ multi-warehouse transfer = BRD v6.0 scope
A2: HOW TO USE: (1) Đọc Introduction (2) Trace theo SRS v2 (Part 3 + RTW Sheet 3/6/7) (3) Cập nhật Status sau mỗi lần chạy dotnet test / vitest (4) Ghi Defect ID khi Fail
A4: Test ID | B4: Coverage Technique | C4: Covers (Decision/Condition) | D4: SRS Reference | E4: Priority | F4: Given (Precondition / Mock Setup) | G4: When (Input / Act) | H4: Then (Expected Output / Assert) | I4: Negative? | J4: Status | K4: Defect ID | L4: Notes | M4: Fix Status
A5: ▶ Block: CreateAsync() / DispatchAsync()
A6: L1-ST-01 | B6: EP-Valid | C6: Create transfer Draft between two different warehouses | D6: FT-11 AC-01; BV-03 | E6: P2 | F6: W1 source, W2 destination; P1 qty=5 requested | G6: stockTransferService.CreateAsync(dto{W1->W2, P1 qty=5}, userId) | H6: Transfer persisted status Draft with 1 item Email notification to destination warehouse (mock IEmailService) | I6: No | J6: Pass | M6: ✅ Pass (không đổi)
A7: L1-ST-02 | B7: EP-Invalid | C7: Create transfer with source == destination -> rejected | D7: FT-11 NAC-01; BV-03 | E7: P2 | F7: dto{W1 -> W1} | G7: stockTransferService.CreateAsync(dto, userId) | H7: Rejected validation; nothing persisted | I7: Yes | J7: Pass | M7: ✅ Pass (không đổi)
A8: L1-ST-03 | B8: State-Valid | C8: Dispatch Draft transfer -> source stock decremented, status Dispatched | D8: FT-11 AC-01; BV-01; BR-035 | E8: P1 | F8: Transfer T1 Draft (P1 qty=5); stock(P1,W1) = 10 | G8: stockTransferService.DispatchAsync(T1) | H8: stock(P1,W1) = 5; T1 = Dispatched; StockTransaction logged | I8: No | J8: Pass | M8: ✅ Pass (không đổi)
A9: L1-ST-04 | B9: State-Invalid | C9: Dispatch a non-Draft transfer -> conflict | D9: FT-11 NAC-04; BR-021; BR-035 | E9: P1 | F9: T1 Status = Dispatched | G9: stockTransferService.DispatchAsync(T1) | H9: Throws conflict; stocks unchanged | I9: Yes | J9: Pass | M9: ✅ Pass (không đổi)
A10: ▶ Block: ReceiveAsync() / CancelAsync()
A11: L1-ST-05 | B11: State-Valid | C11: Receive Dispatched transfer -> destination stock incremented by received qty | D11: FT-11 AC-02; BV-02; BR-035 | E11: P1 | F11: T1 Dispatched (P1 qty=5); stock(P1,W2) = 2 | G11: stockTransferService.ReceiveAsync(T1, dto{received qty=5}) | H11: stock(P1,W2) = 7; T1 = Received (terminal) | I11: No | J11: Pass | M11: ✅ Pass (không đổi)
A12: L1-ST-06 | B12: EP-Invalid | C12: Received qty > dispatched qty -> rejected / flagged as discrepancy | D12: FT-11 NAC-03; BV-02 | E12: P1 | F12: T1 Dispatched qty=5 | G12: stockTransferService.ReceiveAsync(T1, dto{received qty=6}) | H12: Rejected (or discrepancy record) — destination NOT incremented by 6 | I12: Yes | J12: Pass | M12: ✅ Pass (không đổi)
A13: ▶ Template Row — copy khi thêm case mới
A14: L1-XX-[NN] | B14: [BC-TRUE | BC-FALSE | CC | EP-Valid | EP-Invalid | BVA-* | State-* | Guard-* | Concurrency | Idempotency | Atomicity] | C14: [Branch / condition / partition] | D14: [FT-xx AC/NAC/BV-xx; BR-xxx; NFR-xxx] | E14: P2 | F14: [Arrange: state + _mock.Setup(...)] | G14: service.Method(params) | H14: [result.Should().Be(...) / Throws / _mock.Verify(..., Times.Never)] | I14: No | J14: Not Run

Sheet WarehouseManagementService
A1: WarehouseManagementService | methods: CreateWarehouseAsync, UpdateWarehouseAsync, DeleteWarehouseAsync | EF Core InMemory | ⚠ 3-warehouse model = BRD v6.0 scope
A2: HOW TO USE: (1) Đọc Introduction (2) Trace theo SRS v2 (Part 3 + RTW Sheet 3/6/7) (3) Cập nhật Status sau mỗi lần chạy dotnet test / vitest (4) Ghi Defect ID khi Fail
A4: Test ID | B4: Coverage Technique | C4: Covers (Decision/Condition) | D4: SRS Reference | E4: Priority | F4: Given (Precondition / Mock Setup) | G4: When (Input / Act) | H4: Then (Expected Output / Assert) | I4: Negative? | J4: Status | K4: Defect ID | L4: Notes | M4: Fix Status
A5: ▶ Block: CRUD + delete guard
A6: L1-WM-01 | B6: EP-Valid | C6: Create warehouse with valid data | D6: FT-09 AC-03 | E6: P3 | F6: Valid CreateWarehouseDto | G6: warehouseManagementService.CreateWarehouseAsync(dto) | H6: Warehouse persisted; DTO echoes input | I6: No | J6: Pass | M6: ✅ Pass (không đổi)
A7: L1-WM-02 | B7: EP-Invalid | C7: Delete a warehouse still holding inventory (qty > 0) -> blocked | D7: FT-09 AC-03; FT-05 NAC-01 | E7: P1 | F7: W1 has inventory rows with qty > 0 | G7: warehouseManagementService.DeleteWarehouseAsync(W1) | H7: Rejected; warehouse and inventory intact | I7: Yes | J7: Pass | M7: ✅ Pass (không đổi)
A8: L1-WM-03 | B8: EP-Invalid | C8: Update unknown warehouse id -> not found | D8: FT-09 AC-03 | E8: P3 | F8: No warehouse Wx | G8: warehouseManagementService.UpdateWarehouseAsync(Wx, dto) | H8: Throws not-found; nothing created | I8: Yes | J8: Pass | M8: ✅ Pass (không đổi)
A9: ▶ Template Row — copy khi thêm case mới
A10: L1-XX-[NN] | B10: [BC-TRUE | BC-FALSE | CC | EP-Valid | EP-Invalid | BVA-* | State-* | Guard-* | Concurrency | Idempotency | Atomicity] | C10: [Branch / condition / partition] | D10: [FT-xx AC/NAC/BV-xx; BR-xxx; NFR-xxx] | E10: P2 | F10: [Arrange: state + _mock.Setup(...)] | G10: service.Method(params) | H10: [result.Should().Be(...) / Throws / _mock.Verify(..., Times.Never)] | I10: No | J10: Not Run

Sheet MaterialService
A1: MaterialService | methods: GetAllAsync, GetByIdAsync, CreateAsync, UpdateAsync | EF Core InMemory | raw materials — FT-11 / BR-34 (partial)
A2: HOW TO USE: (1) Đọc Introduction (2) Trace theo SRS v2 (Part 3 + RTW Sheet 3/6/7) (3) Cập nhật Status sau mỗi lần chạy dotnet test / vitest (4) Ghi Defect ID khi Fail
A4: Test ID | B4: Coverage Technique | C4: Covers (Decision/Condition) | D4: SRS Reference | E4: Priority | F4: Given (Precondition / Mock Setup) | G4: When (Input / Act) | H4: Then (Expected Output / Assert) | I4: Negative? | J4: Status | K4: Defect ID | L4: Notes | M4: Fix Status
A5: ▶ Block: CRUD
A6: L1-MAT-01 | B6: EP-Valid | C6: Create material with valid data | D6: FT-12 AC-05; BR-045 | E6: P3 | F6: Valid CreateMaterialDto | G6: materialService.CreateAsync(dto) | H6: Material persisted; DTO fields echo input | I6: No | J6: Pass | M6: ✅ Pass (không đổi)
A7: L1-MAT-02 | B7: EP-Valid | C7: GetAll with search keyword filters by name | D7: FT-12 AC-05 | E7: P3 | F7: Materials 'Nhựa PP', 'Giấy Kraft'; search='nhựa' | G7: materialService.GetAllAsync('nhựa') | H7: Only 'Nhựa PP' returned (case-insensitive) | I7: No | J7: Pass | M7: ✅ Pass (không đổi)
A8: L1-MAT-03 | B8: EP-Invalid | C8: Update unknown material id -> not found | D8: FT-12 AC-05 | E8: P3 | F8: No material Mx | G8: materialService.UpdateAsync(Mx, dto) | H8: Throws not-found; no upsert | I8: Yes | J8: Pass | M8: ✅ Pass (không đổi)
A9: ▶ Template Row — copy khi thêm case mới
A10: L1-XX-[NN] | B10: [BC-TRUE | BC-FALSE | CC | EP-Valid | EP-Invalid | BVA-* | State-* | Guard-* | Concurrency | Idempotency | Atomicity] | C10: [Branch / condition / partition] | D10: [FT-xx AC/NAC/BV-xx; BR-xxx; NFR-xxx] | E10: P2 | F10: [Arrange: state + _mock.Setup(...)] | G10: service.Method(params) | H10: [result.Should().Be(...) / Throws / _mock.Verify(..., Times.Never)] | I10: No | J10: Not Run

Sheet SalesChangeRequestService
A1: SalesChangeRequestService | methods: CreateAsync, CancelAsync, SubmitAdditionalInfoAsync, SubmitExplanationAsync, RequestExplanationAsync, RequestMoreInfoAsync, ApproveAsync, RejectAsync | EF Core InMemory | ⚠ sales-change workflow not in SRS v1.5
A2: HOW TO USE: (1) Đọc Introduction (2) Trace theo SRS v2 (Part 3 + RTW Sheet 3/6/7) (3) Cập nhật Status sau mỗi lần chạy dotnet test / vitest (4) Ghi Defect ID khi Fail
A4: Test ID | B4: Coverage Technique | C4: Covers (Decision/Condition) | D4: SRS Reference | E4: Priority | F4: Given (Precondition / Mock Setup) | G4: When (Input / Act) | H4: Then (Expected Output / Assert) | I4: Negative? | J4: Status | K4: Defect ID | L4: Notes | M4: Fix Status
A5: ▶ Block: CreateAsync() / CancelAsync() | customer side
A6: L1-SCR-01 | B6: EP-Valid | C6: Customer creates a sales-change request -> Pending, manager notified | D6: FT-04 AC-04; BV-03 | E6: P2 | F6: Customer U1 assigned to sales S1; reason provided | G6: salesChangeRequestService.CreateAsync(U1, dto{reason}) | H6: Request persisted status Pending referencing U1/S1 Manager notification created | I6: No | J6: Pass | M6: ✅ Pass (không đổi)
A7: L1-SCR-02 | B7: EP-Invalid | C7: Customer with an OPEN request creates another -> rejected | D7: FT-04 BV-03 | E7: P2 | F7: U1 already has request in Pending | G7: salesChangeRequestService.CreateAsync(U1, dto) | H7: Rejected: one open request at a time; nothing persisted | I7: Yes | J7: Pass | M7: ✅ Pass (không đổi)
A8: L1-SCR-03 | B8: EP-Invalid | C8: Cancel a request owned by another customer -> forbidden | D8: FT-04 NAC-04; NFR-SEC03 | E8: P1 | F8: Request R9 belongs to U9 | G8: salesChangeRequestService.CancelAsync(U1, R9) | H8: Throws forbidden/not-found; R9 unchanged | I8: Yes | J8: Pass | M8: ✅ Pass (không đổi)
A9: ▶ Block: Review workflow: RequestExplanation / SubmitExplanation / Approve / Reject
A10: L1-SCR-04 | B10: State-Valid | C10: Manager requests explanation -> staff notified, status advances to AwaitingExplanation | D10: FT-04 AC-04 | E10: P2 | F10: Request R1 Pending | G10: salesChangeRequestService.RequestExplanationAsync(managerId, R1) | H10: Status = AwaitingExplanation; notification to sales S1 | I10: No | J10: Pass | M10: ✅ Pass (không đổi)
A11: L1-SCR-05 | B11: State-Valid | C11: Staff submits explanation -> stored, returns to manager review | D11: FT-04 AC-04 | E11: P2 | F11: R1 AwaitingExplanation, assigned staff S1 | G11: salesChangeRequestService.SubmitExplanationAsync(S1, R1, dto{text}) | H11: Explanation stored; status back to manager review queue | I11: No | J11: Pass | M11: ✅ Pass (không đổi)
A12: L1-SCR-06 | B12: State-Valid | C12: Approve -> customer reallocated to chosen sales, request closed Approved | D12: FT-04 AC-04; AC-05; BR-031 | E12: P1 | F12: R1 under review; dto.newSalesId = S2 | G12: salesChangeRequestService.ApproveAsync(managerId, R1, dto) | H12: CustomerProfile.AssignedSales = S2; R1 = Approved (terminal) Both old & new sales notified | I12: No | J12: Pass | M12: ✅ Pass (không đổi)
A13: L1-SCR-07 | B13: State-Valid | C13: Reject with note -> request closed Rejected, assignment unchanged | D13: FT-04 AC-04 | E13: P2 | F13: R1 under review; customer assigned S1 | G13: salesChangeRequestService.RejectAsync(managerId, R1, 'insufficient grounds') | H13: R1 = Rejected with note; AssignedSales still S1 | I13: No | J13: Pass | M13: ✅ Pass (không đổi)
A14: ▶ Template Row — copy khi thêm case mới
A15: L1-XX-[NN] | B15: [BC-TRUE | BC-FALSE | CC | EP-Valid | EP-Invalid | BVA-* | State-* | Guard-* | Concurrency | Idempotency | Atomicity] | C15: [Branch / condition / partition] | D15: [FT-xx AC/NAC/BV-xx; BR-xxx; NFR-xxx] | E15: P2 | F15: [Arrange: state + _mock.Setup(...)] | G15: service.Method(params) | H15: [result.Should().Be(...) / Throws / _mock.Verify(..., Times.Never)] | I15: No | J15: Not Run

Sheet NotificationService
A1: NotificationService | methods: CreateNotificationAsync, CreateRoleNotificationAsync | EF Core InMemory
A2: HOW TO USE: (1) Đọc Introduction (2) Trace theo SRS v2 (Part 3 + RTW Sheet 3/6/7) (3) Cập nhật Status sau mỗi lần chạy dotnet test / vitest (4) Ghi Defect ID khi Fail
A4: Test ID | B4: Coverage Technique | C4: Covers (Decision/Condition) | D4: SRS Reference | E4: Priority | F4: Given (Precondition / Mock Setup) | G4: When (Input / Act) | H4: Then (Expected Output / Assert) | I4: Negative? | J4: Status | K4: Defect ID | L4: Notes | M4: Fix Status
A5: ▶ Block: CreateNotificationAsync() / CreateRoleNotificationAsync()
A6: L1-NOTI-01 | B6: EP-Valid | C6: Create notification persists type, recipient, title/body and reference | D6: FT-09 AC-02 | E6: P2 | F6: Recipient user U1 exists | G6: notificationService.CreateNotificationAsync(OrderConfirmed, U1, title, body, refId, 'Order') | H6: Notification row persisted: RecipientUserId=U1, unread, ReferenceId/Type set | I6: No | J6: Pass | M6: ✅ Pass (không đổi)
A7: L1-NOTI-02 | B7: EP-Valid | C7: Role notification creates one row per user holding the role | D7: FT-09 AC-02 | E7: P1 | F7: 3 users with role SalesStaff, 2 other roles | G7: notificationService.CreateRoleNotificationAsync(NewOrder, SalesStaff, ...) | H7: Exactly 3 notification rows created — one per SalesStaff; none for other roles | I7: No | J7: Pass | M7: ✅ Pass (không đổi)
A8: L1-NOTI-03 | B8: EP-Invalid | C8: Unknown recipient id -> handled without crash, nothing persisted | D8: FT-09 AC-02 | E8: P3 | F8: No user Ux | G8: notificationService.CreateNotificationAsync(type, Ux, ...) | H8: No exception bubbles to caller (or documented exception); no orphan row | I8: Yes | J8: Pass | M8: ✅ Pass (không đổi)
A9: ▶ Template Row — copy khi thêm case mới
A10: L1-XX-[NN] | B10: [BC-TRUE | BC-FALSE | CC | EP-Valid | EP-Invalid | BVA-* | State-* | Guard-* | Concurrency | Idempotency | Atomicity] | C10: [Branch / condition / partition] | D10: [FT-xx AC/NAC/BV-xx; BR-xxx; NFR-xxx] | E10: P2 | F10: [Arrange: state + _mock.Setup(...)] | G10: service.Method(params) | H10: [result.Should().Be(...) / Throws / _mock.Verify(..., Times.Never)] | I10: No | J10: Not Run

Sheet FE-Services
A1: FE-Services (Vitest + MSW) | src/services: authService.fetchWithToken, cartService, orderService, productService | Mock: MSW handlers, vi.mock(navigate), localStorage stub
A2: HOW TO USE: (1) Đọc Introduction (2) Trace theo SRS v2 (Part 3 + RTW Sheet 3/6/7) (3) Cập nhật Status sau mỗi lần chạy dotnet test / vitest (4) Ghi Defect ID khi Fail
A4: Test ID | B4: Coverage Technique | C4: Covers (Decision/Condition) | D4: SRS Reference | E4: Priority | F4: Given (Precondition / Mock Setup) | G4: When (Input / Act) | H4: Then (Expected Output / Assert) | I4: Negative? | J4: Status | K4: Defect ID | L4: Notes | M4: Fix Status
A5: ▶ Block: authService.fetchWithToken() | silent refresh — NFR-SEC04
A6: L1-FES-01 | B6: EP-Valid | C6: Request carries Authorization: Bearer <accessToken> | D6: NFR-SEC03 | E6: P1 | F6: Access token 'jwt-1' in auth state; MSW echoes headers | G6: await fetchWithToken('GET','/api/orders') | H6: MSW captured request has header Authorization = 'Bearer jwt-1' Response JSON returned to caller | I6: No | J6: Pass | M6: ✅ Pass (không đổi)
A7: L1-FES-02 | B7: BC-TRUE | C7: 401 response -> silent refresh then retry original request ONCE | D7: NFR-SEC02 | E7: P1 | F7: MSW: first /api/orders -> 401; /api/auth/refresh -> new token; second /api/orders -> 200 | G7: await fetchWithToken('GET','/api/orders') | H7: refresh endpoint called exactly once; original request retried with NEW token Caller receives the 200 payload — no error surfaced | I7: No | J7: Fail | K7: GH-31 | M7: ❌ CHƯA FIX authService.js:4-27 fetchWithToken khi 401 chỉ xoá storage + redirect /login, KHÔNG gọi refresh token, KHÔNG retry request gốc.
A8: L1-FES-03 | B8: BC-FALSE | C8: Refresh also fails -> session cleared + redirect to /login | D8: NFR-SEC02; FT-01 NAC-05 | E8: P1 | F8: MSW: /api/orders -> 401; /api/auth/refresh -> 401 | G8: await fetchWithToken('GET','/api/orders') | H8: Auth state cleared (logout); navigate('/login') called once No infinite retry loop (refresh attempted once) | I8: Yes | J8: Pass | M8: ✅ Pass (không đổi)
A9: ▶ Block: cartService / orderService / productService | payload correctness
A10: L1-FES-04 | B10: EP-Valid | C10: cartService.addItem posts {productId, quantity} to correct endpoint | D10: FT-01 AC-05 | E10: P2 | F10: MSW handler on POST /api/cart/items capturing body | G10: await cartService.addItem({productId:'P1', quantity:2}) | H10: Captured body = {productId:'P1', quantity:2}; success response returned | I10: No | J10: Pass | M10: ✅ Pass (không đổi)
A11: L1-FES-05 | B11: EP-Valid | C11: getOrderTimeline maps order status to the correct ordered step list | D11: FT-01 AC-05 | E11: P2 | F11: orderStatusMeta constant loaded | G11: getOrderTimeline('In Delivery') | H11: Steps up to 'In Delivery' marked done/current in 4.4.1 order 'Delivered' step not yet active | I11: No | J11: Pass | M11: ✅ Pass (không đổi)
A12: L1-FES-06 | B12: EP-Valid | C12: formatPrice renders VND with thousands separators | D12: NFR-U02 | E12: P3 | F12: — | G12: formatPrice(9999999) | H12: Returns '9.999.999 ₫' (or project's canonical format) — assert exact current format | I12: No | J12: Pass | M12: ✅ Pass (không đổi)
A13: ▶ Template Row — copy khi thêm case mới
A14: L1-XX-[NN] | B14: [BC-TRUE | BC-FALSE | CC | EP-Valid | EP-Invalid | BVA-* | State-* | Guard-* | Concurrency | Idempotency | Atomicity] | C14: [Branch / condition / partition] | D14: [FT-xx AC/NAC/BV-xx; BR-xxx; NFR-xxx] | E14: P2 | F14: [Arrange: state + _mock.Setup(...)] | G14: service.Method(params) | H14: [result.Should().Be(...) / Throws / _mock.Verify(..., Times.Never)] | I14: No | J14: Not Run
A16: ▶ Block: ⊕ v2.3 — Endpoint gửi lại OTP | authService.resendOtp | FT-01 AC-04; BV-02
A17: L1-FES-07 | B17: EP-Valid | C17: resendOtp gọi ĐÚNG endpoint /api/auth/resend-otp | D17: FT-01 AC-04 | E17: P2 | F17: MSW handler bắt POST /api/auth/resend-otp | G17: await authService.resendOtp({ email }) | H17: Đúng 1 request tới /api/auth/resend-otp với body {email} KHÔNG còn gọi lại /api/auth/register như cách hack cũ | I17: No | J17: Pass | M17: ✅ Pass (không đổi)
A18: L1-FES-08 | B18: EP-Invalid | C18: Server trả 429 (quá nhanh) -> hiển thị lỗi, không coi là đã gửi | D18: FT-01 BV-02 | E18: P2 | F18: MSW trả 429 kèm errorCode OTP_RESEND_TOO_SOON | G18: await authService.resendOtp({ email }) | H18: Trả lỗi có kiểm soát; UI không hiển thị 'đã gửi' Không tự retry ngầm | I18: Yes | J18: Pass | M18: ✅ Pass (không đổi)

Sheet FE-Contexts
A1: FE-Contexts (Vitest + RTL renderHook) | AuthContext, CartContext, ToastContext
A2: HOW TO USE: (1) Đọc Introduction (2) Trace theo SRS v2 (Part 3 + RTW Sheet 3/6/7) (3) Cập nhật Status sau mỗi lần chạy dotnet test / vitest (4) Ghi Defect ID khi Fail
A4: Test ID | B4: Coverage Technique | C4: Covers (Decision/Condition) | D4: SRS Reference | E4: Priority | F4: Given (Precondition / Mock Setup) | G4: When (Input / Act) | H4: Then (Expected Output / Assert) | I4: Negative? | J4: Status | K4: Defect ID | L4: Notes | M4: Fix Status
A5: ▶ Block: AuthContext | login/logout state
A6: L1-FEC-01 | B6: EP-Valid | C6: login() stores user + tokens; isAuthenticated = true | D6: NFR-SEC02 | E6: P1 | F6: MSW: /api/auth/login -> {user, accessToken, refreshToken} | G6: act(() => result.current.login(credentials)) | H6: user populated; isAuthenticated === true Token available to fetchWithToken | I6: No | J6: Pass | M6: ✅ Pass (không đổi)
A7: L1-FEC-02 | B7: EP-Valid | C7: logout() clears user/token state | D7: NFR-SEC02 | E7: P1 | F7: Authenticated state from L1-FEC-01 setup | G7: act(() => result.current.logout()) | H7: user = null; isAuthenticated === false; storage cleared | I7: No | J7: Pass | M7: ✅ Pass (không đổi)
A8: ▶ Block: CartContext | FT-01 NAC-01, cart state
A9: L1-FEC-03 | B9: EP-Valid | C9: addItem updates cart state and cartCount | D9: FT-01 AC-05 | E9: P1 | F9: Đã đăng nhập; MSW mock endpoint /api/Cart ProductCard.jsx gọi addToCart({ id, name, imageUrl, price }, 1) | G9: act(() => result.current.addToCart({ id:'P1', name:'SP A', imageUrl:'...', price:50000 }, 2)) | H9: Giỏ có 1 dòng P1 số lượng 2; cartCount = 2 Request gửi lên chứa productId='P1' (KHÔNG phải undefined) | I9: No | J9: Pass | M9: ✅ Pass (không đổi)
A10: L1-FEC-04 | B10: BC-TRUE | C10: GUEST addItem -> redirect to /login, intended product preserved for post-login add | D10: FT-01 AC-05; NAC-05 | E10: P1 | F10: CHƯA đăng nhập (khách vãng lai); localStorage trống Mock navigate | G10: act(() => result.current.addToCart({ id:'P1', name, price }, 1)) Sau đó đăng nhập và để CartContext chạy mergeGuestCartIntoServer() | H10: cartService.addGuestCartItem ghi localStorage['guestCart'] chứa P1 Sau khi đăng nhập: mergeGuestCartIntoServer() gộp P1 vào giỏ server localStorage['guestCart'] được xoá sau khi gộp thành công | I10: No | J10: Pass | M10: ✅ Pass (không đổi)
A11: ▶ Block: ToastContext
A12: L1-FEC-05 | B12: EP-Valid | C12: showToast renders toast then auto-dismisses after timeout | D12: NFR-U03 | E12: P3 | F12: vi.useFakeTimers() | G12: showToast('success','Đã thêm vào giỏ') ; vi.advanceTimersByTime(toastDuration) | H12: Toast visible with message; removed from DOM after duration | I12: No | J12: Pass | M12: ✅ Pass (không đổi)
A13: ▶ Template Row — copy khi thêm case mới
A14: L1-XX-[NN] | B14: [BC-TRUE | BC-FALSE | CC | EP-Valid | EP-Invalid | BVA-* | State-* | Guard-* | Concurrency | Idempotency | Atomicity] | C14: [Branch / condition / partition] | D14: [FT-xx AC/NAC/BV-xx; BR-xxx; NFR-xxx] | E14: P2 | F14: [Arrange: state + _mock.Setup(...)] | G14: service.Method(params) | H14: [result.Should().Be(...) / Throws / _mock.Verify(..., Times.Never)] | I14: No | J14: Not Run
A16: ▶ Block: ⊕ v2.3 — Gộp giỏ khách vãng lai | mergeGuestCartIntoServer | FT-01 AC-05; BR-025; FT-02 NAC-01
A17: L1-FEC-06 | B17: Concurrency | C17: Cờ mergingRef chống chạy song song khi React StrictMode double-invoke | D17: FT-01 AC-05 | E17: P1 | F17: localStorage['guestCart'] có 1 sản phẩm MSW đếm số request POST /api/Cart | G17: Render provider trong <StrictMode> (effect chạy 2 lần) hoặc gọi mergeGuestCartIntoServer() 2 lần liên tiếp | H17: Chỉ đúng 1 lượt gộp được thực hiện; KHÔNG tạo Cart trùng, KHÔNG cộng đôi số lượng localStorage['guestCart'] xoá đúng 1 lần | I17: No | J17: Pass | M17: ✅ Pass (không đổi)
A18: L1-FEC-07 | B18: EP-Invalid | C18: Giá của giỏ khách vãng lai phải do SERVER tính lại khi gộp | D18: BR-025; FT-02 NAC-01; FT-01 AC-05 | E18: P1 | F18: localStorage['guestCart'] chứa P1 kèm price=1000 (giá client, có thể bị sửa tay) | G18: Đăng nhập -> mergeGuestCartIntoServer() | H18: Request gộp chỉ gửi productId + quantity; server tự tính giá và tạo PriceSnapshot tại thời điểm gộp Nếu FE gửi kèm price và server tin theo -> LỖ HỔNG cùng loại CLIENT_PRICE_MISMATCH | I18: Yes | J18: Pass | M18: ✅ Pass (không đổi)
A19: L1-FEC-08 | B19: EP-Valid | C19: Gộp thất bại -> KHÔNG xoá guestCart (không mất hàng của khách) | D19: FT-01 AC-05 | E19: P2 | F19: localStorage['guestCart'] có 2 sản phẩm; MSW trả 500 cho POST /api/Cart | G19: Đăng nhập -> mergeGuestCartIntoServer() | H19: localStorage['guestCart'] VẪN còn nguyên để thử lại lần sau Hiển thị lỗi cho người dùng, không im lặng | I19: Yes | J19: Pass | M19: ⚠ FIX MỘT PHẦN CartContext.jsx:36-53 giữ nguyên guestCart khi merge lỗi (đúng) nhưng KHÔNG setError() nên người dùng không thấy lỗi.

Sheet FE-Components
A1: FE-Components (Vitest + RTL) | ProtectedRoute, Cart, Checkout, PhoneVerificationModal, Pagination, ProductCard, NotificationBell
A2: HOW TO USE: (1) Đọc Introduction (2) Trace theo SRS v2 (Part 3 + RTW Sheet 3/6/7) (3) Cập nhật Status sau mỗi lần chạy dotnet test / vitest (4) Ghi Defect ID khi Fail
A4: Test ID | B4: Coverage Technique | C4: Covers (Decision/Condition) | D4: SRS Reference | E4: Priority | F4: Given (Precondition / Mock Setup) | G4: When (Input / Act) | H4: Then (Expected Output / Assert) | I4: Negative? | J4: Status | K4: Defect ID | L4: Notes | M4: Fix Status
A5: ▶ Block: ProtectedRoute | role gating — NFR-SEC04
A6: L1-FCMP-01 | B6: BC-TRUE | C6: Unauthenticated user hits protected route -> redirected to /login | D6: FT-01 NAC-05; NFR-SEC03 | E6: P1 | F6: Auth state: not logged in; MemoryRouter at /checkout | G6: render(<ProtectedRoute><Checkout/></ProtectedRoute>) | H6: Redirect to /login rendered; Checkout content NOT in DOM | I6: Yes | J6: Pass | M6: ✅ Pass (không đổi)
A7: L1-FCMP-02 | B7: EP-Invalid | C7: Customer role opens /warehouse portal -> access blocked | D7: NFR-SEC03; FT-09 NAC-01 | E7: P1 | F7: Auth: role=Customer; route requires WarehouseStaff | G7: render warehouse route inside ProtectedRoute | H7: Warehouse portal NOT rendered; redirected/denied view shown | I7: Yes | J7: Pass | M7: ✅ Pass (không đổi)
A8: ▶ Block: Cart & Checkout pages | FT-01 NAC-02/NAC-03; FT-02 SB-2; FT-03 BV-01
A9: L1-FCMP-03 | B9: BC-TRUE | C9: Empty cart -> 'Proceed to Checkout' disabled + tooltip | D9: FT-01 AC-05 | E9: P1 | F9: MSW: GET /api/cart -> {items: []} | G9: render(<Cart/>) | H9: Checkout button disabled; tooltip 'Your cart is empty...' (VN text per Screen Design) No navigation on click | I9: Yes | J9: Pass | M9: ✅ Pass (không đổi)
A10: L1-FCMP-04 | B10: BC-TRUE | C10: Price-Expired cart -> warning banner + checkout blocked until refresh | D10: FT-01 NAC-03; BV-01; BR-025 | E10: P1 | F10: MSW: cart with isPriceExpired=true | G10: render(<Checkout/>) | H10: Banner 'Your cart prices may have changed...' visible Proceed blocked until user confirms refreshed prices | I10: Yes | J10: Blocked | L10: Không tồn tại isPriceExpired/banner giá trong FE — tính năng chưa có | M10: ❌ CHƯA FIX Suy luận từ ORD-09/GH-08 (BE vẫn chưa chặn giá hết hạn) — banner cảnh báo phía FE nhiều khả năng vẫn chưa tồn tại; CHƯA xác minh trực tiếp mã FE cho case này, cần kiểm tra lại Checkout component.
A11: L1-FCMP-05 | B11: Guard-FALSE | C11: Total >= 100M without negotiated price -> Payment hidden, 'Request Quotation' shown | D11: FT-02 AC-03; BR-026 | E11: P1 | F11: MSW: checkout summary {total:120,000,000, requiresQuotation:true} | G11: render(<Checkout/>) | H11: 'Proceed to Payment' NOT in DOM; 'Request Quotation' button rendered | I11: No | J11: Pass | M11: ⚠ FIX MỘT PHẦN Cart.jsx:323-342 đã hiện khối 'Yêu cầu báo giá đặc biệt' khi >=100M, nhưng nút 'Đặt Hàng & Xem Hóa Đơn' (426-433) vẫn hiện song song — khách vẫn bấm đặt hàng thẳng được.
A12: L1-FCMP-06 | B12: BVA-Max | C12: SePay 15-min countdown reaches 0 -> expired state + manual-verify guidance | D12: FT-03 BV-01; BR-008 | E12: P1 | F12: vi.useFakeTimers; QR screen with expiry NOW+15min | G12: render QR screen; vi.advanceTimersByTime(15*60*1000) | H12: Countdown shows 00:00; expired message rendered QR hidden/disabled; guidance to contact Sales for manual verification | I12: No | J12: Blocked | L12: Màn QR SePay không có đếm ngược 15 phút — tính năng chưa có | M12: ❌ CHƯA FIX Checkout.jsx:379 countdown chỉ là bộ đếm 5s auto-redirect SAU khi thanh toán xong, không phải bộ đếm hết hạn QR 15 phút. Màn QR (878-960) không có countdown/trạng thái hết hạn.
A13: ▶ Block: Form validation & shared components
A14: L1-FCMP-07 | B14: EP-Invalid | C14: Phone input '091234567' (9 digits) and '0912345678a' -> validation error shown | D14: FT-01 NAC-02; BV-02 | E14: P1 | F14: render(<PhoneVerificationModal/>) — [Theory-style test.each] | G14: type invalid phone; submit | H14: Error 'Invalid phone number format.' displayed; submit blocked; no API call (MSW not hit) | I14: Yes | J14: Fail | K14: GH-34 | M14: ❌ CHƯA FIX PhoneVerificationModal.jsx:29-52 chỉ check rỗng, không có regex định dạng — SĐT sai định dạng vẫn lọt qua và gọi API.
A15: L1-FCMP-08 | B15: BVA-Min | C15: Pagination on page 1 -> Prev disabled; renders correct page count | D15: FT-01 AC-01 | E15: P3 | F15: props {page:1, totalPages:5} | G15: render(<Pagination/>) | H15: Prev button disabled; 5 page indicators; onChange fires with correct page | I15: No | J15: Pass | M15: ✅ Pass (không đổi)
A16: L1-FCMP-09 | B16: EP-Valid | C16: ProductCard shows formatted VND price and product name | D16: FT-01 AC-01; NFR-U02 | E16: P3 | F16: product {name, price: 9999999} | G16: render(<ProductCard/>) | H16: Formatted price rendered ('9.999.999 ₫'); name visible; image alt set | I16: No | J16: Pass | M16: ✅ Pass (không đổi)
A17: L1-FCMP-10 | B17: EP-Valid | C17: NotificationBell shows unread count badge from service | D17: FT-09 AC-02 | E17: P2 | F17: MSW: /api/notifications/unread-count -> {count: 3} | G17: render(<NotificationBell/>) | H17: Badge '3' rendered; opening dropdown lists notifications | I17: No | J17: Pass | M17: ✅ Pass (không đổi)
A18: ▶ Template Row — copy khi thêm case mới
A19: L1-XX-[NN] | B19: [BC-TRUE | BC-FALSE | CC | EP-Valid | EP-Invalid | BVA-* | State-* | Guard-* | Concurrency | Idempotency | Atomicity] | C19: [Branch / condition / partition] | D19: [FT-xx AC/NAC/BV-xx; BR-xxx; NFR-xxx] | E19: P2 | F19: [Arrange: state + _mock.Setup(...)] | G19: service.Method(params) | H19: [result.Should().Be(...) / Throws / _mock.Verify(..., Times.Never)] | I19: No | J19: Not Run
A21: ▶ Block: ⊕ v2.3 — ProtectedRoute: prop allowGuest + điều hướng theo vai trò | NFR-SEC03; FT-01 NAC-05
A22: L1-FCMP-11 | B22: BC-TRUE | C22: allowGuest=true cho phép khách vãng lai xem route công khai | D22: FT-01 AC-01; NFR-SEC03 | E22: P2 | F22: Chưa đăng nhập; route /products bọc trong ProtectedRoute allowGuest | G22: render(<ProtectedRoute allowGuest><Products/></ProtectedRoute>) | H22: Nội dung hiển thị bình thường, KHÔNG redirect (khớp bảng vai trò SRS: Guest được duyệt catalogue) | I22: No | J22: Pass | M22: ✅ Pass (không đổi)
A23: L1-FCMP-12 | B23: BC-FALSE | C23: allowGuest KHÔNG được rò sang route nhạy cảm | D23: FT-01 NAC-05; NFR-SEC03 | E23: P1 | F23: Chưa đăng nhập [Theory] /checkout, /profile, /sales, /admin, /warehouse | G23: Truy cập từng route trên | H23: TẤT CẢ đều redirect /login, không route nào render nội dung allowGuest chỉ có tác dụng ở route được khai báo tường minh | I23: Yes | J23: Pass | M23: ✅ Pass (không đổi)
A24: L1-FCMP-13 | B24: EP-Valid | C24: Bảng điều hướng sau đăng nhập theo vai trò | D24: NFR-SEC03; FT-09 AC-01 | E24: P2 | F24: [Theory] vai trò SalesStaff / SalesManager / Admin / CEO / WarehouseStaff / Customer | G24: Đăng nhập rồi vào route gốc được bảo vệ | H24: Điều hướng đúng: /sales · /sales-manager · /admin · CEOPortal · /warehouse · trang khách Không vai trò nào rơi vào portal của vai trò khác | I24: No | J24: Pass | M24: ✅ Pass (không đổi)

Sheet InventoryReservationService
A1: InventoryReservationService | MỚI v2.1 | methods: ReserveAsync, AllocateAsync, ReleaseReservedAsync, ReleaseAllocatedAsync, DeductOnHandAsync | FT-03; FT-05; BR-008/032/033
A2: HOW TO USE: (1) Đọc Introduction (2) Trace theo SRS v2 (Part 3 + RTW Sheet 3/6/7) (3) Cập nhật Status sau mỗi lần chạy dotnet test / vitest (4) Ghi Defect ID khi Fail
A4: Test ID | B4: Coverage Technique | C4: Covers (Decision/Condition) | D4: SRS Reference | E4: Priority | F4: Given (Precondition / Mock Setup) | G4: When (Input / Act) | H4: Then (Expected Output / Assert) | I4: Negative? | J4: Status | K4: Defect ID | L4: Notes | M4: Fix Status
A5: ▶ Block: ReserveAsync() | FT-03 AC-01; BR-008; BV-01
A6: L1-RES-01 | B6: EP-Valid | C6: Giữ tồn cho đơn SePay -> hạn 15 phút | D6: FT-03 AC-01; BR-008 | E6: P1 | F6: Inventory P1: OnHand=10, Reserved=0, Allocated=0, Damaged=0, Quarantine=0 => AvailableQuantity = 10 | G6: reservationService.ReserveAsync(new[]{ (P1, 3) }) | H6: Reserved P1 = 3; OnHand vẫn = 10 AvailableQuantity (computed) = 10-3-0-0-0 = 7 Method trả Task (void), không ném exception | I6: No | J6: Pass | M6: ✅ Pass (không đổi)
A7: L1-RES-02 | B7: EP-Valid | C7: Giữ tồn cho đơn COD -> hạn 35 phút | D7: FT-03 AC-04; BR-008; BV-02 | E7: P1 | F7: Inventory P1 Available=10, P2 Available=5 | G7: reservationService.ReserveAsync(new[]{ (P1,3), (P2,2) }) | H7: Cả 2 SKU cùng tăng Reserved trong 1 lệnh P1 Available=7; P2 Available=3 | I7: No | J7: Pass | M7: ✅ Pass (không đổi)
A8: L1-RES-03 | B8: BVA-Max | C8: Giữ đúng bằng tồn khả dụng -> cho phép, Available về 0 | D8: FT-05 BV-01; BR-032 | E8: P1 | F8: Inventory P1: OnHand=10, Reserved=0 => Available=10 | G8: reservationService.ReserveAsync(new[]{ (P1, 10) }) | H8: Reserved = 10; OnHandQuantity vẫn = 10 RawAvailable() = 10-10-0-0-0 = 0 (assert biểu thức THÔ, không dùng AvailableQuantity) Không ném exception | I8: No | J8: Pass | L8: 🟠 BẪY ASSERTION: Inventory.AvailableQuantity (Inventory.cs:24) bọc Math.Max(0, ...) nên assert "không âm" LUÔN XANH kể cả khi đã oversell. Phải assert OnHandQuantity VÀ biểu thức thô RawAvailable() (= OnHand - Reserved - Allocated - Damaged - Quarantine, CHƯA kẹp). | M8: ✅ Pass (không đổi)
A9: L1-RES-04 | B9: BVA-Max+1 | C9: Giữ vượt tồn khả dụng 1 đơn vị -> từ chối toàn bộ | D9: FT-05 NAC-01; BV-01; BR-032 | E9: P1 | F9: Inventory P1 Available=10 | G9: reservationService.ReserveAsync(new[]{ (P1, 11) }) | H9: Ném Exception (thiếu tồn) Reserved P1 vẫn = 0; OnHandQuantity = 10; RawAvailable() = 10 KHÔNG assert AvailableQuantity | I9: Yes | J9: Pass | L9: 🟠 BẪY ASSERTION: Inventory.AvailableQuantity (Inventory.cs:24) bọc Math.Max(0, ...) nên assert "không âm" LUÔN XANH kể cả khi đã oversell. Phải assert OnHandQuantity VÀ biểu thức thô RawAvailable() (= OnHand - Reserved - Allocated - Damaged - Quarantine, CHƯA kẹp). | M9: ✅ Pass (không đổi)
A10: L1-RES-05 | B10: Atomicity | C10: Nhiều dòng, 1 dòng thiếu hàng -> rollback toàn bộ | D10: FT-05 NAC-01; BR-032 | E10: P1 | F10: Inventory P1 Available=10, P2 Available=1 | G10: reservationService.ReserveAsync(new[]{ (P1,4), (P2,2) }) | H10: Ném Exception P1 KHÔNG bị giữ 4 — toàn bộ lệnh rollback trong 1 transaction | I10: Yes | J10: Pass | M10: ✅ Pass (không đổi)
A11: L1-RES-06 | B11: Concurrency | C11: Hai đơn cùng giữ 10 sản phẩm cuối -> đúng 1 đơn thành công | D11: FT-05 NAC-01; NFR-A05; NFR-D01 | E11: P1 | F11: Inventory P1 Available=10; hai luồng song song dùng TaskCompletionSource làm barrier | G11: Task.WhenAll( ReserveAsync(new[]{(P1,10)}), ReserveAsync(new[]{(P1,10)}) ) | H11: Đúng 1 luồng thành công, 1 luồng ném Exception OnHandQuantity = 10, Reserved = 10, RawAvailable() = 0 và KHÔNG ÂM | I11: No | J11: Pass | L11: ⚠ KHÔNG THAY THẾ ĐƯỢC L2: chạy in-memory nên ghi bị serialise. Bằng chứng thật cho NFR-A05/D01 là L2-FUL-08 (Pass 5/5 vòng trên SQL Server thật). | 🟠 BẪY ASSERTION: Inventory.AvailableQuantity (Inventory.cs:24) bọc Math.Max(0, ...) nên assert "không âm" LUÔN XANH kể cả khi đã oversell. Phải assert OnHandQuantity VÀ biểu thức thô RawAvailable() (= OnHand - Reserved - Allocated - Damaged - Quarantine, CHƯA kẹp). | M11: ✅ Pass (không đổi)
A12: ▶ Block: AllocateAsync() / ReleaseReservedAsync() / ReleaseAllocatedAsync() | BR-033
A13: L1-RES-07 | B13: EP-Valid | C13: Chuyển Reserved -> Allocated nguyên tử | D13: FT-03 AC-02; FT-05 AC-02 | E13: P1 | F13: Inventory P1: Reserved=3, Allocated=0 | G13: reservationService.AllocateAsync(new[]{ (P1, 3) }) | H13: Reserved=0; Allocated=3; OnHand không đổi AvailableQuantity không đổi (cả 2 đều trừ vào Available) | I13: No | J13: Pass | M13: ✅ Pass (không đổi)
A14: L1-RES-08 | B14: EP-Valid | C14: Hết hạn giữ chỉ giải phóng phần RESERVED, KHÔNG đụng ALLOCATED | D14: BR-033; FT-05 AC-02 | E14: P1 | F14: Inventory P1: Reserved=3, Available=7 | G14: reservationService.ReleaseReservedAsync(new[]{ (P1, 3) }) | H14: Reserved=0; Available=10 KHÔNG đụng tới AllocatedQuantity | I14: No | J14: Pass | M14: ✅ Pass (không đổi)
A15: L1-RES-09 | B15: State-Invalid | C15: Giải phóng reservation đã chuyển allocated -> từ chối | D15: BR-033; FT-03 BV-03 | E15: P1 | F15: Inventory P1: Reserved=1 (ít hơn số muốn trả) | G15: reservationService.ReleaseReservedAsync(new[]{ (P1, 3) }) | H15: Ném Exception hoặc chặn; Reserved không xuống dưới 0 Assert trực tiếp giá trị Reserved, không suy ra qua AvailableQuantity | I15: Yes | J15: Pass | L15: 🟠 BẪY ASSERTION: Inventory.AvailableQuantity (Inventory.cs:24) bọc Math.Max(0, ...) nên assert "không âm" LUÔN XANH kể cả khi đã oversell. Phải assert OnHandQuantity VÀ biểu thức thô RawAvailable() (= OnHand - Reserved - Allocated - Damaged - Quarantine, CHƯA kẹp). | M15: ✅ Pass (không đổi)
A16: L1-RES-10 | B16: EP-Valid | C16: ReleaseAllocated khi huỷ đơn -> trả hàng về khả dụng | D16: FT-08 AC-01; BR-032 | E16: P1 | F16: Inventory P1: Allocated=3, Available=7 | G16: reservationService.ReleaseAllocatedAsync(new[]{ (P1, 3) }) | H16: Allocated=0; Available=10; Reserved không đổi | I16: No | J16: Pass | M16: ✅ Pass (không đổi)
A17: ▶ Block: DeductOnHandAsync() | BR-032; NFR-A05
A18: L1-RES-11 | B18: EP-Valid | C18: Trừ tồn thực khi xuất kho -> OnHand giảm, Allocated giảm | D18: FT-05 AC-05; BR-032 | E18: P1 | F18: Inventory P1: OnHand=10, Reserved=0, Allocated=0 (bán tại quầy, KHÔNG qua Reserve/Allocate) | G18: reservationService.DeductOnHandAsync(new[]{ (P1, 3) }) | H18: OnHand=7; Reserved/Allocated không đổi AvailableQuantity=7 | I18: No | J18: Pass | M18: ✅ Pass (không đổi)
A19: L1-RES-12 | B19: BVA-Min-1 | C19: Trừ tồn làm OnHand âm -> chặn | D19: FT-05 NAC-01; BV-01; BR-032 | E19: P1 | F19: Inventory P1: OnHand=2 | G19: reservationService.DeductOnHandAsync(new[]{ (P1, 3) }) | H19: Ném Exception; OnHandQuantity vẫn = 2 (guarded UPDATE chặn tại DB) RawAvailable() không âm | I19: Yes | J19: Pass | L19: 🟠 BẪY ASSERTION: Inventory.AvailableQuantity (Inventory.cs:24) bọc Math.Max(0, ...) nên assert "không âm" LUÔN XANH kể cả khi đã oversell. Phải assert OnHandQuantity VÀ biểu thức thô RawAvailable() (= OnHand - Reserved - Allocated - Damaged - Quarantine, CHƯA kẹp). | M19: ✅ Pass (không đổi)
A20: L1-RES-13 | B20: Idempotency | C20: Gọi trừ tồn lần 2 cho cùng đơn -> không trừ kép | D20: BR-029; BR-032 | E20: P1 | F20: Inventory P1: OnHand=10 | G20: Gọi DeductOnHandAsync(new[]{(P1,3)}) HAI lần liên tiếp | H20: OnHand = 4 — service KHÔNG tự idempotent (đúng thiết kế) => Idempotency phải do tầng gọi (OrderService) đảm bảo bằng business key | I20: Yes | J20: Pass | M20: ✅ Pass (không đổi)
A21: ▶ Template Row — copy khi thêm case mới
A22: L1-XX-[NN] | B22: [BC-TRUE | BC-FALSE | CC | EP-Valid | EP-Invalid | BVA-* | State-* | Guard-* | Concurrency | Idempotency | Atomicity] | C22: [Branch / condition / partition] | D22: [FT-xx AC/NAC/BV-xx; BR-xxx; NFR-xxx] | E22: P2 | F22: [Arrange: state + _mock.Setup(...)] | G22: service.Method(params) | H22: [result.Should().Be(...) / Throws / _mock.Verify(..., Times.Never)] | I22: No | J22: Not Run
A24: ▶ Block: ⊕ v2.2 — Công thức AvailableQuantity | BR-032; FT-05 BV-01
A25: L1-RES-14 | B25: BVA-Min | C25: Available = OnHand - Reserved - Allocated - Damaged - Quarantine, sàn tại 0 | D25: FT-05 BV-01; BR-032 | E25: P1 | F25: Inventory P1: OnHand=10, Reserved=3, Allocated=2, Damaged=1, Quarantine=1 | G25: Đọc thuộc tính tính toán inventory.AvailableQuantity | H25: RawAvailable() = 10-3-2-1-1 = 3 [Theory] khi tổng trừ VƯỢT OnHand: RawAvailable() ÂM (dấu hiệu oversell cần phát hiện) trong khi AvailableQuantity vẫn trả 0 do Math.Max => chính là lý do KHÔNG được assert trên AvailableQuantity | I25: No | J25: Pass | L25: 🟠 BẪY ASSERTION: Inventory.AvailableQuantity (Inventory.cs:24) bọc Math.Max(0, ...) nên assert "không âm" LUÔN XANH kể cả khi đã oversell. Phải assert OnHandQuantity VÀ biểu thức thô RawAvailable() (= OnHand - Reserved - Allocated - Damaged - Quarantine, CHƯA kẹp). | M25: ✅ Pass (không đổi)
A26: L1-RES-15 | B26: EP-Valid | C26: Hàng cách ly và hàng hỏng bị loại khỏi tồn bán được | D26: FT-08 AC-05; BR-019; BR-032 | E26: P1 | F26: Inventory P1: OnHand=10, Quarantine=4 (hàng trả về chờ kiểm định) | G26: Đọc inventory.AvailableQuantity | H26: RawAvailable() = 10-0-0-0-4 = 6 — hàng cách ly KHÔNG bán được (FT-08) | I26: No | J26: Pass | L26: 🟠 BẪY ASSERTION: Inventory.AvailableQuantity (Inventory.cs:24) bọc Math.Max(0, ...) nên assert "không âm" LUÔN XANH kể cả khi đã oversell. Phải assert OnHandQuantity VÀ biểu thức thô RawAvailable() (= OnHand - Reserved - Allocated - Damaged - Quarantine, CHƯA kẹp). | M26: ✅ Pass (không đổi)

Sheet DiscountTierService
A1: DiscountTierService | MỚI v2.1 | methods: GetAll, GetById, Create, Update, GetApplicableDiscountPercent | FT-02; BR-006; BR-050
A2: HOW TO USE: (1) Đọc Introduction (2) Trace theo SRS v2 (Part 3 + RTW Sheet 3/6/7) (3) Cập nhật Status sau mỗi lần chạy dotnet test / vitest (4) Ghi Defect ID khi Fail
A4: Test ID | B4: Coverage Technique | C4: Covers (Decision/Condition) | D4: SRS Reference | E4: Priority | F4: Given (Precondition / Mock Setup) | G4: When (Input / Act) | H4: Then (Expected Output / Assert) | I4: Negative? | J4: Status | K4: Defect ID | L4: Notes | M4: Fix Status
A5: ▶ Block: GetApplicableDiscountPercentAsync() | FT-02 AC-01; BV-01; BR-006
A6: L1-DT-01 | B6: BVA-Max | C6: Tổng 9.999.999đ -> 0% (giá niêm yết) | D6: FT-02 AC-01; BV-01; BR-006 | E6: P1 | F6: Bảng bậc chiết khấu đã seed | G6: discountTierService.GetApplicableDiscountPercentAsync(9_999_999) | H6: Trả 0% — dưới ngưỡng bậc đầu tiên | I6: No | J6: Pass | M6: ✅ Pass (không đổi)
A7: L1-DT-02 | B7: BVA-Min | C7: Tổng đúng 10.000.000đ -> áp bậc đầu tiên | D7: FT-02 AC-01; BV-01; BR-006 | E7: P1 | F7: Bậc 1 bắt đầu từ 10.000.000đ | G7: discountTierService.GetApplicableDiscountPercentAsync(10_000_000) | H7: Trả đúng % của bậc 1 (không phải 0%) | I7: No | J7: Pass | M7: ✅ Pass (không đổi)
A8: L1-DT-03 | B8: BVA-Max | C8: Tổng 99.999.999đ -> vẫn trong dải chiết khấu tự động | D8: FT-02 BV-01; BR-006 | E8: P1 | F8: Bảng bậc seed đầy đủ | G8: discountTierService.GetApplicableDiscountPercentAsync(99_999_999) | H8: Trả % của bậc cao nhất < 100M; không rơi vào luồng báo giá | I8: No | J8: Pass | M8: ✅ Pass (không đổi)
A9: L1-DT-04 | B9: BVA-Min | C9: Tổng đúng 100.000.000đ -> KHÔNG áp chiết khấu tự động | D9: FT-02 AC-01; BV-01; BR-026 | E9: P1 | F9: Ngưỡng báo giá = 100.000.000đ | G9: discountTierService.GetApplicableDiscountPercentAsync(100_000_000) | H9: Trả 0% / báo cần báo giá — không tự áp bậc | I9: No | J9: Pass | M9: ✅ Pass (không đổi)
A10: L1-DT-05 | B10: BVA-Min-1 | C10: Tổng âm hoặc 0 -> 0%, không lỗi | D10: FT-02 BV-01 | E10: P2 | F10: [Theory] subtotal = -1 và 0 | G10: discountTierService.GetApplicableDiscountPercentAsync(x) | H10: Trả 0%; không ném lỗi hạ tầng | I10: No | J10: Pass | M10: ✅ Pass (không đổi)
A11: L1-DT-06 | B11: EP-Valid | C11: Chỉ dùng bậc đang hiệu lực tại thời điểm tính | D11: BR-050; FT-09 AC-03 | E11: P1 | F11: Bậc cũ hết hiệu lực hôm qua, bậc mới hiệu lực hôm nay | G11: discountTierService.GetApplicableDiscountPercentAsync(15_000_000) | H11: Áp bậc MỚI; bậc hết hiệu lực bị bỏ qua | I11: No | J11: Pass | M11: ✅ Pass (không đổi)
A12: ▶ Block: CRUD | BR-050; FT-09 AC-03
A13: L1-DT-07 | B13: EP-Invalid | C13: Tạo bậc chồng lấn khoảng giá trị -> từ chối | D13: BR-006; BR-050 | E13: P1 | F13: Đã có bậc 10.000.000–49.999.999 | G13: discountTierService.CreateAsync(dto{from:30_000_000, to:60_000_000}) | H13: Từ chối vì chồng lấn; bảng bậc không đổi | I13: Yes | J13: Pass | M13: ✅ ĐÃ FIX DiscountTierService.cs:36,114-124 EnsureNoOverlapAsync throw khi khoảng giá trị chồng lấn.
A14: L1-DT-08 | B14: EP-Invalid | C14: Tạo bậc có % ngoài khoảng 0–100 -> từ chối | D14: BR-006 | E14: P2 | F14: [Theory] percent = -1 và 101 | G14: discountTierService.CreateAsync(dto{percent:x}) | H14: Từ chối validation | I14: Yes | J14: Pass | M14: ✅ Pass (không đổi)
A15: L1-DT-09 | B15: EP-Valid | C15: Sửa bậc tạo phiên bản hiệu lực mới, không ghi đè lịch sử | D15: BR-050; FT-09 NAC-04 | E15: P1 | F15: Bậc T1 đang hiệu lực và đã dùng cho đơn cũ | G15: discountTierService.UpdateAsync(T1, dto) | H15: Giá trị cũ vẫn tra cứu được; đơn cũ không bị tính lại | I15: No | J15: Pass | M15: ✅ Pass (không đổi)
A16: ▶ Template Row — copy khi thêm case mới
A17: L1-XX-[NN] | B17: [BC-TRUE | BC-FALSE | CC | EP-Valid | EP-Invalid | BVA-* | State-* | Guard-* | Concurrency | Idempotency | Atomicity] | C17: [Branch / condition / partition] | D17: [FT-xx AC/NAC/BV-xx; BR-xxx; NFR-xxx] | E17: P2 | F17: [Arrange: state + _mock.Setup(...)] | G17: service.Method(params) | H17: [result.Should().Be(...) / Throws / _mock.Verify(..., Times.Never)] | I17: No | J17: Not Run

Sheet SystemConfigService
A1: SystemConfigService | MỚI v2.1 | methods: GetAllAsync, GetEffectiveValueAsync, GetHistoryAsync, SetValueAsync | FT-09; BR-050; BR-022
A2: HOW TO USE: (1) Đọc Introduction (2) Trace theo SRS v2 (Part 3 + RTW Sheet 3/6/7) (3) Cập nhật Status sau mỗi lần chạy dotnet test / vitest (4) Ghi Defect ID khi Fail
A4: Test ID | B4: Coverage Technique | C4: Covers (Decision/Condition) | D4: SRS Reference | E4: Priority | F4: Given (Precondition / Mock Setup) | G4: When (Input / Act) | H4: Then (Expected Output / Assert) | I4: Negative? | J4: Status | K4: Defect ID | L4: Notes | M4: Fix Status
A5: ▶ Block: GetEffectiveValueAsync() | FT-09 AC-03; BV-02; BR-050
A6: L1-CFG-01 | B6: BVA | C6: Lấy giá trị tại T-1s / T / T+1s quanh thời điểm hiệu lực | D6: FT-09 BV-02; BR-050 | E6: P1 | F6: Config key 'QUOTATION_MIN_VALUE' có phiên bản mới hiệu lực từ T | G6: [Theory] systemConfigService.GetEffectiveValueAsync('QUOTATION_MIN_VALUE', asOf: T-1s | T | T+1s) | H6: T-1s trả giá trị CŨ; T và T+1s trả giá trị MỚI Kiểu trả về là string? — phải parse trước khi so sánh | I6: No | J6: Pass | M6: ✅ Pass (không đổi)
A7: L1-CFG-02 | B7: EP-Invalid | C7: Khoá cấu hình không tồn tại -> trả mặc định / not-found rõ ràng | D7: FT-09 AC-03 | E7: P2 | F7: Không tồn tại key 'UNKNOWN_KEY' | G7: systemConfigService.GetEffectiveValueAsync('UNKNOWN_KEY') | H7: Trả null (kiểu string?) — không ném lỗi hạ tầng Tầng gọi phải có giá trị mặc định | I7: Yes | J7: Pass | M7: ✅ Pass (không đổi)
A8: ▶ Block: SetValueAsync() / GetHistoryAsync() | BR-022; BR-050
A9: L1-CFG-03 | B9: EP-Valid | C9: Đổi cấu hình tạo PHIÊN BẢN mới + ghi audit, không ghi đè bản cũ | D9: FT-09 AC-03; AC-04; BR-050; BR-022 | E9: P1 | F9: Key 'COD_WARNING_MINUTES' đang có giá trị 25 | G9: systemConfigService.SetValueAsync('COD_WARNING_MINUTES', UpdateSystemConfigRequest{Value:'20'}, actorUserId, actorEmail, ipAddress) | H9: Tạo phiên bản MỚI; GetHistoryAsync('COD_WARNING_MINUTES') trả cả bản 25 và 20 AuditLog ghi actorEmail + ipAddress + before/after | I9: No | J9: Pass | M9: ✅ Pass (không đổi)
A10: L1-CFG-04 | B10: EP-Invalid | C10: Đặt thời điểm hiệu lực vào QUÁ KHỨ để tính lại dữ liệu cũ -> từ chối | D10: FT-09 NAC-04; BR-050 | E10: P1 | F10: Có giỏ hàng đang giữ giá và đơn đã hoàn tất | G10: systemConfigService.SetValueAsync('LIST_PRICE_MAX_EXCLUSIVE', request{EffectiveFrom: NOW-1d}, actor...) | H10: Từ chối thay đổi hồi tố; snapshot giá và đơn cũ không đổi | I10: Yes | J10: Pass | M10: ✅ ĐÃ FIX SystemConfigService.cs:95-96 throw nếu EffectiveDate < UtcNow (chặn hồi tố).
A11: L1-CFG-05 | B11: EP-Invalid | C11: Ghi audit thất bại -> giao dịch cấu hình KHÔNG hoàn tất | D11: FT-09 AC-04; BR-022 | E11: P1 | F11: Mock audit ném lỗi khi ghi | G11: systemConfigService.SetValueAsync('PRICE_LOCK_HOURS', request, actor...) | H11: Cấu hình KHÔNG được lưu — rollback trọn vẹn | I11: Yes | J11: Pass | M11: ✅ Pass (không đổi)
A12: L1-CFG-06 | B12: EP-Valid | C12: Lịch sử trả theo thứ tự thời gian, đủ actor và lý do | D12: FT-09 AC-04 | E12: P2 | F12: Key 'SEPAY_RESERVATION_MINUTES' đã đổi 3 lần | G12: systemConfigService.GetHistoryAsync('SEPAY_RESERVATION_MINUTES') | H12: Trả List<SystemConfigVersionDto> đủ 3 bản, sắp theo thời gian, mỗi bản có actor + giá trị | I12: No | J12: Pass | M12: ✅ Pass (không đổi)
A13: ▶ Template Row — copy khi thêm case mới
A14: L1-XX-[NN] | B14: [BC-TRUE | BC-FALSE | CC | EP-Valid | EP-Invalid | BVA-* | State-* | Guard-* | Concurrency | Idempotency | Atomicity] | C14: [Branch / condition / partition] | D14: [FT-xx AC/NAC/BV-xx; BR-xxx; NFR-xxx] | E14: P2 | F14: [Arrange: state + _mock.Setup(...)] | G14: service.Method(params) | H14: [result.Should().Be(...) / Throws / _mock.Verify(..., Times.Never)] | I14: No | J14: Not Run

Sheet AdminUserService
A1: AdminUserService | MỚI v2.1 | methods: SearchAsync, GetByIdAsync, CreateStaffAsync, ChangeRoleAsync, SetActiveStatusAsync | FT-09; NFR-SEC03; BR-022
A2: HOW TO USE: (1) Đọc Introduction (2) Trace theo SRS v2 (Part 3 + RTW Sheet 3/6/7) (3) Cập nhật Status sau mỗi lần chạy dotnet test / vitest (4) Ghi Defect ID khi Fail
A4: Test ID | B4: Coverage Technique | C4: Covers (Decision/Condition) | D4: SRS Reference | E4: Priority | F4: Given (Precondition / Mock Setup) | G4: When (Input / Act) | H4: Then (Expected Output / Assert) | I4: Negative? | J4: Status | K4: Defect ID | L4: Notes | M4: Fix Status
A5: ▶ Block: CreateStaffAsync() / ChangeRoleAsync() | FT-09 AC-04; BR-022
A6: L1-ADM-01 | B6: EP-Valid | C6: Tạo tài khoản nhân viên -> mật khẩu lưu dạng hash, gán đúng vai trò | D6: NFR-SEC02; FT-09 AC-04 | E6: P1 | F6: Email nhân viên mới chưa tồn tại | G6: adminUserService.CreateStaffAsync(CreateStaffUserRequest, actorUserId, actorEmail, ipAddress) | H6: Trả AdminUserDto đúng vai trò; PasswordHash != plaintext AuditLog ghi actorEmail + ipAddress | I6: No | J6: Pass | M6: ✅ Pass (không đổi)
A7: L1-ADM-02 | B7: EP-Invalid | C7: Tạo nhân viên trùng email -> từ chối | D7: FT-01 NAC-01 | E7: P1 | F7: Email đã tồn tại | G7: adminUserService.CreateStaffAsync(request{emailTrùng}, actor...) | H7: Ném lỗi trùng danh tính; không tạo user thứ 2 | I7: Yes | J7: Pass | M7: ✅ Pass (không đổi)
A8: L1-ADM-03 | B8: EP-Valid | C8: Đổi vai trò -> ghi audit before/after | D8: FT-09 AC-04; BR-022 | E8: P1 | F8: U1 đang là SalesStaff | G8: adminUserService.ChangeRoleAsync(U1, ChangeUserRoleRequest{Role:'SalesManager'}, actor...) | H8: Vai trò đổi; AuditLog ghi before/after + actorEmail + ipAddress | I8: No | J8: Pass | M8: ✅ Pass (không đổi)
A9: L1-ADM-04 | B9: EP-Invalid | C9: Đổi vai trò sang giá trị không hợp lệ -> từ chối | D9: NFR-SEC03 | E9: P1 | F9: Vai trò 'SuperUser' không nằm trong 7 vai trò SRS | G9: adminUserService.ChangeRoleAsync(U1, request{Role:'SuperUser'}, actor...) | H9: Từ chối validation; vai trò cũ giữ nguyên | I9: Yes | J9: Pass | M9: ✅ Pass (không đổi)
A10: L1-ADM-05 | B10: EP-Invalid | C10: Hạ vai trò Sales đang phụ trách khách -> phải xử lý bàn giao trước | D10: FT-04 NAC-03; BV-01 | E10: P1 | F10: S1 đang phụ trách 5 khách (CustomerProfile.AssignedSalesStaffId = S1) | G10: adminUserService.ChangeRoleAsync(S1, request{Role:'WarehouseStaff'}, actor...) | H10: Từ chối hoặc buộc bàn giao trước — không để 5 khách mất người phụ trách | I10: Yes | J10: Pass | M10: ✅ ĐÃ FIX AdminUserService.cs:145-152 check còn khách gán cho NV trước khi đổi role, throw nếu còn.
A11: ▶ Block: SetActiveStatusAsync() / SearchAsync()
A12: L1-ADM-06 | B12: EP-Valid | C12: Vô hiệu hoá tài khoản -> phiên hiện tại không dùng được nữa | D12: NFR-SEC02; NFR-SEC03 | E12: P1 | F12: U1 đang hoạt động, có RefreshToken | G12: adminUserService.SetActiveStatusAsync(U1, SetUserActiveStatusRequest{IsActive:false}, actor...) | H12: IsActive=false; refresh token bị thu hồi; AuditLog được ghi | I12: No | J12: Pass | M12: ✅ Pass (không đổi)
A13: L1-ADM-07 | B13: EP-Invalid | C13: Vô hiệu hoá Sales đang là người duy nhất trong round-robin -> cảnh báo/chặn | D13: FT-04 NAC-03; BV-02 | E13: P1 | F13: Chỉ còn S1 trong danh sách round-robin | G13: adminUserService.SetActiveStatusAsync(S1, request{IsActive:false}, actor...) | H13: Chặn hoặc cảnh báo — tránh không còn ai nhận khách mới | I13: Yes | J13: Pass | M13: ✅ ĐÃ FIX AdminUserService.cs:209-216 đếm NV Sales active còn lại, chặn vô hiệu hoá người cuối cùng.
A14: L1-ADM-08 | B14: EP-Valid | C14: Search lọc theo vai trò + trạng thái + phân trang | D14: FT-09 AC-01 | E14: P3 | F14: 10 user: 4 SalesStaff (1 inactive) | G14: adminUserService.SearchAsync(AdminUserQueryDto{Role:'SalesStaff', IsActive:true}) | H14: Trả PagedResultDto<AdminUserDto> đúng 3 user; TotalCount=3 | I14: No | J14: Pass | M14: ✅ Pass (không đổi)
A15: L1-ADM-09 | B15: EP-Invalid | C15: GetById với id không tồn tại -> not-found, không lộ thông tin | D15: FT-09 NAC-01 | E15: P3 | F15: Không có user Ux | G15: adminUserService.GetByIdAsync(Ux) | H15: Ném not-found; không lộ thông tin | I15: Yes | J15: Pass | M15: ✅ Pass (không đổi)
A16: ▶ Template Row — copy khi thêm case mới
A17: L1-XX-[NN] | B17: [BC-TRUE | BC-FALSE | CC | EP-Valid | EP-Invalid | BVA-* | State-* | Guard-* | Concurrency | Idempotency | Atomicity] | C17: [Branch / condition / partition] | D17: [FT-xx AC/NAC/BV-xx; BR-xxx; NFR-xxx] | E17: P2 | F17: [Arrange: state + _mock.Setup(...)] | G17: service.Method(params) | H17: [result.Should().Be(...) / Throws / _mock.Verify(..., Times.Never)] | I17: No | J17: Not Run

Sheet VehicleService
A1: VehicleService | MỚI v2.1 | methods: GetAllAsync, GetByIdAsync, CreateAsync, UpdateAsync | FT-07; BV-01; BR-037
A2: HOW TO USE: (1) Đọc Introduction (2) Trace theo SRS v2 (Part 3 + RTW Sheet 3/6/7) (3) Cập nhật Status sau mỗi lần chạy dotnet test / vitest (4) Ghi Defect ID khi Fail
A4: Test ID | B4: Coverage Technique | C4: Covers (Decision/Condition) | D4: SRS Reference | E4: Priority | F4: Given (Precondition / Mock Setup) | G4: When (Input / Act) | H4: Then (Expected Output / Assert) | I4: Negative? | J4: Status | K4: Defect ID | L4: Notes | M4: Fix Status
A5: ▶ Block: CRUD đội xe | FT-07 BV-01; BR-037
A6: L1-VEH-01 | B6: EP-Valid | C6: Danh sách xe chỉ trả xe đang hoạt động khi lọc active | D6: FT-07 BV-01; BR-037 | E6: P1 | F6: 5 xe: 4 active, 1 bảo trì | G6: vehicleService.GetAllAsync(query{active:true}) | H6: Trả đúng 4 xe; xe bảo trì không xuất hiện để chọn lịch | I6: No | J6: Pass | M6: ✅ Pass (không đổi)
A7: L1-VEH-02 | B7: EP-Valid | C7: Tạo xe mới với biển số hợp lệ | D7: FT-07 BR-037 | E7: P3 | F7: Biển số chưa tồn tại | G7: vehicleService.CreateAsync(dto) | H7: Xe được lưu, mặc định trạng thái hoạt động | I7: No | J7: Pass | M7: ✅ Pass (không đổi)
A8: L1-VEH-03 | B8: EP-Invalid | C8: Tạo xe trùng biển số -> từ chối | D8: BR-037 | E8: P2 | F8: Biển số đã tồn tại | G8: vehicleService.CreateAsync(dto{biểnSốTrùng}) | H8: Từ chối; không tạo bản ghi thứ 2 | I8: Yes | J8: Pass | M8: ✅ ĐÃ FIX VehicleService.cs:44-46 check trùng biển số, throw nếu trùng.
A9: L1-VEH-04 | B9: EP-Valid | C9: Chuyển xe sang trạng thái bảo trì -> không còn xếp lịch được | D9: FT-07 NAC-01; BR-037 | E9: P1 | F9: Xe V1 đang hoạt động | G9: vehicleService.UpdateAsync(V1, dto{status:'Maintenance'}) | H9: V1 không còn trong danh sách xe khả dụng để lập chuyến | I9: No | J9: Pass | M9: ✅ Pass (không đổi)
A10: L1-VEH-05 | B10: EP-Invalid | C10: Đưa xe đang có chuyến trong tương lai vào bảo trì -> cảnh báo/chặn | D10: FT-07 NAC-01 | E10: P2 | F10: V1 đã được xếp chuyến ngày mai | G10: vehicleService.UpdateAsync(V1, dto{status:'Maintenance'}) | H10: Chặn hoặc buộc xử lý chuyến đã xếp trước | I10: Yes | J10: Pass | L10: VehicleService không biết tới lịch chuyến — tính năng chưa có | M10: ✅ ĐÃ FIX VehicleService.cs:91-102 khi chuyển sang Maintenance, check Orders có chuyến trong tương lai chưa giao, chặn nếu có.
A11: ▶ Template Row — copy khi thêm case mới
A12: L1-XX-[NN] | B12: [BC-TRUE | BC-FALSE | CC | EP-Valid | EP-Invalid | BVA-* | State-* | Guard-* | Concurrency | Idempotency | Atomicity] | C12: [Branch / condition / partition] | D12: [FT-xx AC/NAC/BV-xx; BR-xxx; NFR-xxx] | E12: P2 | F12: [Arrange: state + _mock.Setup(...)] | G12: service.Method(params) | H12: [result.Should().Be(...) / Throws / _mock.Verify(..., Times.Never)] | I12: No | J12: Not Run

Sheet WebhookLogService
A1: WebhookLogService | MỚI v2.1 | methods: LogReceivedAsync, MarkProcessedAsync, MarkFailedAsync, RetryAsync, SearchAsync | FT-03; BR-029; BR-049; NFR-SEC05
A2: HOW TO USE: (1) Đọc Introduction (2) Trace theo SRS v2 (Part 3 + RTW Sheet 3/6/7) (3) Cập nhật Status sau mỗi lần chạy dotnet test / vitest (4) Ghi Defect ID khi Fail
A4: Test ID | B4: Coverage Technique | C4: Covers (Decision/Condition) | D4: SRS Reference | E4: Priority | F4: Given (Precondition / Mock Setup) | G4: When (Input / Act) | H4: Then (Expected Output / Assert) | I4: Negative? | J4: Status | K4: Defect ID | L4: Notes | M4: Fix Status
A5: ▶ Block: Ghi nhận & đánh dấu | FT-03 AC-01; NAC-01; BR-049
A6: L1-WHL-01 | B6: EP-Valid | C6: Mọi callback đều được ghi log, kể cả callback bị từ chối | D6: FT-03 NAC-01; NFR-SEC05 | E6: P1 | F6: Callback SePay có chữ ký SAI | G6: webhookLogService.LogReceivedAsync(SePayWebhookDto payload) | H6: Trả Guid id của bản ghi log; Status = WebhookLogStatus.Received (0) Mọi callback đều được ghi log trước khi validate | I6: No | J6: Pass | M6: ✅ Pass (không đổi)
A7: L1-WHL-02 | B7: EP-Valid | C7: Đánh dấu đã xử lý -> lưu kết quả để trả lại cho lần gửi trùng | D7: FT-03 NAC-02; BR-029 | E7: P1 | F7: Log L1 Status=Received | G7: webhookLogService.MarkProcessedAsync(L1) | H7: Status = Processed (1) | I7: No | J7: Pass | M7: ✅ Pass (không đổi)
A8: L1-WHL-03 | B8: EP-Valid | C8: Đánh dấu thất bại -> tăng số lần thử, giữ nguyên lỗi | D8: BR-049; FT-09 AC-05 | E8: P1 | F8: Log L1 đã thất bại 1 lần (AttemptCount=1) | G8: webhookLogService.MarkFailedAsync(L1, exception) | H8: Status = Failed (2); AttemptCount tăng lên 2; nội dung exception được lưu | I8: No | J8: Pass | M8: ✅ Pass (không đổi)
A9: L1-WHL-04 | B9: EP-Valid | C9: Search lọc theo trạng thái/khoảng thời gian | D9: FT-03 SB; FT-09 AC-01 | E9: P2 | F9: 3 log: 1 Processed, 2 Failed | G9: webhookLogService.SearchAsync(WebhookLogQueryDto{Status:'Failed'}) | H9: Trả PagedResultDto<WebhookLogDto> đúng 2 bản ghi | I9: No | J9: Pass | M9: ✅ Pass (không đổi)
A10: ▶ Block: RetryAsync() | BR-029; BR-049
A11: L1-WHL-05 | B11: EP-Valid | C11: Retry callback thất bại -> xử lý lại đúng 1 lần | D11: BR-029 | E11: P1 | F11: Log L1 Status=Failed, đơn chưa Paid | G11: webhookLogService.RetryAsync(L1) | H11: Trả WebhookLogDto; xử lý lại bằng token ĐỌC TỪ CẤU HÌNH SERVER (không dùng token đã lưu) Nếu hợp lệ: đơn chuyển Paid đúng 1 lần | I11: No | J11: Pass | M11: ✅ Pass (không đổi)
A12: L1-WHL-06 | B12: Delegation-Guard | C12: Retry callback ĐÃ xử lý thành công -> không tạo giao dịch thứ 2 | D12: FT-03 NAC-02; BR-029 | E12: P1 | F12: Log L1 Status=Processed (đã xử lý xong) | G12: webhookLogService.RetryAsync(L1) | H12: Verify KHÔNG gọi xuống OrderService.ProcessSePayWebhookAsync lần nữa (delegation guard tại tầng log) Trả WebhookLogDto phản ánh kết quả gốc | I12: Yes | J12: Pass | M12: ✅ Pass (không đổi)
A13: L1-WHL-07 | B13: BVA-Max+1 | C13: Vượt số lần retry tối đa -> dừng và cảnh báo | D13: BR-049; FT-09 BV-03 | E13: P1 | F13: [Theory] AttemptCount = 4 / 5 / 6 (const WebhookLogService.MaxAttempts = 5) | G13: webhookLogService.RetryAsync(L1) | H13: AttemptCount=4: vẫn thử lại AttemptCount >= 5: Status = Abandoned (3), dừng thử lại + tạo cảnh báo | I13: Yes | J13: Pass | M13: ✅ Pass (không đổi)
A14: ▶ Template Row — copy khi thêm case mới
A15: L1-XX-[NN] | B15: [BC-TRUE | BC-FALSE | CC | EP-Valid | EP-Invalid | BVA-* | State-* | Guard-* | Concurrency | Idempotency | Atomicity] | C15: [Branch / condition / partition] | D15: [FT-xx AC/NAC/BV-xx; BR-xxx; NFR-xxx] | E15: P2 | F15: [Arrange: state + _mock.Setup(...)] | G15: service.Method(params) | H15: [result.Should().Be(...) / Throws / _mock.Verify(..., Times.Never)] | I15: No | J15: Not Run

Sheet AuditLogService
A1: AuditLogService | MỚI v2.1 | methods: LogAsync, SearchAsync, ExportCsvAsync | FT-09; BR-022; BR-048; NFR-SEC08
A2: HOW TO USE: (1) Đọc Introduction (2) Trace theo SRS v2 (Part 3 + RTW Sheet 3/6/7) (3) Cập nhật Status sau mỗi lần chạy dotnet test / vitest (4) Ghi Defect ID khi Fail
A4: Test ID | B4: Coverage Technique | C4: Covers (Decision/Condition) | D4: SRS Reference | E4: Priority | F4: Given (Precondition / Mock Setup) | G4: When (Input / Act) | H4: Then (Expected Output / Assert) | I4: Negative? | J4: Status | K4: Defect ID | L4: Notes | M4: Fix Status
A5: ▶ Block: LogAsync() | FT-09 AC-04; BR-022; BR-048
A6: L1-AUD-01 | B6: EP-Valid | C6: Ghi log đầy đủ actor, hành động, thực thể, thời điểm, before/after | D6: FT-09 AC-04; BR-022 | E6: P1 | F6: Thay đổi giá của sản phẩm P1 | G6: auditLogService.LogAsync(entity:'Product', action:'PriceChange', before, after, actorId) | H6: Bản ghi lưu đủ 5 thành phần; không thiếu trường bắt buộc | I6: No | J6: Pass | M6: ✅ Pass (không đổi)
A7: L1-AUD-02 | B7: EP-Invalid | C7: Thiếu actor hoặc thực thể -> từ chối ghi log rỗng nghĩa | D7: BR-022 | E7: P2 | F7: actorId = null | G7: auditLogService.LogAsync(entity:'Order', action:'Cancel', actorId:null) | H7: Từ chối / ghi rõ hệ thống là actor — không tạo bản ghi khuyết thông tin | I7: Yes | J7: Pass | M7: ✅ Pass (không đổi)
A8: L1-AUD-03 | B8: EP-Valid | C8: Log là APPEND-ONLY: không có API sửa/xoá | D8: FT-09 NAC-03; BR-048; NFR-SEC08 | E8: P1 | F8: Đã có bản ghi A1 | G8: Rà interface IAuditLogService + thử cập nhật entity qua context | H8: Không tồn tại phương thức Update/Delete Mọi nỗ lực sửa đều bị chặn | I8: Yes | J8: Pass | M8: ✅ Pass (không đổi)
A9: L1-AUD-04 | B9: EP-Valid | C9: PII trong log được mask | D9: NFR-SEC06 | E9: P1 | F9: Thay đổi hồ sơ chứa SĐT và MST | G9: auditLogService.LogAsync(... before/after chứa PII ...) | H9: Giá trị lưu đã mask (vd 0912***678); không lưu token/secret | I9: No | J9: Pass | M9: ✅ ĐÃ FIX SensitiveDataRedactor.cs mask PII (phone/MST dạng 0912***678), redact hoàn toàn secret/token; đã wire vào AuditLogService.cs:41-42.
A10: ▶ Block: SearchAsync() / ExportCsvAsync()
A11: L1-AUD-05 | B11: EP-Valid | C11: Search lọc theo thực thể, actor, khoảng thời gian | D11: FT-09 AC-04 | E11: P2 | F11: 10 bản ghi thuộc 3 thực thể | G11: auditLogService.SearchAsync(query{entity:'Order', from, to}) | H11: Chỉ trả bản ghi khớp bộ lọc | I11: No | J11: Pass | M11: ✅ Pass (không đổi)
A12: L1-AUD-06 | B12: EP-Valid | C12: Export CSV giữ nguyên nội dung và escape ký tự đặc biệt | D12: FT-09 AC-04 | E12: P2 | F12: Bản ghi có dấu phẩy và dấu ngoặc kép trong lý do | G12: auditLogService.ExportCsvAsync(query) | H12: CSV hợp lệ, không vỡ cột; nội dung khớp bản ghi gốc | I12: No | J12: Pass | M12: ✅ Pass (không đổi)
